Workbook
Name Print_Area: 'Nota Mes'!$C$1:$AE$52

Sheet Evaluación
B3: Bien | C3: 90
B4: Regular | C4: 85
B5: Mal | C5: 70
B6: Muy Mal
B8: Cantidad | C8: 26

Sheet Nota Mes
C1: Año | D1: 2026
C2: Mes | D2: ene
C5: Valores | D5: Parque Diversiones Pueblo Antiguo | E5: Avenida Escazú | F5: Terramall | G5: Food Court Parque Diversiones | H5: Oxígeno | I5: Real Cariari | J5: Guadalupe | K5: Real Alajuela | L5: Cartago | M5: Alajuela | N5: Multiplaza Curridabat | O5: Coronado | P5: San José | Q5: Práctiko | R5: Tibás | S5: Lincoln | T5: Multiplaza Escazú | U5: Santa Ana | V5: Curridabat | W5: Desamparados | X5: City Mall | Y5: Heredia | Z5: Sabana | AA5: San Francisco | AB5: Escazú | AC5: Pinares | AD5: Total general
B6: % | C6: Total Puntos | D6: 97 | E6: 93 | F6: 91 | G6: 91 | H6: 90 | I6: 89 | J6: 88 | K6: 87 | L6: 86 | M6: 86 | N6: 86 | O6: 85 | P6: 85 | Q6: 85 | R6: 84 | S6: 84 | T6: 83 | U6: 83 | V6: 82 | W6: 78 | X6: 77 | Y6: 76 | Z6: 74 | AA6: 74 | AB6: 73 | AC6: 72 | AD6: 83.807692
C7: Cantidad evaluaciones | D7: 1 | E7: 1 | F7: 1 | G7: 1 | H7: 1 | I7: 1 | J7: 1 | K7: 1 | L7: 1 | M7: 1 | N7: 1 | O7: 1 | P7: 1 | Q7: 1 | R7: 1 | S7: 1 | T7: 1 | U7: 1 | V7: 1 | W7: 1 | X7: 1 | Y7: 1 | Z7: 1 | AA7: 1 | AB7: 1 | AC7: 1 | AD7: 26
B8: =((AD8/MAX(D8:AC8))/Evaluación!$C$8)*100 -> 96.153846 | C8: Limpieza exteriores | D8: 2 | E8: 2 | F8: 2 | G8: 2 | H8: 2 | I8: 2 | J8: 2 | K8: 2 | L8: 2 | M8: 2 | N8: 2 | O8: 2 | P8: 2 | Q8: 2 | R8: 2 | S8: 2 | T8: 2 | U8: 2 | V8: 2 | W8: 2 | X8: 2 | Y8: 2 | Z8: 2 | AA8: 2 | AB8: 2 | AC8: 0 | AD8: 50
B9: =((AD9/MAX(D9:AC9))/Evaluación!$C$8)*100 -> 65.384615 | C9: Áreas de Salón e Intermedio | D9: 2 | E9: 2 | F9: 2 | G9: 2 | H9: 0 | I9: 2 | J9: 2 | K9: 0 | L9: 2 | M9: 0 | N9: 2 | O9: 2 | P9: 2 | Q9: 0 | R9: 2 | S9: 0 | T9: 0 | U9: 0 | V9: 2 | W9: 2 | X9: 0 | Y9: 2 | Z9: 2 | AA9: 0 | AB9: 2 | AC9: 2 | AD9: 34
B10: =((AD10/MAX(D10:AC10))/Evaluación!$C$8)*100 -> 100 | C10: Baño Invitados | D10: 2 | E10: 2 | F10: 2 | G10: 2 | H10: 2 | I10: 2 | J10: 2 | K10: 2 | L10: 2 | M10: 2 | N10: 2 | O10: 2 | P10: 2 | Q10: 2 | R10: 2 | S10: 2 | T10: 2 | U10: 2 | V10: 2 | W10: 2 | X10: 2 | Y10: 2 | Z10: 2 | AA10: 2 | AB10: 2 | AC10: 2 | AD10: 52
B11: =((AD11/MAX(D11:AC11))/Evaluación!$C$8)*100 -> 96.153846 | C11: Documentación Legal | D11: 3 | E11: 3 | F11: 3 | G11: 3 | H11: 3 | I11: 3 | J11: 3 | K11: 3 | L11: 3 | M11: 3 | N11: 3 | O11: 3 | P11: 3 | Q11: 3 | R11: 3 | S11: 3 | T11: 3 | U11: 0 | V11: 3 | W11: 3 | X11: 3 | Y11: 3 | Z11: 3 | AA11: 3 | AB11: 3 | AC11: 3 | AD11: 75
B12: =((AD12/MAX(D12:AC12))/Evaluación!$C$8)*100 -> 100 | C12: Urna de Postres | D12: 2 | E12: 2 | F12: 2 | G12: 2 | H12: 2 | I12: 2 | J12: 2 | K12: 2 | L12: 2 | M12: 2 | N12: 2 | O12: 2 | P12: 2 | Q12: 2 | R12: 2 | S12: 2 | T12: 2 | U12: 2 | V12: 2 | W12: 2 | X12: 2 | Y12: 2 | Z12: 2 | AA12: 2 | AB12: 2 | AC12: 2 | AD12: 52
B13: =((AD13/MAX(D13:AC13))/Evaluación!$C$8)*100 -> 100 | C13: Área Serv. Exprés | D13: 2 | E13: 2 | F13: 2 | G13: 2 | H13: 2 | I13: 2 | J13: 2 | K13: 2 | L13: 2 | M13: 2 | N13: 2 | O13: 2 | P13: 2 | Q13: 2 | R13: 2 | S13: 2 | T13: 2 | U13: 2 | V13: 2 | W13: 2 | X13: 2 | Y13: 2 | Z13: 2 | AA13: 2 | AB13: 2 | AC13: 2 | AD13: 52
B14: =((AD14/MAX(D14:AC14))/Evaluación!$C$8)*100 -> 100 | C14: Personal de servicio Exprés | D14: 2 | E14: 2 | F14: 2 | G14: 2 | H14: 2 | I14: 2 | J14: 2 | K14: 2 | L14: 2 | M14: 2 | N14: 2 | O14: 2 | P14: 2 | Q14: 2 | R14: 2 | S14: 2 | T14: 2 | U14: 2 | V14: 2 | W14: 2 | X14: 2 | Y14: 2 | Z14: 2 | AA14: 2 | AB14: 2 | AC14: 2 | AD14: 52
B15: =((AD15/MAX(D15:AC15))/Evaluación!$C$8)*100 -> 100 | C15: PCC Maneno Term. | D15: 3 | E15: 3 | F15: 3 | G15: 3 | H15: 3 | I15: 3 | J15: 3 | K15: 3 | L15: 3 | M15: 3 | N15: 3 | O15: 3 | P15: 3 | Q15: 3 | R15: 3 | S15: 3 | T15: 3 | U15: 3 | V15: 3 | W15: 3 | X15: 3 | Y15: 3 | Z15: 3 | AA15: 3 | AB15: 3 | AC15: 3 | AD15: 78
B16: =((AD16/MAX(D16:AC16))/Evaluación!$C$8)*100 -> 88.461538 | C16: Puesto Lavado | D16: 3 | E16: 3 | F16: 3 | G16: 3 | H16: 3 | I16: 3 | J16: 3 | K16: 3 | L16: 3 | M16: 3 | N16: 3 | O16: 0 | P16: 3 | Q16: 3 | R16: 3 | S16: 0 | T16: 3 | U16: 3 | V16: 3 | W16: 3 | X16: 0 | Y16: 3 | Z16: 3 | AA16: 3 | AB16: 3 | AC16: 3 | AD16: 69 | AG16: s
B17: =((AD17/MAX(D17:AC17))/Evaluación!$C$8)*100 -> 76.923077 | C17: Puesto Lavado Manipuladores | D17: 2 | E17: 0 | F17: 2 | G17: 2 | H17: 2 | I17: 2 | J17: 2 | K17: 2 | L17: 2 | M17: 2 | N17: 2 | O17: 2 | P17: 0 | Q17: 2 | R17: 2 | S17: 2 | T17: 2 | U17: 2 | V17: 0 | W17: 2 | X17: 2 | Y17: 0 | Z17: 0 | AA17: 2 | AB17: 0 | AC17: 2 | AD17: 40
B18: =((AD18/MAX(D18:AC18))/Evaluación!$C$8)*100 -> 96.153846 | C18: Áreas de pilas rejilla | D18: 2 | E18: 2 | F18: 2 | G18: 2 | H18: 2 | I18: 2 | J18: 2 | K18: 2 | L18: 2 | M18: 2 | N18: 2 | O18: 2 | P18: 2 | Q18: 2 | R18: 2 | S18: 2 | T18: 2 | U18: 2 | V18: 2 | W18: 2 | X18: 2 | Y18: 2 | Z18: 2 | AA18: 0 | AB18: 2 | AC18: 2 | AD18: 50
B19: =((AD19/MAX(D19:AC19))/Evaluación!$C$8)*100 -> 61.538462 | C19: Área de pilas limpieza | D19: 2 | E19: 2 | F19: 2 | G19: 2 | H19: 2 | I19: 2 | J19: 2 | K19: 0 | L19: 2 | M19: 0 | N19: 2 | O19: 2 | P19: 2 | Q19: 0 | R19: 2 | S19: 2 | T19: 0 | U19: 0 | V19: 2 | W19: 0 | X19: 0 | Y19: 2 | Z19: 0 | AA19: 0 | AB19: 0 | AC19: 2 | AD19: 32
B20: =((AD20/MAX(D20:AC20))/Evaluación!$C$8)*100 -> 84.615385 | C20: Área de pilas delantal | D20: 2 | E20: 0 | F20: 2 | G20: 0 | H20: 2 | I20: 2 | J20: 0 | K20: 2 | L20: 2 | M20: 2 | N20: 2 | O20: 2 | P20: 2 | Q20: 2 | R20: 2 | S20: 2 | T20: 2 | U20: 2 | V20: 2 | W20: 2 | X20: 0 | Y20: 2 | Z20: 2 | AA20: 2 | AB20: 2 | AC20: 2 | AD20: 44
B21: =((AD21/MAX(D21:AC21))/Evaluación!$C$8)*100 -> 100 | C21: Área de pilas químicos | D21: 1 | E21: 1 | F21: 1 | G21: 1 | H21: 1 | I21: 1 | J21: 1 | K21: 1 | L21: 1 | M21: 1 | N21: 1 | O21: 1 | P21: 1 | Q21: 1 | R21: 1 | S21: 1 | T21: 1 | U21: 1 | V21: 1 | W21: 1 | X21: 1 | Y21: 1 | Z21: 1 | AA21: 1 | AB21: 1 | AC21: 1 | AD21: 26
B22: =((AD22/MAX(D22:AC22))/Evaluación!$C$8)*100 -> 100 | C22: Área de cocina Limpieza | D22: 1 | E22: 1 | F22: 1 | G22: 1 | H22: 1 | I22: 1 | J22: 1 | K22: 1 | L22: 1 | M22: 1 | N22: 1 | O22: 1 | P22: 1 | Q22: 1 | R22: 1 | S22: 1 | T22: 1 | U22: 1 | V22: 1 | W22: 1 | X22: 1 | Y22: 1 | Z22: 1 | AA22: 1 | AB22: 1 | AC22: 1 | AD22: 26
B23: =((AD23/MAX(D23:AC23))/Evaluación!$C$8)*100 -> 88.461538 | C23: Pañitos y utencilios | D23: 2 | E23: 2 | F23: 2 | G23: 0 | H23: 2 | I23: 2 | J23: 2 | K23: 2 | L23: 0 | M23: 2 | N23: 2 | O23: 2 | P23: 2 | Q23: 2 | R23: 2 | S23: 2 | T23: 2 | U23: 2 | V23: 2 | W23: 2 | X23: 2 | Y23: 2 | Z23: 2 | AA23: 0 | AB23: 2 | AC23: 2 | AD23: 46
B24: =((AD24/MAX(D24:AC24))/Evaluación!$C$8)*100 -> 61.538462 | C24: Equipos eléctricos | D24: 3 | E24: 3 | F24: 3 | G24: 3 | H24: 3 | I24: 3 | J24: 0 | K24: 0 | L24: 0 | M24: 3 | N24: 3 | O24: 3 | P24: 3 | Q24: 3 | R24: 0 | S24: 3 | T24: 3 | U24: 3 | V24: 0 | W24: 3 | X24: 3 | Y24: 0 | Z24: 0 | AA24: 0 | AB24: 0 | AC24: 0 | AD24: 48
B25: =((AD25/MAX(D25:AC25))/Evaluación!$C$8)*100 -> 42.307692 | C25: Equipos de almacenamiento | D25: 0 | E25: 3 | F25: 0 | G25: 3 | H25: 0 | I25: 3 | J25: 0 | K25: 0 | L25: 3 | M25: 0 | N25: 0 | O25: 0 | P25: 3 | Q25: 0 | R25: 3 | S25: 0 | T25: 0 | U25: 0 | V25: 3 | W25: 0 | X25: 0 | Y25: 3 | Z25: 3 | AA25: 3 | AB25: 0 | AC25: 3 | AD25: 33
B26: =((AD26/MAX(D26:AC26))/Evaluación!$C$8)*100 -> 23.076923 | C26: Equipos de Gas | D26: 3 | E26: 0 | F26: 3 | G26: 0 | H26: 0 | I26: 0 | J26: 3 | K26: 0 | L26: 0 | M26: 0 | N26: 0 | O26: 0 | P26: 0 | Q26: 3 | R26: 0 | S26: 3 | T26: 3 | U26: 0 | V26: 0 | W26: 0 | X26: 0 | Y26: 0 | Z26: 0 | AA26: 0 | AB26: 0 | AC26: 0 | AD26: 18
B27: =((AD27/MAX(D27:AC27))/Evaluación!$C$8)*100 -> 69.230769 | C27: Holding Gabinet Limpieza | D27: 2 | E27: 2 | F27: 2 | G27: 2 | H27: 2 | I27: 2 | J27: 2 | K27: 2 | L27: 0 | M27: 2 | N27: 0 | O27: 2 | P27: 2 | Q27: 2 | R27: 0 | S27: 2 | T27: 2 | U27: 2 | V27: 0 | W27: 0 | X27: 2 | Y27: 2 | Z27: 0 | AA27: 2 | AB27: 0 | AC27: 0 | AD27: 36
B28: =((AD28/MAX(D28:AC28))/Evaluación!$C$8)*100 -> 73.076923 | C28: Almacenamiento Alimentos | D28: 2 | E28: 2 | F28: 2 | G28: 0 | H28: 2 | I28: 2 | J28: 2 | K28: 2 | L28: 0 | M28: 0 | N28: 2 | O28: 2 | P28: 2 | Q28: 2 | R28: 0 | S28: 2 | T28: 0 | U28: 2 | V28: 2 | W28: 0 | X28: 0 | Y28: 2 | Z28: 2 | AA28: 2 | AB28: 2 | AC28: 2 | AD28: 38
... B52: =((AD52/MAX(D52:AC52))/Evaluación!$C$8)*100 -> 73.076923 | C52: Registro de cocción de pollo | D52: 4 | E52: 4 | F52: 4 | G52: 4 | H52: 4 | I52: 4 | J52: 4 | K52: 4 | L52: 4 | M52: 4 | N52: 4 | O52: 0 | P52: 4 | Q52: 0 | R52: 4 | S52: 0 | T52: 0 | U52: 4 | V52: 0 | W52: 4 | X52: 4 | Y52: 4 | Z52: 4 | AA52: 0 | AB52: 4 | AC52: 0 | AD52: 76

Sheet Datos
A1: ID | B1: Hora de inicio | C1: Hora de finalización | D1: Correo electrónico | E1: Nombre | F1: Total de puntos | G1: Comentarios del cuestionario | H1: Restaurante | I1: Puntos: Restaurante | J1: Comentarios: Restaurante | K1: Fecha de la evaluación | L1: Puntos: Fecha de la evaluación | M1: Comentarios: Fecha de la evaluación | N1: Nombre del administrativo a cargo del turno: | O1: Puntos: Nombre del administrativo a cargo del turno: | P1: Comentarios: Nombre del administrativo a cargo del turno: | Q1: Nombre del evaluador: | R1: Puntos: Nombre del evaluador: | S1: Comentarios: Nombre del evaluador: | T1: LIMPIEZA DE EXTERIORES: Exteriores del establecimiento limpios, ordenados. Jardín recortado, plantas en buen estado. | U1: Puntos: LIMPIEZA DE EXTERIORES: Exteriores del establecimiento limpios, ordenados. Jardín recortado, plantas en buen estado. | V1: Comentarios: LIMPIEZA DE EXTERIORES: Exteriores del establecimiento limpios, ordenados. Jardín recortado, plantas en buen estado. | W1: Comentarios pregunta 5: | X1: Puntos: Comentarios pregunta 5: | Y1: Comentarios: Comentarios pregunta 5: | Z1: AREAS DE SALON EN INTERMEDIO: Las áreas de salón e intermedio se encuentra en optimas condiciones de orden y limpieza. | AA1: Puntos: AREAS DE SALON EN INTERMEDIO: Las áreas de salón e intermedio se encuentra en optimas condiciones de orden y limpieza. | AB1: Comentarios: AREAS DE SALON EN INTERMEDIO: Las áreas de salón e intermedio se encuentra en optimas condiciones de orden y limpieza. | AC1: Comentarios pregunta #7: | AD1: Puntos: Comentarios pregunta #7: | AE1: Comentarios: Comentarios pregunta #7: | AF1: BAÑO DE CLIENTES: Baño de clientes en buenas condiciones: Limpio, ordenado y con buen olor. *Equipado con: puesto de lavado de manos (agua, jabón líquido, secador de aire caliente), papel higiénic... | AG1: Puntos: BAÑO DE CLIENTES: Baño de clientes en buenas condiciones: Limpio, ordenado y con buen olor. *Equipado con: puesto de lavado de manos (agua, jabón líquido, secador de aire caliente), papel higiénic... | AH1: Comentarios: BAÑO DE CLIENTES: Baño de clientes en buenas condiciones: Limpio, ordenado y con buen olor. *Equipado con: puesto de lavado de manos (agua, jabón líquido, secador de aire caliente), papel higiénic... | AI1: Comentarios pregunta #9: | AJ1: Puntos: Comentarios pregunta #9: | AK1: Comentarios: Comentarios pregunta #9: | AL1: DOCUMENTACION LEGAL: Permiso sanitario de funcionamiento (PSF), Patente Comercial y de Licores vigentes y colocadas en un lugar visible. Mínimo el 95% de los colaboradores cumplen con el carnet de... | AM1: Puntos: DOCUMENTACION LEGAL: Permiso sanitario de funcionamiento (PSF), Patente Comercial y de Licores vigentes y colocadas en un lugar visible. Mínimo el 95% de los colaboradores cumplen con el carnet de... | AN1: Comentarios: DOCUMENTACION LEGAL: Permiso sanitario de funcionamiento (PSF), Patente Comercial y de Licores vigentes y colocadas en un lugar visible. Mínimo el 95% de los colaboradores cumplen con el carnet de... | AO1: Comentarios pregunta #11: | AP1: Puntos: Comentarios pregunta #11: | AQ1: Comentarios: Comentarios pregunta #11: | AR1: URNA DE POSTRES: La urna de postres se encuentra bien presentada, sin faltande de postres, los mismos cumplen la con la presentación establecida según el perfil de producto, sin deterioro, deshidr... | AS1: Puntos: URNA DE POSTRES: La urna de postres se encuentra bien presentada, sin faltande de postres, los mismos cumplen la con la presentación establecida según el perfil de producto, sin deterioro, deshidr... | AT1: Comentarios: URNA DE POSTRES: La urna de postres se encuentra bien presentada, sin faltande de postres, los mismos cumplen la con la presentación establecida según el perfil de producto, sin deterioro, deshidr... | AU1: Comentarios pregunta #13: | AV1: Puntos: Comentarios pregunta #13: | AW1: Comentarios: Comentarios pregunta #13: | AX1: AREA DE SERVICIO EXPRESS: El área de servicio express se encuentra limpia, ordenada, bolsos de transportar alimentos limpios y en buenas condiciones. No se colocan en el piso. | AY1: Puntos: AREA DE SERVICIO EXPRESS: El área de servicio express se encuentra limpia, ordenada, bolsos de transportar alimentos limpios y en buenas condiciones. No se colocan en el piso. | AZ1: Comentarios: AREA DE SERVICIO EXPRESS: El área de servicio express se encuentra limpia, ordenada, bolsos de transportar alimentos limpios y en buenas condiciones. No se colocan en el piso. | BA1: Comentarios pregunta #15: | BB1: Puntos: Comentarios pregunta #15: | BC1: Comentarios: Comentarios pregunta #15: | BD1: PERSONAL DE SERVICIO EXPRESS: El personal de mensajería cuenta con uniforme limpio y buena presentación personal, BPM, normas internas de Rosti (maquillaje, joyas, barba, uso de redecilla, uñas c... | BE1: Puntos: PERSONAL DE SERVICIO EXPRESS: El personal de mensajería cuenta con uniforme limpio y buena presentación personal, BPM, normas internas de Rosti (maquillaje, joyas, barba, uso de redecilla, uñas c... | BF1: Comentarios: PERSONAL DE SERVICIO EXPRESS: El personal de mensajería cuenta con uniforme limpio y buena presentación personal, BPM, normas internas de Rosti (maquillaje, joyas, barba, uso de redecilla, uñas c... | BG1: Comentarios pregunta #17: | BH1: Puntos: Comentarios pregunta #17: | BI1: Comentarios: Comentarios pregunta #17: | BJ1: PCC MANEJO DE TERMÓMETRO: Termómetros se mantienen disponibles, limpios, en buen estado y con escala de acuerdo a su uso; cuenten con opción de lectura de grados Centígrados y grados Fahrenheit ... | BK1: Puntos: PCC MANEJO DE TERMÓMETRO: Termómetros se mantienen disponibles, limpios, en buen estado y con escala de acuerdo a su uso; cuenten con opción de lectura de grados Centígrados y grados Fahrenheit ... | BL1: Comentarios: PCC MANEJO DE TERMÓMETRO: Termómetros se mantienen disponibles, limpios, en buen estado y con escala de acuerdo a su uso; cuenten con opción de lectura de grados Centígrados y grados Fahrenheit ... | BM1: Comentarios pregunta #19: | BN1: Puntos: Comentarios pregunta #19: | BO1: Comentarios: Comentarios pregunta #19: | BP1: PUESTO DE LAVADO: El puesto de lavado de manos se encuentra debidamente equipado (agua, jabón desinfectante, basurero y papel toalla) y con las adecuadas condiciones de limpieza. Es de uso exclusi... | BQ1: Puntos: PUESTO DE LAVADO: El puesto de lavado de manos se encuentra debidamente equipado (agua, jabón desinfectante, basurero y papel toalla) y con las adecuadas condiciones de limpieza. Es de uso exclusi... | BR1: Comentarios: PUESTO DE LAVADO: El puesto de lavado de manos se encuentra debidamente equipado (agua, jabón desinfectante, basurero y papel toalla) y con las adecuadas condiciones de limpieza. Es de uso exclusi... | BS1: Comentarios pregunta #21: | BT1: Puntos: Comentarios pregunta #21: | BU1: Comentarios: Comentarios pregunta #21: | BV1: PUESTO DE LAVADO: Los manipuladores de alimentos se lavan sus manos cada vez que se puedan haber contaminado o en cuanto suene el timer, siguiendo el procedimiento correcto. Alarma sonora (timer) ... | BW1: Puntos: PUESTO DE LAVADO: Los manipuladores de alimentos se lavan sus manos cada vez que se puedan haber contaminado o en cuanto suene el timer, siguiendo el procedimiento correcto. Alarma sonora (timer) ... | BX1: Comentarios: PUESTO DE LAVADO: Los manipuladores de alimentos se lavan sus manos cada vez que se puedan haber contaminado o en cuanto suene el timer, siguiendo el procedimiento correcto. Alarma sonora (timer) ... | BY1: Comentarios pregunta #23: | BZ1: Puntos: Comentarios pregunta #23: | CA1: Comentarios: Comentarios pregunta #23: | CB1: AREA DE PILAS: Pilas cuentan con rejillas y sistema de retención de agua para lavado por inmersión. Tren de lavado funcionando de la manera correcta (lavado-enjuague- sanitización). Cumplen con mé... | CC1: Puntos: AREA DE PILAS: Pilas cuentan con rejillas y sistema de retención de agua para lavado por inmersión. Tren de lavado funcionando de la manera correcta (lavado-enjuague- sanitización). Cumplen con mé... | CD1: Comentarios: AREA DE PILAS: Pilas cuentan con rejillas y sistema de retención de agua para lavado por inmersión. Tren de lavado funcionando de la manera correcta (lavado-enjuague- sanitización). Cumplen con mé... | CE1: Comentarios pregunta # 25: | CF1: Puntos: Comentarios pregunta # 25: | CG1: Comentarios: Comentarios pregunta # 25: | CH1: AREA DE PILAS: limpia y ordenada, además no se identifica vajilla de la noche anterior sucia o con residuos en el área. Si el tiempo no permite realizar el proceso de lavado de la vajilla la noch... | CI1: Puntos: AREA DE PILAS: limpia y ordenada, además no se identifica vajilla de la noche anterior sucia o con residuos en el área. Si el tiempo no permite realizar el proceso de lavado de la vajilla la noch... | CJ1: Comentarios: AREA DE PILAS: limpia y ordenada, además no se identifica vajilla de la noche anterior sucia o con residuos en el área. Si el tiempo no permite realizar el proceso de lavado de la vajilla la noch... | CK1: Comentarios pregunta #27: | CL1: Puntos: Comentarios pregunta #27: | CM1: Comentarios: Comentarios pregunta #27: | CN1: AREA DE PILAS: Delantal blanco limpio y en buen estado. Canastas de escurrir vajilla limpias y en buen estado. Sin daños o presencia de hongos. El colaborador retira los residuos sólidos de la va... | CO1: Puntos: AREA DE PILAS: Delantal blanco limpio y en buen estado. Canastas de escurrir vajilla limpias y en buen estado. Sin daños o presencia de hongos. El colaborador retira los residuos sólidos de la va... | CP1: Comentarios: AREA DE PILAS: Delantal blanco limpio y en buen estado. Canastas de escurrir vajilla limpias y en buen estado. Sin daños o presencia de hongos. El colaborador retira los residuos sólidos de la va... | CQ1: Comentarios pregunta #29: | CR1: Puntos: Comentarios pregunta #29: | CS1: Comentarios: Comentarios pregunta #29: | CT1: AREA DE PILAS: Químicos en uso en pilas sin exceso de suciedad o material orgánico (grasa o alimentos). Sanitizante concentración mínima 200 ppm. | CU1: Puntos: AREA DE PILAS: Químicos en uso en pilas sin exceso de suciedad o material orgánico (grasa o alimentos). Sanitizante concentración mínima 200 ppm. | CV1: Comentarios: AREA DE PILAS: Químicos en uso en pilas sin exceso de suciedad o material orgánico (grasa o alimentos). Sanitizante concentración mínima 200 ppm. | CW1: Comentarios pregunta #31 | CX1: Puntos: Comentarios pregunta #31 | CY1: Comentarios: Comentarios pregunta #31 | CZ1: AREA DE COCINA: limpia y ordenada. No hay exceso de grasa o humedad en el piso. Muebles y repisas para almacenamiento con condiciones de limpieza adecuadas. | DA1: Puntos: AREA DE COCINA: limpia y ordenada. No hay exceso de grasa o humedad en el piso. Muebles y repisas para almacenamiento con condiciones de limpieza adecuadas. | DB1: Comentarios: AREA DE COCINA: limpia y ordenada. No hay exceso de grasa o humedad en el piso. Muebles y repisas para almacenamiento con condiciones de limpieza adecuadas. | DC1: Comentarios pregunta #33: | DD1: Puntos: Comentarios pregunta #33: | DE1: Comentarios: Comentarios pregunta #33: | DF1: PAÑITOS Y UTENSILIOS EN SOLUCIÓN SANITIZANTE: Los utensilios y pañitos que estan en uso, se mantienen en solución desinfectante de amonio cuaternario (mínimo 200 ppm.) El contenido de los recipi... | DG1: Puntos: PAÑITOS Y UTENSILIOS EN SOLUCIÓN SANITIZANTE: Los utensilios y pañitos que estan en uso, se mantienen en solución desinfectante de amonio cuaternario (mínimo 200 ppm.) El contenido de los recipi... | DH1: Comentarios: PAÑITOS Y UTENSILIOS EN SOLUCIÓN SANITIZANTE: Los utensilios y pañitos que estan en uso, se mantienen en solución desinfectante de amonio cuaternario (mínimo 200 ppm.) El contenido de los recipi... | DI1: Comentarios pregunta #35: | DJ1: Puntos: Comentarios pregunta #35: | DK1: Comentarios: Comentarios pregunta #35: | DL1: EQUIPOS ELECTRICOS: Limpios, en buen estado y funcionando correctamente (incluir abanicos) | DM1: Puntos: EQUIPOS ELECTRICOS: Limpios, en buen estado y funcionando correctamente (incluir abanicos) | DN1: Comentarios: EQUIPOS ELECTRICOS: Limpios, en buen estado y funcionando correctamente (incluir abanicos) | DO1: Comentarios pregunta #37: | DP1: Puntos: Comentarios pregunta #37: | DQ1: Comentarios: Comentarios pregunta #37: | DR1: EQUIPOS ALMACENAMIENTO FRIO: Limpios, en buen estado y funcionando correctamente. Las rejillas no se encuentran oxidadas. Cuentan con los empaques en buen estado. (Cámaras de refrigeración y cong... | DS1: Puntos: EQUIPOS ALMACENAMIENTO FRIO: Limpios, en buen estado y funcionando correctamente. Las rejillas no se encuentran oxidadas. Cuentan con los empaques en buen estado. (Cámaras de refrigeración y cong... | DT1: Comentarios: EQUIPOS ALMACENAMIENTO FRIO: Limpios, en buen estado y funcionando correctamente. Las rejillas no se encuentran oxidadas. Cuentan con los empaques en buen estado. (Cámaras de refrigeración y cong... | DU1: Comentarios pregunta #39: | DV1: Puntos: Comentarios pregunta #39: | DW1: Comentarios: Comentarios pregunta #39: | DX1: EQUIPOS DE GAS: Limpios, en buen estado y funcionando correctamente. El color de la llama es azul y no genera hollín. (freidores, plancha, olla arrocerra, horno, hornillón). Canastas de los freido... | DY1: Puntos: EQUIPOS DE GAS: Limpios, en buen estado y funcionando correctamente. El color de la llama es azul y no genera hollín. (freidores, plancha, olla arrocerra, horno, hornillón). Canastas de los freido... | DZ1: Comentarios: EQUIPOS DE GAS: Limpios, en buen estado y funcionando correctamente. El color de la llama es azul y no genera hollín. (freidores, plancha, olla arrocerra, horno, hornillón). Canastas de los freido... | EA1: Comentarios pregunta #41: | EB1: Puntos: Comentarios pregunta #41: | EC1: Comentarios: Comentarios pregunta #41: | ED1: HOLDING CABINET: Equipo limpio y en buen estado. Empaques en buen estado. Bandeja con agua para mantener la humedad del producto. | EE1: Puntos: HOLDING CABINET: Equipo limpio y en buen estado. Empaques en buen estado. Bandeja con agua para mantener la humedad del producto. | EF1: Comentarios: HOLDING CABINET: Equipo limpio y en buen estado. Empaques en buen estado. Bandeja con agua para mantener la humedad del producto. | EG1: Comentarios pregunta #43: | EH1: Puntos: Comentarios pregunta #43: | EI1: Comentarios: Comentarios pregunta #43: | EJ1: ALMACENAMIENTO DE LOS ALIMENTOS: Los alimentos deben mantenerse correctamente fechados y cubiertos (tapa o plástico adhesivo). Protegidos de contaminantes. Albahaca se mantiene en agua fresca, no ... | EK1: Puntos: ALMACENAMIENTO DE LOS ALIMENTOS: Los alimentos deben mantenerse correctamente fechados y cubiertos (tapa o plástico adhesivo). Protegidos de contaminantes. Albahaca se mantiene en agua fresca, no ... | EL1: Comentarios: ALMACENAMIENTO DE LOS ALIMENTOS: Los alimentos deben mantenerse correctamente fechados y cubiertos (tapa o plástico adhesivo). Protegidos de contaminantes. Albahaca se mantiene en agua fresca, no ... | EM1: Comentarios pregunta #45: | EN1: Puntos: Comentarios pregunta #45: | EO1: Comentarios: Comentarios pregunta #45: | EP1: VIDA UTIL Y ROTACION DE LOS ALIMENTOS: Se respeta la vida útil de todas las materias primas y productos preparados así como la rotación de los mismos cumpliendo con el método PEPS | EQ1: Puntos: VIDA UTIL Y ROTACION DE LOS ALIMENTOS: Se respeta la vida útil de todas las materias primas y productos preparados así como la rotación de los mismos cumpliendo con el método PEPS | ER1: Comentarios: VIDA UTIL Y ROTACION DE LOS ALIMENTOS: Se respeta la vida útil de todas las materias primas y productos preparados así como la rotación de los mismos cumpliendo con el método PEPS | ES1: Comentarios pregunta #47: | ET1: Puntos: Comentarios pregunta #47: | EU1: Comentarios: Comentarios pregunta #47: | EV1: ACEITE DE FREIDOR: temperatura 335C-350 C, sin humear y calidad correcta. Llenado correcto, no debe estar menos del límite mínimo ni más del límite máximo. | EW1: Puntos: ACEITE DE FREIDOR: temperatura 335C-350 C, sin humear y calidad correcta. Llenado correcto, no debe estar menos del límite mínimo ni más del límite máximo. | EX1: Comentarios: ACEITE DE FREIDOR: temperatura 335C-350 C, sin humear y calidad correcta. Llenado correcto, no debe estar menos del límite mínimo ni más del límite máximo. | EY1: Comentarios pregunta #49: | EZ1: Puntos: Comentarios pregunta #49: | FA1: Comentarios: Comentarios pregunta #49: | FB1: MANEJO DE POLLO CRUDO EN ZONA DEL FREIDOR: Se hace uso de la pinza amarilla o guantes para su manipulaciòn. El producto (pollo), se encuentra tapado para evitar deshidratación y contaminación. | FC1: Puntos: MANEJO DE POLLO CRUDO EN ZONA DEL FREIDOR: Se hace uso de la pinza amarilla o guantes para su manipulaciòn. El producto (pollo), se encuentra tapado para evitar deshidratación y contaminación. | FD1: Comentarios: MANEJO DE POLLO CRUDO EN ZONA DEL FREIDOR: Se hace uso de la pinza amarilla o guantes para su manipulaciòn. El producto (pollo), se encuentra tapado para evitar deshidratación y contaminación. | FE1: Comentarios pregunta #51: | FF1: Puntos: Comentarios pregunta #51: | FG1: Comentarios: Comentarios pregunta #51: | FH1: MANEJO CORRECTO DE LOS ALIMENTOS Y DESCONGELACIÓN: Los alimentos no se mantienen dentro de la zona de peligro (5°C a 60°C). Los alimentos congelados se descongelan siguiendo los procedimientos apr... | FI1: Puntos: MANEJO CORRECTO DE LOS ALIMENTOS Y DESCONGELACIÓN: Los alimentos no se mantienen dentro de la zona de peligro (5°C a 60°C). Los alimentos congelados se descongelan siguiendo los procedimientos apr... | FJ1: Comentarios: MANEJO CORRECTO DE LOS ALIMENTOS Y DESCONGELACIÓN: Los alimentos no se mantienen dentro de la zona de peligro (5°C a 60°C). Los alimentos congelados se descongelan siguiendo los procedimientos apr... | FK1: Comentarios pregunta #53: | FL1: Puntos: Comentarios pregunta #53: | FM1: Comentarios: Comentarios pregunta #53: | FN1: PROCESO DE ENFRIAMIENTO: Los alimentos sobrantes se enfrían siguiendo los procedimientos establecidos. | FO1: Puntos: PROCESO DE ENFRIAMIENTO: Los alimentos sobrantes se enfrían siguiendo los procedimientos establecidos. | FP1: Comentarios: PROCESO DE ENFRIAMIENTO: Los alimentos sobrantes se enfrían siguiendo los procedimientos establecidos. | FQ1: Comentarios pregunta #55: | FR1: Puntos: Comentarios pregunta #55: | FS1: Comentarios: Comentarios pregunta #55: | FT1: RECALENTAMIENTO Y MANTENIMIENTO DE LOS ALIMENTOS: el alimento debe alcanzar una temperatura mínima de 74°C al centro o en su parte más gruesa por 15 segundos posteriormente mantenerse a una tem... | FU1: Puntos: RECALENTAMIENTO Y MANTENIMIENTO DE LOS ALIMENTOS: el alimento debe alcanzar una temperatura mínima de 74°C al centro o en su parte más gruesa por 15 segundos posteriormente mantenerse a una tem... | FV1: Comentarios: RECALENTAMIENTO Y MANTENIMIENTO DE LOS ALIMENTOS: el alimento debe alcanzar una temperatura mínima de 74°C al centro o en su parte más gruesa por 15 segundos posteriormente mantenerse a una tem... | FW1: Comentarios pregunta #57: | FX1: Puntos: Comentarios pregunta #57: | FY1: Comentarios: Comentarios pregunta #57: | FZ1: BASUREROS: Basureros internos se deben mantener limpios, sin mal olor, bolsa ajustada, los basureros de mayor uso deben de contar al menos con tapa reducida. | GA1: Puntos: BASUREROS: Basureros internos se deben mantener limpios, sin mal olor, bolsa ajustada, los basureros de mayor uso deben de contar al menos con tapa reducida. | GB1: Comentarios: BASUREROS: Basureros internos se deben mantener limpios, sin mal olor, bolsa ajustada, los basureros de mayor uso deben de contar al menos con tapa reducida. | GC1: Comentarios pregunta #59: | GD1: Puntos: Comentarios pregunta #59: | GE1: Comentarios: Comentarios pregunta #59: | GF1: PROCEDIMIENTO DE REVISIÓN DE LECHUGA: Se cumple con la revisión de la lechuga hoja por hoja antes del proceso de corte con el fin de identificar algún posible cuerpo extraño (insecto). En caso de ... | GG1: Puntos: PROCEDIMIENTO DE REVISIÓN DE LECHUGA: Se cumple con la revisión de la lechuga hoja por hoja antes del proceso de corte con el fin de identificar algún posible cuerpo extraño (insecto). En caso de ... | GH1: Comentarios: PROCEDIMIENTO DE REVISIÓN DE LECHUGA: Se cumple con la revisión de la lechuga hoja por hoja antes del proceso de corte con el fin de identificar algún posible cuerpo extraño (insecto). En caso de ... | GI1: Comentarios pregunta #61: | GJ1: Puntos: Comentarios pregunta #61: | GK1: Comentarios: Comentarios pregunta #61: | GL1: AREA DE POLLO CRUDO: limpia, ordenada y sin presencia de mal olor. Pila de pollo cuenta con rejilla o Rhino para la retención de desechos sólidos. | GM1: Puntos: AREA DE POLLO CRUDO: limpia, ordenada y sin presencia de mal olor. Pila de pollo cuenta con rejilla o Rhino para la retención de desechos sólidos. | GN1: Comentarios: AREA DE POLLO CRUDO: limpia, ordenada y sin presencia de mal olor. Pila de pollo cuenta con rejilla o Rhino para la retención de desechos sólidos. | GO1: Comentarios pregunta #63: | GP1: Puntos: Comentarios pregunta #63: | GQ1: Comentarios: Comentarios pregunta #63: | GR1: MANEJO DE POLLO CRUDO Y EQUIPO EN ALMACENAMIENTO: El pollo debe estar fechado con los datos de la inyección y de vencimiento para la adecuada rotación. Las bolsas de pollo deben mantenerse cerrad... | GS1: Puntos: MANEJO DE POLLO CRUDO Y EQUIPO EN ALMACENAMIENTO: El pollo debe estar fechado con los datos de la inyección y de vencimiento para la adecuada rotación. Las bolsas de pollo deben mantenerse cerrad... | GT1: Comentarios: MANEJO DE POLLO CRUDO Y EQUIPO EN ALMACENAMIENTO: El pollo debe estar fechado con los datos de la inyección y de vencimiento para la adecuada rotación. Las bolsas de pollo deben mantenerse cerrad... | GU1: Comentarios pregunta #65: | GV1: Puntos: Comentarios pregunta #65: | GW1: Comentarios: Comentarios pregunta #65: | GX1: PROCEDIMIENTO DE MANEJO DE POLLO CRUDO: Cuentan con los utensilios amarillos para la manipulación de pollo crudo (delantal, tabla, cuchillo). Se realiza el procedimiento de desinfección de las sup... | GY1: Puntos: PROCEDIMIENTO DE MANEJO DE POLLO CRUDO: Cuentan con los utensilios amarillos para la manipulación de pollo crudo (delantal, tabla, cuchillo). Se realiza el procedimiento de desinfección de las sup... | GZ1: Comentarios: PROCEDIMIENTO DE MANEJO DE POLLO CRUDO: Cuentan con los utensilios amarillos para la manipulación de pollo crudo (delantal, tabla, cuchillo). Se realiza el procedimiento de desinfección de las sup... | HA1: Comentarios pregunta #67: | HB1: Puntos: Comentarios pregunta #67: | HC1: Comentarios: Comentarios pregunta #67: | HD1: AREA DE ALMACENAMIENTO DE VEGETALES: Estantes en buen estado y canastas limpias. No se identifican vegetales en estado de deterioro o descomposición. | HE1: Puntos: AREA DE ALMACENAMIENTO DE VEGETALES: Estantes en buen estado y canastas limpias. No se identifican vegetales en estado de deterioro o descomposición. | HF1: Comentarios: AREA DE ALMACENAMIENTO DE VEGETALES: Estantes en buen estado y canastas limpias. No se identifican vegetales en estado de deterioro o descomposición. | HG1: Comentarios pregunta #69: | HH1: Puntos: Comentarios pregunta #69: | HI1: Comentarios: Comentarios pregunta #69: | HJ1: BODEGA DE ALMACENAMIENTO: se encuentra cerrada, limpia y ordenada. Estantes en buen estado. Los alimentos y material de empaque se colocan mínimo a 10 cm del piso.Solo se recibe materias primas de... | HK1: Puntos: BODEGA DE ALMACENAMIENTO: se encuentra cerrada, limpia y ordenada. Estantes en buen estado. Los alimentos y material de empaque se colocan mínimo a 10 cm del piso.Solo se recibe materias primas de... | HL1: Comentarios: BODEGA DE ALMACENAMIENTO: se encuentra cerrada, limpia y ordenada. Estantes en buen estado. Los alimentos y material de empaque se colocan mínimo a 10 cm del piso.Solo se recibe materias primas de... | HM1: Comentarios pregunta #71: | HN1: Puntos: Comentarios pregunta #71: | HO1: Comentarios: Comentarios pregunta #71: | HP1: PCC CONTAMINACION CRUZADA: Existe algún peligro de contaminación cruzada o riesgo de cuerpos extraños por contaminación física, química o microbiológica, tanto en procesos de elaboración como alma... | HQ1: Puntos: PCC CONTAMINACION CRUZADA: Existe algún peligro de contaminación cruzada o riesgo de cuerpos extraños por contaminación física, química o microbiológica, tanto en procesos de elaboración como alma... | HR1: Comentarios: PCC CONTAMINACION CRUZADA: Existe algún peligro de contaminación cruzada o riesgo de cuerpos extraños por contaminación física, química o microbiológica, tanto en procesos de elaboración como alma... | HS1: Comentarios pregunta #73: | HT1: Puntos: Comentarios pregunta #73: | HU1: Comentarios: Comentarios pregunta #73: | HV1: UNIFORME: Uniforme limpio y completo. El uniforme no se trae puesto desde la casa (autorizado pantalón y zapatos)*Calzado limpio y cerrado. La malla cubre todo el cabello, hasta las orejas. Se cu... | HW1: Puntos: UNIFORME: Uniforme limpio y completo. El uniforme no se trae puesto desde la casa (autorizado pantalón y zapatos)*Calzado limpio y cerrado. La malla cubre todo el cabello, hasta las orejas. Se cu... | HX1: Comentarios: UNIFORME: Uniforme limpio y completo. El uniforme no se trae puesto desde la casa (autorizado pantalón y zapatos)*Calzado limpio y cerrado. La malla cubre todo el cabello, hasta las orejas. Se cu... | HY1: Comentarios pregunta #75: | HZ1: Puntos: Comentarios pregunta #75: | IA1: Comentarios: Comentarios pregunta #75: | IB1: USO DE CELULAR: No se identifican celulares en uso en áreas de proceso e intermedio. Solamente el personal administrativo cuenta con autorización de uso de teléfono celular en horas laborales. | IC1: Puntos: USO DE CELULAR: No se identifican celulares en uso en áreas de proceso e intermedio. Solamente el personal administrativo cuenta con autorización de uso de teléfono celular en horas laborales. | ID1: Comentarios: USO DE CELULAR: No se identifican celulares en uso en áreas de proceso e intermedio. Solamente el personal administrativo cuenta con autorización de uso de teléfono celular en horas laborales. | IE1: Comentarios pregunta #77: | IF1: Puntos: Comentarios pregunta #77: | IG1: Comentarios: Comentarios pregunta #77: | IH1: BAÑO DE COLABORADORES Y AREA DE LOCKERS: Areas limpias y ordenadas. No se almacenan artículos en des uso. Mueble de lockers en buen estado sin etiquetas adhesivas colocadas (No personalizados). ... | II1: Puntos: BAÑO DE COLABORADORES Y AREA DE LOCKERS: Areas limpias y ordenadas. No se almacenan artículos en des uso. Mueble de lockers en buen estado sin etiquetas adhesivas colocadas (No personalizados). ... | IJ1: Comentarios: BAÑO DE COLABORADORES Y AREA DE LOCKERS: Areas limpias y ordenadas. No se almacenan artículos en des uso. Mueble de lockers en buen estado sin etiquetas adhesivas colocadas (No personalizados). ... | IK1: Comentarios pregunta #79: | IL1: Puntos: Comentarios pregunta #79: | IM1: Comentarios: Comentarios pregunta #79: | IN1: MANEJO DE ALIMENTOS Y ARTICULOS DE COLABORADORES: Se destina un espacio para el almacenamiento de comida de colaboradores. No se identifican alimentos u artículos personales de colaboradores en la... | IO1: Puntos: MANEJO DE ALIMENTOS Y ARTICULOS DE COLABORADORES: Se destina un espacio para el almacenamiento de comida de colaboradores. No se identifican alimentos u artículos personales de colaboradores en la... | IP1: Comentarios: MANEJO DE ALIMENTOS Y ARTICULOS DE COLABORADORES: Se destina un espacio para el almacenamiento de comida de colaboradores. No se identifican alimentos u artículos personales de colaboradores en la... | IQ1: Comentarios pregunta #81: | IR1: Puntos: Comentarios pregunta #81: | IS1: Comentarios: Comentarios pregunta #81: | IT1: PROVEEDORES: Proveedor sigue las reglas Rosti al ingresar al local. Uso de redecilla o gorra para el cabello. Aplica para proveedores (materias primas, mantenimiento, TI), visitas, y repartidores. | IU1: Puntos: PROVEEDORES: Proveedor sigue las reglas Rosti al ingresar al local. Uso de redecilla o gorra para el cabello. Aplica para proveedores (materias primas, mantenimiento, TI), visitas, y repartidores. | IV1: Comentarios: PROVEEDORES: Proveedor sigue las reglas Rosti al ingresar al local. Uso de redecilla o gorra para el cabello. Aplica para proveedores (materias primas, mantenimiento, TI), visitas, y repartidores. | IW1: Comentarios pregunta #83: | IX1: Puntos: Comentarios pregunta #83: | IY1: Comentarios: Comentarios pregunta #83: | IZ1: PRODUCTOS QUIMICOS: Se cuenta con los productos químicos, equipos de limpieza y desinfección necesarios, aprobados, en buen estado y dentro de su vida útil. Los mismos almacenados bajo llave lejo... | JA1: Puntos: PRODUCTOS QUIMICOS: Se cuenta con los productos químicos, equipos de limpieza y desinfección necesarios, aprobados, en buen estado y dentro de su vida útil. Los mismos almacenados bajo llave lejo... | JB1: Comentarios: PRODUCTOS QUIMICOS: Se cuenta con los productos químicos, equipos de limpieza y desinfección necesarios, aprobados, en buen estado y dentro de su vida útil. Los mismos almacenados bajo llave lejo... | JC1: Comentarios pregunta #85: | JD1: Puntos: Comentarios pregunta #85: | JE1: Comentarios: Comentarios pregunta #85: | JF1: EQUIPO DE INOCUIDAD: Disponible, en buen estado y funcionando correctamente (Kit de cloro residual, cinta de medición de sanitizante, tabla de medición del aceite, timer) | JG1: Puntos: EQUIPO DE INOCUIDAD: Disponible, en buen estado y funcionando correctamente (Kit de cloro residual, cinta de medición de sanitizante, tabla de medición del aceite, timer) | JH1: Comentarios: EQUIPO DE INOCUIDAD: Disponible, en buen estado y funcionando correctamente (Kit de cloro residual, cinta de medición de sanitizante, tabla de medición del aceite, timer) | JI1: Comentarios pregunta #87: | JJ1: Puntos: Comentarios pregunta #87: | JK1: Comentarios: Comentarios pregunta #87: | JL1: AGUAS RESIDUALES: Trampas de grasa y rhinos en buen estado y con evidencia de limpieza frecuente. El rhino cuenta con malla bien colocada y en buen estado, pilas y drenajes de piso cuentan con re... | JM1: Puntos: AGUAS RESIDUALES: Trampas de grasa y rhinos en buen estado y con evidencia de limpieza frecuente. El rhino cuenta con malla bien colocada y en buen estado, pilas y drenajes de piso cuentan con re... | JN1: Comentarios: AGUAS RESIDUALES: Trampas de grasa y rhinos en buen estado y con evidencia de limpieza frecuente. El rhino cuenta con malla bien colocada y en buen estado, pilas y drenajes de piso cuentan con re... | JO1: Comentarios pregunta #89: | JP1: Puntos: Comentarios pregunta #89: | JQ1: Comentarios: Comentarios pregunta #89: | JR1: MANEJO INTEGRADO DE PLAGAS: Se identifica actividad de plagas (insectos, roedores, etc). Se evidencian de manera visible o hay rastros de presencia de los mismos en el local. En caso positivo, hay... | JS1: Puntos: MANEJO INTEGRADO DE PLAGAS: Se identifica actividad de plagas (insectos, roedores, etc). Se evidencian de manera visible o hay rastros de presencia de los mismos en el local. En caso positivo, hay... | JT1: Comentarios: MANEJO INTEGRADO DE PLAGAS: Se identifica actividad de plagas (insectos, roedores, etc). Se evidencian de manera visible o hay rastros de presencia de los mismos en el local. En caso positivo, hay... | JU1: Comentarios pregunta #91: | JV1: Puntos: Comentarios pregunta #91: | JW1: Comentarios: Comentarios pregunta #91: | JX1: REGISTRO DE COCCION DE POLLO: Los registro de cocción de pollo se encuentra completo, al día (hasta la última desmonta del pollo), ordenado y verificado (mínimo una vez por semana). Cumplimiento d... | JY1: Puntos: REGISTRO DE COCCION DE POLLO: Los registro de cocción de pollo se encuentra completo, al día (hasta la última desmonta del pollo), ordenado y verificado (mínimo una vez por semana). Cumplimiento d... | JZ1: Comentarios: REGISTRO DE COCCION DE POLLO: Los registro de cocción de pollo se encuentra completo, al día (hasta la última desmonta del pollo), ordenado y verificado (mínimo una vez por semana). Cumplimiento d... | KA1: Comentarios pregunta #93: | KB1: Puntos: Comentarios pregunta #93: | KC1: Comentarios: Comentarios pregunta #93: | KD1: COMENTARIOS ADICIONALES: | KE1: Puntos: COMENTARIOS ADICIONALES: | KF1: Comentarios: COMENTARIOS ADICIONALES:
A2: 1 | B2: 45061.437 | C2: 45061.438 | D2: anonymous | F2: 29 | H2: Coronado | K2: 45061 | N2: prueba | Q2: Nazira Herrera | T2: Cumple | U2: 2 | Z2: Cumple | AA2: 2 | AF2: Cumple | AG2: 2 | AM2: 0 | AS2: 0 | AY2: 0 | BE2: 0 | BK2: 0 | BP2: Cumple | BQ2: 3 | BV2: Cumple | BW2: 2 | CC2: 0 | CH2: Cumple | CI2: 2 | CN2: Cumple | CO2: 2 | CU2: 0 | CZ2: Cumple | DA2: 2 | DF2: Cumple | DG2: 2 | DL2: Cumple | DM2: 3 | DR2: Cumple | DS2: 3 | DX2: No cumple | DY2: 0 | EE2: 0 | EJ2: No cumple | EK2: 0 | EP2: No cumple | EQ2: 0 | EW2: 0 | FB2: No cumple | FC2: 0 | FH2: No cumple | FI2: 0 | FN2: No cumple | FO2: 0 | FT2: Cumple | FU2: 2 | FZ2: No cumple | GA2: 0 | GF2: No cumple | GG2: 0 | GL2: No cumple | GM2: 0 | GR2: Cumple | GS2: 2 | GY2: 0 | HE2: 0 | HK2: 0 | HQ2: 0 | HW2: 0 | IC2: 0 | II2: 0 | IO2: 0 | IU2: 0 | JA2: 0 | JG2: 0 | JM2: 0 | JS2: 0 | JY2: 0
A3: 2 | B3: 45061.44 | C3: 45061.442 | D3: anonymous | F3: 32 | H3: City Mall | K3: 45061 | N3: prueba | Q3: Nazira Herrera | T3: Cumple | U3: 2 | Z3: Cumple | AA3: 2 | AF3: Cumple | AG3: 2 | AM3: 0 | AS3: 0 | AY3: 0 | BE3: 0 | BK3: 0 | BP3: No cumple | BQ3: 0 | BV3: Cumple | BW3: 2 | CC3: 0 | CH3: Cumple | CI3: 2 | CN3: Cumple | CO3: 2 | CU3: 0 | CZ3: Cumple | DA3: 2 | DF3: No cumple | DG3: 0 | DL3: Cumple | DM3: 3 | DR3: No cumple | DS3: 0 | DX3: Cumple | DY3: 3 | EE3: 0 | EJ3: Cumple | EK3: 2 | EP3: Cumple | EQ3: 2 | EW3: 0 | FB3: Cumple | FC3: 2 | FH3: Cumple | FI3: 2 | FN3: No cumple | FO3: 0 | FT3: No cumple | FU3: 0 | FZ3: No cumple | GA3: 0 | GF3: Cumple | GG3: 2 | GL3: Cumple | GM3: 2 | GR3: No cumple | GS3: 0 | GY3: 0 | HE3: 0 | HK3: 0 | HQ3: 0 | HW3: 0 | IC3: 0 | II3: 0 | IO3: 0 | IU3: 0 | JA3: 0 | JG3: 0 | JM3: 0 | JS3: 0 | JY3: 0
A4: 3 | B4: 45061.449 | C4: 45061.456 | D4: anonymous | F4: 27 | H4: Coronado | K4: 45061 | N4: prueba | Q4: Nazira Herrera | T4: Cumple | U4: 2 | Z4: Cumple | AA4: 2 | AF4: Cumple | AG4: 2 | AM4: 0 | AS4: 0 | AY4: 0 | BE4: 0 | BK4: 0 | BP4: Cumple | BQ4: 3 | BV4: Cumple | BW4: 2 | CC4: 0 | CH4: Cumple | CI4: 2 | CN4: No cumple | CO4: 0 | CU4: 0 | CZ4: No cumple | DA4: 0 | DF4: No cumple | DG4: 0 | DL4: No cumple | DM4: 0 | DR4: Cumple | DS4: 3 | DX4: Cumple | DY4: 3 | EE4: 0 | EJ4: Cumple | EK4: 2 | EP4: No cumple | EQ4: 0 | EW4: 0 | FB4: No cumple | FC4: 0 | FH4: Cumple | FI4: 2 | FN4: No cumple | FO4: 0 | FT4: No cumple | FU4: 0 | FZ4: No cumple | GA4: 0 | GF4: Cumple | GG4: 2 | GL4: Cumple | GM4: 2 | GR4: No cumple | GS4: 0 | GY4: 0 | HE4: 0 | HK4: 0 | HQ4: 0 | HW4: 0 | IC4: 0 | II4: 0 | IO4: 0 | IU4: 0 | JA4: 0 | JG4: 0 | JM4: 0 | JS4: 0 | JY4: 0
A5: 4 | B5: 45062.619 | C5: 45062.64 | D5: anonymous | F5: 42 | H5: Curridabat | K5: 45062 | N5: Dayanna Trejos Chavez | Q5: Maura Osegueda | T5: Cumple | U5: 2 | Z5: Cumple | AA5: 2 | AF5: No cumple | AG5: 0 | AI5: No se había llenado la información de la segunda monta hasta el momento que se le pidió el registro y se hizo la desmonta sin pedir el registro. | AM5: 0 | AS5: 0 | AY5: 0 | BE5: 0 | BK5: 0 | BP5: Cumple | BQ5: 3 | BV5: Cumple | BW5: 2 | CC5: 0 | CH5: Cumple | CI5: 2 | CN5: Cumple | CO5: 2 | CU5: 0 | CZ5: Cumple | DA5: 2 | DF5: Cumple | DG5: 2 | DL5: Cumple | DM5: 3 | DR5: Cumple | DS5: 3 | DX5: Cumple | DY5: 3 | EE5: 0 | EJ5: No cumple | EK5: 0 | EM5: Se encuentra varios puntos con fechas incorrectas: -Limonada con fechas vencidas -Cebollitas picantes en el mostrador vencidas. -Envaces con fecha erróneas. | EP5: Cumple | EQ5: 2 | EW5: 0 | FB5: Cumple | FC5: 2 | FH5: Cumple | FI5: 2 | FN5: Cumple | FO5: 2 | FT5: Cumple | FU5: 2 | FZ5: No cumple | GA5: 0 | GC5: Se encuentra con productos que no son postres lo cual no se ve bonito para los ojos de los clientes. | GF5: Cumple | GG5: 2 | GL5: Cumple | GM5: 2 | GR5: Cumple | GS5: 2 | GY5: 0 | HE5: 0 | HK5: 0 | HQ5: 0 | HW5: 0 | IC5: 0 | II5: 0 | IO5: 0 | IU5: 0 | JA5: 0 | JG5: 0 | JM5: 0 | JS5: 0 | JY5: 0
A6: 5 | B6: 45062.793 | C6: 45062.799 | D6: anonymous | F6: 44 | H6: San José | K6: 45062 | N6: Diana | Q6: Heidi Murillo | T6: Cumple | U6: 2 | W6: Cumple | Z6: Cumple | AA6: 2 | AC6: Cumple | AF6: Cumple | AG6: 2 | AI6: Cumple | AM6: 0 | AS6: 0 | AY6: 0 | BE6: 0 | BK6: 0 | BP6: Cumple | BQ6: 3 | BS6: Cumple | BV6: Cumple | BW6: 2 | CC6: 0 | CE6: Cumple | CH6: Cumple | CI6: 2 | CK6: Cumple | CN6: Cumple | CO6: 2 | CQ6: Cumple | CU6: 0 | CZ6: No cumple | DA6: 0 | DC6: No se respeta el código de color por áreas y utilizan paños amarillos para limpieza profunda en salón y pila. | DF6: Cumple | DG6: 2 | DI6: Cumple | DL6: Cumple | DM6: 3 | DO6: Cumple | DR6: Cumple | DS6: 3 | DU6: Cumple | DX6: Cumple | DY6: 3 | EA6: Cumple | EE6: 0 | EJ6: Cumple | EK6: 2 | EM6: Cumple | EP6: Cumple | EQ6: 2 | ES6: Cumple | EW6: 0 | FB6: Cumple | FC6: 2 | FE6: Cumple | FH6: Cumple | FI6: 2 | FK6: Cumple | FN6: Cumple | FO6: 2 | FQ6: Cumple | FT6: No cumple | FU6: 0 | FW6: Se encuentran una bolsa de strips mal fechada con 2 dias de vida útil y una bolsa de chicharrón con 4 dias de vida útil, se les hace la corrección. | FZ6: Cumple | GA6: 2 | GC6: Cumple | GF6: Cumple | GG6: 2 | GI6: Cumple | GL6: Cumple | GM6: 2 | GO6: Cumple | GR6: Cumple | GS6: 2 | GY6: 0 | HE6: 0 | HK6: 0 | HQ6: 0 | HW6: 0 | IC6: 0 | II6: 0 | IO6: 0 | IU6: 0 | JA6: 0 | JG6: 0 | JM6: 0 | JS6: 0 | JY6: 0 | KD6: Mantener mucho cuidado cuando se despachan los platillos porque se visualizan cucarachas en la cocina, se recomienda no descuidar la limpieza del segundo piso, principalmente por el área del monta cargas.
A7: 6 | B7: 45065.531 | C7: 45065.553 | D7: anonymous | F7: 44 | H7: FC Pueblo Antiguo | K7: 45065 | N7: Henry Hernàndez | Q7: Nazira Herrera | T7: Cumple | U7: 2 | W7: Se recomienda descartar termómetro con carátula en mal estado, poco legible. | Z7: No Cumple | AA7: 0 | AF7: Cumple | AG7: 2 | AM7: 0 | AS7: 0 | AY7: 0 | BE7: 0 | BK7: 0 | BP7: Cumple | BQ7: 3 | BV7: Cumple | BW7: 2 | CC7: 0 | CH7: Cumple | CI7: 2 | CN7: Cumple | CO7: 2 | CQ7: Cintas de medición vencidas 2019. Reciben nuevas 2025 durante la visita. | CU7: 0 | CZ7: Cumple | DA7: 2 | DF7: Cumple | DG7: 2 | DL7: Cumple | DM7: 3 | DR7: Cumple | DS7: 3 | DX7: Cumple | DY7: 3 | EE7: 0 | EJ7: No cumple | EK7: 0 | EM7: Empanadas no se encuentran identificadas por producto. | EP7: Cumple | EQ7: 2 | EW7: 0 | FB7: Cumple | FC7: 2 | FH7: Cumple | FI7: 2 | FN7: Cumple | FO7: 2 | FT7: Cumple | FU7: 2 | FZ7: Cumple | GA7: 2 | GF7: Cumple | GG7: 2 | GL7: Cumple | GM7: 2 | GR7: Cumple | GS7: 2 | GY7: 0 | HE7: 0 | HK7: 0 | HQ7: 0 | HW7: 0 | IC7: 0 | II7: 0 | IO7: 0 | IU7: 0 | JA7: 0 | JG7: 0 | JM7: 0 | JS7: 0 | JY7: 0
A8: 7 | B8: 45065.878 | C8: 45065.887 | D8: anonymous | F8: 41 | H8: Escazú | K8: 45065 | N8: Doris | Q8: Heidi Murillo | T8: Cumple | U8: 2 | W8: Cumple | Z8: Cumple | AA8: 2 | AC8: No se visualiza riesgo | AF8: No cumple | AG8: 0 | AI8: No se respeta la vida útil del pollo y Pechugas de 3 horas en las montas del 5 y 9 y de 6 horas del 2,3,5 y 9 y registros incompletos los días 7,14 y 17 | AM8: 0 | AS8: 0 | AY8: 0 | BE8: 0 | BK8: 0 | BP8: No cumple | BQ8: 0 | BS8: Masa y empanizador reempacados sin fecha de vencimiento. | BV8: Cumple | BW8: 2 | CC8: 0 | CE8: Cumple | CH8: Cumple | CI8: 2 | CK8: Cumple | CN8: Cumple | CO8: 2 | CQ8: Cumple | CU8: 0 | CZ8: Cumple | DA8: 2 | DC8: Se recomienda cambiar 2 paños verdes de cocina muy deteriorados | DF8: Cumple | DG8: 2 | DI8: Detallar un poquito la limpieza de la cachera del lavamanos | DL8: Cumple | DM8: 3 | DO8: Cumple | DR8: Cumple | DS8: 3 | DU8: Cumple | DX8: Cumple | DY8: 3 | EA8: Cumple | EE8: 0 | EJ8: Cumple | EK8: 2 | EM8: Cumple | EP8: Cumple | EQ8: 2 | ES8: Cumple | EW8: 0 | FB8: Cumple | FC8: 2 | FE8: Cumple | FH8: Cumple | FI8: 2 | FK8: Cumple | FN8: Cumple | FO8: 2 | FQ8: Cumple | FT8: No cumple | FU8: 0 | FW8: Chicharrón de pollo mal fechado con 4 días de vida útil y son sólo 2 días. | FZ8: Cumple | GA8: 2 | GC8: Cumple | GF8: Cumple | GG8: 2 | GI8: Cumple | GL8: Cumple | GM8: 2 | GO8: Cumple | GR8: Cumple | GS8: 2 | GY8: 0 | HE8: 0 | HK8: 0 | HQ8: 0 | HW8: 0 | IC8: 0 | II8: 0 | IO8: 0 | IU8: 0 | JA8: 0 | JG8: 0 | JM8: 0 | JS8: 0 | JY8: 0 | KD8: Se recomienda revisar con el equipo administrativo las oportunidades que se conversaron respecto a los registros de temperatura y monta del pollo. No obstante se nota una mejoría en el orden y la limpieza, se les agradece el esfuerzo y se les insta a seguir trabajando en mejorar.
A9: 8 | B9: 45066.556 | C9: 45066.569 | D9: anonymous | F9: 36 | H9: Sabana | K9: 45066 | N9: Edwin | Q9: Heidi Murillo | T9: Cumple | U9: 2 | W9: Cumple | Z9: Cumple | AA9: 2 | AC9: Cumple no se visualiza ningún riesgo | AF9: Cumple | AG9: 2 | AI9: Cumple | AM9: 0 | AS9: 0 | AY9: 0 | BE9: 0 | BK9: 0 | BP9: No cumple | BQ9: 0 | BS9: El empanizador reempacado estaba sin fecha de vencimiento. | BV9: Cumple | BW9: 2 | CC9: 0 | CE9: Cumple | CH9: Cumple | CI9: 2 | CK9: Cumple, revisar el pedal porque no está funcionando correctamente. | CN9: No cumple | CO9: 0 | CQ9: Cinta de medir el sanitizante vencida desde Nov 2018. | CU9: 0 | CZ9: No cumple | DA9: 0 | DC9: Paños de cocina y pollo los mantienen sobre las mesas de trabajo y no en solución sanitizante. | DF9: No cumple | DG9: 0 | DI9: Se encuentra alimentos de colaboradores fuera de la caja destinada para este fin. Cereales en el express | DL9: Cumple | DM9: 3 | DO9: Cumple | DR9: No cumple | DS9: 0 | DU9: Reforzar la limpieza del area frente a la puerta de empleados, estaba muy desordenada con cajas y había un indigente durmiendo ahí. | DX9: Cumple | DY9: 3 | EA9: Cumple | EE9: 0 | EJ9: Cumple | EK9: 2 | EM9: Cumple | EP9: Cumple | EQ9: 2 | ES9: Cumple | EW9: 0 | FB9: Cumple | FC9: 2 | FE9: Cumple | FH9: Cumple | FI9: 2 | FK9: Cumple | FN9: Cumple | FO9: 2 | FQ9: Cumple | FT9: Cumple | FU9: 2 | FW9: Cumple | FZ9: Cumple | GA9: 2 | GC9: Cumple | GF9: Cumple | GG9: 2 | GI9: Cumple | GL9: Cumple | GM9: 2 | GO9: Cumple | GR9: Cumple | GS9: 2 | GY9: 0 | HE9: 0 | HK9: 0 | HQ9: 0 | HW9: 0 | IC9: 0 | II9: 0 | IO9: 0 | IU9: 0 | JA9: 0 | JG9: 0 | JM9: 0 | JS9: 0 | JY9: 0 | KD9: Se notan avances importantes en limpieza, se les insta a seguir trabajando para mejorar las oportunidades conversadas. Gracias por el esfuerzo que están realizando.
A10: 9 | B10: 45067.575 | C10: 45067.582 | D10: anonymous | F10: 44 | H10: Real Alajuela | K10: 45067 | N10: Sergio | Q10: Heidi Murillo | T10: Cumple | U10: 2 | W10: Cumple | Z10: Cumple | AA10: 2 | AC10: No se visualiza ningún riesgo materializable | AF10: Cumple | AG10: 2 | AI10: Cumple, se conversa con el gerente sobre revisar la exactitud en las horas de monta y desmonta. | AM10: 0 | AS10: 0 | AY10: 0 | BE10: 0 | BK10: 0 | BP10: Cumple | BQ10: 3 | BS10: Cumple | BV10: Cumple | BW10: 2 | CC10: 0 | CE10: Cumple | CH10: Cumple | CI10: 2 | CN10: Cumple | CO10: 2 | CQ10: Cumple | CU10: 0 | CZ10: Cumple | DA10: 2 | DC10: Cumple | DF10: No cumple | DG10: 0 | DI10: Bolso de colaboradora fuera de lockers y pan de colaboradores en estante de la cocina. | DL10: Cumple | DM10: 3 | DO10: Cumple, se recomienda pedir una tapa reducida para el basurero de la pila. | DR10: Cumple | DS10: 3 | DU10: Cumple | DX10: Cumple | DY10: 3 | EA10: Cumple | EE10: 0 | EJ10: No cumple | EK10: 0 | EM10: Chicarrón de pollo sin fechar y tortilla aliñada con fecha equivocada. | EP10: Cumple | EQ10: 2 | ES10: Cumple | EW10: 0 | FB10: Cumple | FC10: 2 | FE10: Cumple | FH10: Cumple | FI10: 2 | FK10: Cumple | FN10: Cumple | FO10: 2 | FQ10: Cumple | FT10: Cumple | FU10: 2 | FZ10: Cumple | GA10: 2 | GC10: Cumple | GF10: Cumple | GG10: 2 | GL10: Cumple | GM10: 2 | GO10: Cumple | GR10: Cumple | GS10: 2 | GY10: 0 | HE10: 0 | HK10: 0 | HQ10: 0 | HW10: 0 | IC10: 0 | II10: 0 | IO10: 0 | IU10: 0 | JA10: 0 | JG10: 0 | JM10: 0 | JS10: 0 | JY10: 0 | KD10: Muchas gracias por la constancia y el seguimiento de la oportunidad es conversadas.
A11: 10 | B11: 45069.886 | C11: 45069.9 | D11: anonymous | F11: 36 | H11: Lincoln | K11: 45069 | N11: Andrea Rojas | Q11: Heidi Murillo | T11: No cumple | U11: 0 | W11: No encuentran el termómetro del freidor, no se logró evaluar. El termómetro de pollo estaba correctamente. | Z11: No Cumple | AA11: 0 | AC11: La colaboradora Dayana estaba deshuesando las pechugas sin guantes, el caldo de pollo lo tenían enfriando en la pila y le estaba cayendo el agua que escurría de las bandejas colocadas en el estante superior. Se le recomendó a la encargada desechar ese producto. | AF11: No cumple | AG11: 0 | AI11: Faltan algunos datos del 18 y algunos registros estaban con fechas incorrectas, lo que hace que pierdan validez (por ejemplo tenían datos de montas con fecha del 24 y apenas hoy es 23) | AM11: 0 | AS11: 0 | AY11: 0 | BE11: 0 | BK11: 0 | BP11: Cumple | BQ11: 3 | BS11: Mejorar la limpieza del piso. | BV11: Cumple | BW11: 2 | CC11: 0 | CE11: Cumple | CH11: No cumple | CI11: 0 | CK11: Lavamanos muy sucio, con residuos de servilletas y papel. | CN11: Cumple | CO11: 2 | CQ11: Cumple | CU11: 0 | CZ11: Cumple | DA11: 2 | DC11: Cumple | DF11: Cumple | DG11: 2 | DI11: Cumple | DL11: Cumple | DM11: 3 | DO11: El basurero de cocina estaba con la tapa muy sucia, llena de tizne como si le hubiesen puesto una olla encima. | DR11: Cumple | DS11: 3 | DU11: Cumple | DX11: Cumple | DY11: 3 | EA11: Cumple | EE11: 0 | EJ11: Cumple | EK11: 2 | EM11: Cumple | EP11: Cumple | EQ11: 2 | ES11: Cumple | EW11: 0 | FB11: Cumple | FC11: 2 | FE11: Cumple | FH11: No cumple | FI11: 0 | FK11: No se respeta el tiempo de enfriamiento. Tenían pasta de pollo y caldo de pollo con muchas horas, con el hielo derretido y el agua del mismo a temperatura ambiente. | FN11: Cumple | FO11: 2 | FQ11: Cumple | FT11: No cumple | FU11: 0 | FW11: El piso detrás de la cámara estaba muy sucio y como había un olor a podrido se procedió a revisar el área y se encontró la bandeja con con residuos en estado de descomposición, se les pidió que la lavaran. | FZ11: Cumple | GA11: 2 | GC11: Cumple | GF11: Cumple | GG11: 2 | GI11: Cumple | GL11: Cumple | GM11: 2 | GO11: Cumple | GR11: Cumple | GS11: 2 | GY11: 0 | HE11: 0 | HK11: 0 | HQ11: 0 | HW11: 0 | IC11: 0 | II11: 0 | IO11: 0 | IU11: 0 | JA11: 0 | JG11: 0 | JM11: 0 | JS11: 0 | JY11: 0 | KD11: Urge revisar las oportunidades evidenciadas. Muchas oportunidades de limpieza.
A12: 11 | B12: 45072.608 | C12: 45072.628 | D12: anonymous | F12: 38 | H12: Multiplaza Curridabat | K12: 45072 | N12: Alejandra Granados | Q12: Nazira Herrera | T12: Cumple | U12: 2 | Z12: No Cumple | AA12: 0 | AF12: No cumple | AG12: 0 | AI12: Hay información ilegible, datos tachados y uso de lápiz en el registro. | AM12: 0 | AS12: 0 | AY12: 0 | BE12: 0 | BK12: 0 | BP12: Cumple | BQ12: 3 | BV12: No cumple | BW12: 0 | CC12: 0 | CE12: Colaboradora de cocina con contacto directo con alimentos utiliza pulsera plástica. | CH12: Cumple | CI12: 2 | CN12: Cumple | CO12: 2 | CU12: 0 | CZ12: Cumple | DA12: 2 | DF12: No cumple | DG12: 0 | DI12: Falta mejorar orden del área de locker, no mantener uniformes sobre los muebles. | DL12: Cumple | DM12: 3 | DR12: Cumple | DS12: 3 | DX12: Cumple | DY12: 3 | EE12: 0 | EJ12: Cumple | EK12: 2 | EP12: Cumple | EQ12: 2 | EW12: 0 | FB12: Cumple | FC12: 2 | FH12: Cumple | FI12: 2 | FN12: Cumple | FO12: 2 | FT12: Cumple | FU12: 2 | FZ12: No cumple | GA12: 0 | GC12: Retirar flores deterioradas y marchitas de postres y urna | GF12: Cumple | GG12: 2 | GL12: Cumple | GM12: 2 | GR12: Cumple | GS12: 2 | GY12: 0 | HE12: 0 | HK12: 0 | HQ12: 0 | HW12: 0 | IC12: 0 | II12: 0 | IO12: 0 | IU12: 0 | JA12: 0 | JG12: 0 | JM12: 0 | JS12: 0 | JY12: 0 | KD12: Muchas mejoras en orden y limpieza de equipos. Excelente el área de servicio y atención a clientes. El área de preparación siempre se mantiene muy incomoda. Evaluar sustitución de pila por mesa de pollo cocinado o soporte para enfriamiento de alimentos etc.
A13: 12 | B13: 45074.581 | C13: 45074.594 | D13: anonymous | F13: 37 | H13: Coronado | K13: 45074 | N13: Graciela | Q13: Heidi Murillo | T13: Cumple | U13: 2 | W13: El termómetro del freidor no está funcionando correctamente, porque se hace prueba y no está censando bien la temperatura, no llegó ni a los 300 F. Se recomienda cambiarlo. | Z13: Cumple | AA13: 2 | AC13: Cumple | AF13: Cumple | AG13: 2 | AI13: Cumple | AM13: 0 | AS13: 0 | AY13: 0 | BE13: 0 | BK13: 0 | BP13: Cumple | BQ13: 3 | BS13: Cumple | BV13: Cumple | BW13: 2 | CC13: 0 | CE13: Cumple | CH13: Cumple | CI13: 2 | CK13: Cumple | CN13: Cumple | CO13: 2 | CQ13: Cumple | CU13: 0 | CZ13: Cumple | DA13: 2 | DC13: Se recomienda cambiar dos paños verde que están muy deteriorados y ya se ven muy curtidos. | DF13: No cumple | DG13: 0 | DI13: No cumple, se guardan alimentos personales en la cámara, fuera de la caja de comida de colaboradores (natilla) | DL13: No cumple | DM13: 0 | DO13: Usan el basurero interno sin tapar, le quitaron la tapa y la tenían debajo de la pila, se les hace la observación y la corrigen en el momento. | DR13: Cumple | DS13: 3 | DU13: Cumple | DX13: Cumple | DY13: 3 | EA13: Cumple | EE13: 0 | EJ13: No cumple | EK13: 0 | EM13: Se encuentra pasta de pollo en bandeja sin fechar. | EP13: Cumple | EQ13: 2 | ES13: Cumple | EW13: 0 | FB13: Cumple | FC13: 2 | FE13: Cumple | FH13: No cumple | FI13: 0 | FK13: Se encuentra Arroz blanco enfriando a temperatura ambiente, sin el procedimiento correcto. | FN13: Cumple | FO13: 2 | FQ13: Cumple | FT13: No cumple | FU13: 0 | FW13: Cámara de pollo muy sucia por fuera, las puertas llenas de residuos de bater y empanizador. | FZ13: Cumple | GA13: 2 | GC13: Cumple | GF13: Cumple | GG13: 2 | GI13: Cumple | GL13: Cumple | GM13: 2 | GO13: Cumple | GR13: Cumple | GS13: 2 | GY13: 0 | HE13: 0 | HK13: 0 | HQ13: 0 | HW13: 0 | IC13: 0 | II13: 0 | IO13: 0 | IU13: 0 | JA13: 0 | JG13: 0 | JM13: 0 | JS13: 0 | JY13: 0 | KD13: Revisar y trabajar en las oportunidades conversadas.
A14: 13 | B14: 45077.548 | C14: 45077.615 | D14: anonymous | F14: 39 | H14: Cartago | K14: 45077 | N14: Grettel - Marco | Q14: Nazira Herrera | T14: Cumple | U14: 2 | Z14: Cumple | AA14: 2 | AF14: Cumple | AG14: 2 | AM14: 0 | AS14: 0 | AY14: 0 | BE14: 0 | BK14: 0 | BP14: No cumple | BQ14: 0 | BS14: Recipiente de almacenamiento de empanizador húmedo y con ranuras puede dañar y contaminar el empanizador. | BV14: Cumple | BW14: 2 | CC14: 0 | CH14: Cumple | CI14: 2 | CN14: Cumple | CO14: 2 | CU14: 0 | CZ14: Cumple | DA14: 2 | DF14: No cumple | DG14: 0 | DI14: Falta orden en el área de lockers, zapatos sobre los lockers, blusas sobre las sillas, bolsos en los sillones. | DL14: Cumple | DM14: 3 | DR14: Cumple | DS14: 3 | DX14: Cumple | DY14: 3 | EE14: 0 | EJ14: No cumple | EK14: 0 | EM14: Empanizador se encuentra porcionado pero no fechado | EP14: Cumple | EQ14: 2 | EW14: 0 | FB14: Cumple | FC14: 2 | FH14: Cumple | FI14: 2 | FN14: Cumple | FO14: 2 | FT14: Cumple | FU14: 2 | FZ14: No cumple | GA14: 0 | GC14: Tres leches sin decoración. Queque de chocolate tiene el caramelo derramado. | GF14: Cumple | GG14: 2 | GL14: Cumple | GM14: 2 | GR14: Cumple | GS14: 2 | GY14: 0 | HE14: 0 | HK14: 0 | HQ14: 0 | HW14: 0 | IC14: 0 | II14: 0 | IO14: 0 | IU14: 0 | JA14: 0 | JG14: 0 | JM14: 0 | JS14: 0 | JY14: 0 | KD14: Buen desempeño y condiciones en general del restaurante. Alto movimiento durante el almuerzo. Detallar en temas de servicio de platillos y empaques.
A15: 14 | B15: 45083.459 | C15: 45083.636 | D15: anonymous | F15: 19 | H15: Lincoln | K15: 45083 | N15: Julissa Chang | Q15: Nazira Herrera | T15: No cumple | U15: 0 | W15: Termómetro no se mantiene en solución sanitizante | Z15: No Cumple | AA15: 0 | AC15: Trampa de grasa con aperturas y mal olor cerca de áreas de preparación. Repollo y bases de sopa en la pila con platos sucios. | AF15: No cumple | AG15: 0 | AI15: Uso de corrector en varios datos del registro, además faltan datos del día de ayer (05/06) solo datos de primer y última monta. | AM15: 0 | AS15: 0 | AY15: 0 | BE15: 0 | BK15: 0 | BP15: No cumple | BQ15: 0 | BS15: Compra de fideos no aprobados para Ramen. Realizar limpieza de recipientes. | BV15: Cumple | BW15: 2 | CC15: 0 | CH15: No cumple | CI15: 0 | CK15: No hay jabón a la hora de realizar la visita (lo colocan de manera posterior cuando se les solicita) | CN15: Cumple | CO15: 2 | CU15: 0 | CZ15: No cumple | DA15: 0 | DC15: No tiene solución sanitizante | DF15: No cumple | DG15: 0 | DI15: Se identifica helado de consumo de colaboradores en cámara de congelación junto a materias primas. | DL15: Cumple | DM15: 3 | DR15: Cumple | DS15: 3 | DX15: Cumple | DY15: 3 | EE15: 0 | EJ15: No cumple | EK15: 0 | EM15: Se identifica alimentos sin fechas (pollo, cocoa) además fideos sin tapar y en agua dentro del holding | EP15: Cumple | EQ15: 2 | EW15: 0 | FB15: No cumple | FC15: 0 | FE15: Culantro y lechugas se mantienen a temperatura ambiente | FH15: No cumple | FI15: 0 | FK15: Arroz con pollo a temperatura ambiente | FN15: Cumple | FO15: 2 | FT15: No cumple | FU15: 0 | FW15: Pollo no estaba fechado | FZ15: No cumple | GA15: 0 | GC15: Tres leches no está correctamente flambeado, cc dulce de leche mal decorado, flan muy amarillo, deshidratado y con fecha manual. | GF15: No cumple | GG15: 0 | GI15: Area de colocación de picheles (acrílico) requiere limpieza, al igual que la base de la máquina de Coca Cola (rejilla y base plástica de hielo) y hielera de dispensadores. Los cubiertos deben estar en canasta no directamente sobre el mueble. Hay artículos junto a los saleros y aderezos que no deben estar ahí y que indican que son de los clientes. | GL15: No cumple | GM15: 0 | GO15: Dispensador sin papel higiénico colocado. | GR15: Cumple | GS15: 2 | GY15: 0 | HE15: 0 | HK15: 0 | HQ15: 0 | HW15: 0 | IC15: 0 | II15: 0 | IO15: 0 | IU15: 0 | JA15: 0 | JG15: 0 | JM15: 0 | JS15: 0 | JY15: 0 | KD15: Revisar procedimientos de limpieza, fechado y temperaturas de almacenamiento. Uso de sanitizante en utensilios y registro correcto de la información. Retirar información obsoleta del área de intermedio.
A16: 15 | B16: 45084.493 | C16: 45084.507 | D16: anonymous | F16: 36 | H16: Coronado | K16: 45084 | N16: Zayda | Q16: Angie Valverde | T16: Cumple | U16: 2 | Z16: Cumple | AA16: 2 | AF16: Cumple | AG16: 2 | AM16: 0 | AS16: 0 | AY16: 0 | BE16: 0 | BK16: 0 | BP16: Cumple | BQ16: 3 | BV16: Cumple | BW16: 2 | CC16: 0 | CH16: Cumple | CI16: 2 | CN16: No cumple | CO16: 0 | CQ16: equipos de área de lavado están dañados, se están usando los químicos manualmente. | CU16: 0 | CZ16: Cumple | DA16: 2 | DF16: No cumple | DG16: 0 | DI16: Se encuentran uvas en el area de cajas | DL16: Cumple | DM16: 3 | DR16: Cumple | DS16: 3 | DX16: Cumple | DY16: 3 | EE16: 0 | EJ16: No cumple | EK16: 0 | EM16: 1-Se encuentra recipiente de batter en mal estado, quebrado, por lo tanto el producto no esta bien tapado. 2- Pollo de strips sin fechar. 3-Recipientes de condimentos sin identificacion( estan con el mismo recipiente y el color de ellos es igual, por lo tanto pueden confundirse) | EP16: Cumple | EQ16: 2 | EW16: 0 | FB16: No cumple | FC16: 0 | FE16: urna de postres no esta cumpliendo con temperatura adecuada ya que la camara esta dañada. | FH16: Cumple | FI16: 2 | FN16: Cumple | FO16: 2 | FT16: No cumple | FU16: 0 | FW16: Pollo de strips sin fechar | FZ16: Cumple | GA16: 2 | GF16: Cumple | GG16: 2 | GL16: Cumple | GM16: 2 | GR16: No cumple | GS16: 0 | GY16: 0 | HE16: 0 | HK16: 0 | HQ16: 0 | HW16: 0 | IC16: 0 | II16: 0 | IO16: 0 | IU16: 0 | JA16: 0 | JG16: 0 | JM16: 0 | JS16: 0 | JY16: 0 | KD16: permiso de salud vencido, me comentan que ya tienen el nuevo, pero no se ha cambiado
A17: 16 | B17: 45084.778 | C17: 45084.835 | D17: anonymous | F17: 18 | H17: Multiplaza Escazú | K17: 45084 | N17: Maricell Porras | Q17: Nazira Herrera | T17: No cumple | U17: 0 | W17: Termómetro del pollo no se encuentra en solución sanitizante. Termómetros del freidor requieren limpieza. | Z17: No Cumple | AA17: 0 | AC17: Pollo crudo almacenado en congelador junto con el pan queso y otros productos. Monta de pollo con delantal de pila. Los moldes de preparación de huevo frito tienen mucha grasa y cochambre acumulada. | AF17: No cumple | AG17: 0 | AI17: No hay datos de montas posterior a la primera del día (18:50) | AM17: 0 | AS17: 0 | AY17: 0 | BE17: 0 | BK17: 0 | BP17: No cumple | BQ17: 0 | BS17: Cerca del área de cajas se identifica caja con material de empaque (cajas ensaladeras) en el piso. Además hay dos sacos de masa para tortillas abiertos y en uso al mismo tiempo, debe consumirse primero uno y al agotarse abrir el otro. | BV17: Cumple | BW17: 2 | CC17: 0 | CH17: No cumple | CI17: 0 | CK17: No hay toallas de secado en ambos lavamanos | CN17: No cumple | CO17: 0 | CQ17: Cintas de medición vencidas y dañadas. | CU17: 0 | CZ17: No cumple | DA17: 0 | DC17: No tienen solución sanitizante | DF17: No cumple | DG17: 0 | DI17: Area de lockers y baño con mucho desorden, requiere limpieza y sacar artículos en desuso. Hay muchos zapatos de colaboradores en varias partes, comida sobre los lockers, dispensador de papel quebrado y no hay papel higiénico. | DL17: Cumple | DM17: 3 | DR17: No cumple | DS17: 0 | DU17: Maceteras requieren plantas. Hay un mueble vacío. | DX17: Cumple | DY17: 3 | EA17: La misma mesa que se usa para los Ubers se encuentra el display de cebollitas | EE17: 0 | EJ17: No cumple | EK17: 0 | EM17: Caldo de birria almacenado sin tapar. Recipiente de almacenamiento de chalupas requiere limpieza. Fideos en mueble de cocina (5 paquetes) | EP17: Cumple | EQ17: 2 | EW17: 0 | FB17: No cumple | FC17: 0 | FE17: Kale se mantiene junto a la plancha sobre los recipientes de aceites. Hierbabuena oxidada, se mantiene en intermedio a temperatura ambiente. | FH17: Cumple | FI17: 2 | FN17: Cumple | FO17: 2 | FT17: Cumple | FU17: 2 | FZ17: No cumple | GA17: 0 | GC17: Artículos "no permitidos" dentro de la urne en exhibición. No hay CC DL | GF17: No cumple | GG17: 0 | GI17: El area de intermedio tiene artículos que no corresponden a este espacio o se colocan de manera desordenada. Hay delantal de colaboradora, cinta adhesiva. En el intermedio del salón (área de postres) los platos de mini postres y platos de llevar los sobrantes de los clientes están sucios con residuos de productos. | GL17: No cumple | GM17: 0 | GO17: Posterior a hora de movimiento el baño de mujeres tiene papeles en el piso y basurero muy llego. No se realizan labores de limpieza. | GR17: Cumple | GS17: 2 | GY17: 0 | HE17: 0 | HK17: 0 | HQ17: 0 | HW17: 0 | IC17: 0 | II17: 0 | IO17: 0 | IU17: 0 | JA17: 0 | JG17: 0 | JM17: 0 | JS17: 0 | JY17: 0 | KD17: Dar seguimiento a temas de limpieza profunda de equipos y utensilios. Llenado de registro de cocción en tiempo y forma correcta y verificación de solución sanitizante.
A18: 17 | B18: 45085.467 | C18: 45085.477 | D18: anonymous | F18: 42 | H18: Cartago | K18: 45085 | N18: Katiola | Q18: Angie Valverde | T18: Cumple | U18: 2 | Z18: Cumple | AA18: 2 | AF18: Cumple | AG18: 2 | AM18: 0 | AS18: 0 | AY18: 0 | BE18: 0 | BK18: 0 | BP18: Cumple | BQ18: 3 | BV18: Cumple | BW18: 2 | CC18: 0 | CH18: No cumple | CI18: 0 | CK18: Lavamanos del área de Refrescos estaba sin jabón. | CN18: Cumple | CO18: 2 | CU18: 0 | CZ18: Cumple | DA18: 2 | DF18: Cumple | DG18: 2 | DL18: Cumple | DM18: 3 | DR18: Cumple | DS18: 3 | DX18: Cumple | DY18: 3 | EE18: 0 | EJ18: No cumple | EK18: 0 | EM18: se encuentra un fresco de cas sin lote y una bolsa de masmelos abierta en gavetas. | EP18: Cumple | EQ18: 2 | EW18: 0 | FB18: No cumple | FC18: 0 | FE18: cámaras de postres, cámara de refrigeración, mesa fría y cámara de congelación no están cumpliendo con las temperaturas por lo tanto los productos no cumplen con la zona de peligro | FH18: Cumple | FI18: 2 | FN18: Cumple | FO18: 2 | FT18: Cumple | FU18: 2 | FZ18: Cumple | GA18: 2 | GF18: Cumple | GG18: 2 | GL18: Cumple | GM18: 2 | GR18: Cumple | GS18: 2 | GY18: 0 | HE18: 0 | HK18: 0 | HQ18: 0 | HW18: 0 | IC18: 0 | II18: 0 | IO18: 0 | IU18: 0 | JA18: 0 | JG18: 0 | JM18: 0 | JS18: 0 | JY18: 0
A19: 18 | B19: 45086.548 | C19: 45086.555 | D19: anonymous | F19: 41 | H19: Terramall | K19: 45086 | N19: Andrea | Q19: Angie Valverde | T19: Cumple | U19: 2 | Z19: Cumple | AA19: 2 | AF19: Cumple | AG19: 2 | AM19: 0 | AS19: 0 | AY19: 0 | BE19: 0 | BK19: 0 | BP19: No cumple | BQ19: 0 | BS19: cajas donde se guardan materias primas estan sucias | BV19: Cumple | BW19: 2 | CC19: 0 | CH19: Cumple | CI19: 2 | CN19: Cumple | CO19: 2 | CU19: 0 | CZ19: No cumple | DA19: 0 | DC19: Paños de limpieza no estaban en solución sanitizante | DF19: Cumple | DG19: 2 | DL19: Cumple | DM19: 3 | DR19: Cumple | DS19: 3 | DX19: Cumple | DY19: 3 | EE19: 0 | EJ19: No cumple | EK19: 0 | EM19: se encuentran materias primas del dia anterior sin fechar; pollo , arroz. | EP19: Cumple | EQ19: 2 | EW19: 0 | FB19: Cumple | FC19: 2 | FH19: Cumple | FI19: 2 | FN19: Cumple | FO19: 2 | FT19: Cumple | FU19: 2 | FZ19: Cumple | GA19: 2 | GF19: Cumple | GG19: 2 | GL19: Cumple | GM19: 2 | GR19: Cumple | GS19: 2 | GY19: 0 | HE19: 0 | HK19: 0 | HQ19: 0 | HW19: 0 | IC19: 0 | II19: 0 | IO19: 0 | IU19: 0 | JA19: 0 | JG19: 0 | JM19: 0 | JS19: 0 | JY19: 0
A20: 19 | B20: 45089.501 | C20: 45089.521 | D20: anonymous | F20: 36 | H20: Curridabat | K20: 45089 | N20: Dayana | Q20: Angie Valverde | T20: Cumple | U20: 2 | Z20: Cumple | AA20: 2 | AF20: Cumple | AG20: 2 | AM20: 0 | AS20: 0 | AY20: 0 | BE20: 0 | BK20: 0 | BP20: No cumple | BQ20: 0 | BS20: bodega de materias primas, sucia, con cucarachas, guantes sucios, cajas donde ponen verduras sucias. | BV20: Cumple | BW20: 2 | CC20: 0 | CH20: Cumple | CI20: 2 | CN20: Cumple | CO20: 2 | CU20: 0 | CZ20: No cumple | DA20: 0 | DC20: se encuentran pañitos sin solución sanitizante y utensilios de postres. | DF20: Cumple | DG20: 2 | DL20: Cumple | DM20: 3 | DR20: No cumple | DS20: 0 | DU20: se encuentra esponjas , servilletas , guantes, bolsas de basura. | DX20: Cumple | DY20: 3 | EE20: 0 | EJ20: No cumple | EK20: 0 | EM20: pollo cocinado en camara de pollo sin fechar | EP20: Cumple | EQ20: 2 | EW20: 0 | FB20: Cumple | FC20: 2 | FH20: Cumple | FI20: 2 | FN20: Cumple | FO20: 2 | FT20: No cumple | FU20: 0 | FW20: Delantal pollo crudo con pedazos de pollo. | FZ20: Cumple | GA20: 2 | GF20: Cumple | GG20: 2 | GL20: Cumple | GM20: 2 | GR20: Cumple | GS20: 2 | GY20: 0 | HE20: 0 | HK20: 0 | HQ20: 0 | HW20: 0 | IC20: 0 | II20: 0 | IO20: 0 | IU20: 0 | JA20: 0 | JG20: 0 | JM20: 0 | JS20: 0 | JY20: 0
A21: 20 | B21: 45090.514 | C21: 45090.528 | D21: anonymous | F21: 33 | H21: San José | K21: 45090 | N21: Rosalyn | Q21: Angie Valverde | T21: No cumple | U21: 0 | W21: termómetro sin sanitizante | Z21: No Cumple | AA21: 0 | AC21: químicos en el mismo sitio que las pajillas y a la par | AF21: Cumple | AG21: 2 | AM21: 0 | AS21: 0 | AY21: 0 | BE21: 0 | BK21: 0 | BP21: No cumple | BQ21: 0 | BS21: se encuentra aceite, bolsas, en el piso. y los huevos están encima de productos | BV21: Cumple | BW21: 2 | CC21: 0 | CH21: Cumple | CI21: 2 | CN21: No cumple | CO21: 0 | CQ21: productos químicos están en mesas donde almacenan pajillas y otras cosas. solicitar cambio de escobas porque están en mal estado | CU21: 0 | CZ21: Cumple | DA21: 2 | DF21: Cumple | DG21: 2 | DL21: Cumple | DM21: 3 | DR21: Cumple | DS21: 3 | DX21: Cumple | DY21: 3 | EE21: 0 | EJ21: No cumple | EK21: 0 | EM21: se encuentran elotes sin ninguna fecha | EP21: Cumple | EQ21: 2 | EW21: 0 | FB21: No cumple | FC21: 0 | FE21: mesas frias, camara de pollo y camara de postres no cumplen con temperaturas por lo tanto los productos tampoco | FH21: Cumple | FI21: 2 | FN21: Cumple | FO21: 2 | FT21: No cumple | FU21: 0 | FW21: bolsas abiertas en las cámaras de pollo, además de bolsas rotas y con evidencia de pollo deshidratado | FZ21: Cumple | GA21: 2 | GF21: Cumple | GG21: 2 | GL21: Cumple | GM21: 2 | GR21: Cumple | GS21: 2 | GY21: 0 | HE21: 0 | HK21: 0 | HQ21: 0 | HW21: 0 | IC21: 0 | II21: 0 | IO21: 0 | IU21: 0 | JA21: 0 | JG21: 0 | JM21: 0 | JS21: 0 | JY21: 0
A22: 21 | B22: 45091.631 | C22: 45091.638 | D22: anonymous | F22: 35 | H22: Desamparados | K22: 45091 | N22: Sonia | Q22: Angie Valverde | T22: Cumple | U22: 2 | Z22: No Cumple | AA22: 0 | AC22: se encuentra jabón en polvo regado encima de un congelador | AF22: No cumple | AG22: 0 | AI22: están la montas hasta las 2 pm | AM22: 0 | AS22: 0 | AY22: 0 | BE22: 0 | BK22: 0 | BP22: No cumple | BQ22: 0 | BS22: se encuentran bolsas directo en el piso | BV22: Cumple | BW22: 2 | CC22: 0 | CH22: Cumple | CI22: 2 | CN22: No cumple | CO22: 0 | CQ22: jabon en polvo en sitios donde no deben estar | CU22: 0 | CZ22: Cumple | DA22: 2 | DF22: Cumple | DG22: 2 | DL22: Cumple | DM22: 3 | DR22: Cumple | DS22: 3 | DX22: Cumple | DY22: 3 | EE22: 0 | EJ22: No cumple | EK22: 0 | EM22: rostineta sin fechar | EP22: Cumple | EQ22: 2 | EW22: 0 | FB22: No cumple | FC22: 0 | FE22: cámaras no cumplen temperatura , por lo tanto los alimentos están en zona de peligro | FH22: Cumple | FI22: 2 | FN22: Cumple | FO22: 2 | FT22: Cumple | FU22: 2 | FZ22: Cumple | GA22: 2 | GF22: Cumple | GG22: 2 | GL22: Cumple | GM22: 2 | GR22: Cumple | GS22: 2 | GY22: 0 | HE22: 0 | HK22: 0 | HQ22: 0 | HW22: 0 | IC22: 0 | II22: 0 | IO22: 0 | IU22: 0 | JA22: 0 | JG22: 0 | JM22: 0 | JS22: 0 | JY22: 0
A23: 22 | B23: 45092.639 | C23: 45092.644 | D23: anonymous | F23: 44 | H23: Oxígeno | K23: 45092 | N23: German | Q23: Angie Valverde | T23: Cumple | U23: 2 | Z23: Cumple | AA23: 2 | AF23: Cumple | AG23: 2 | AM23: 0 | AS23: 0 | AY23: 0 | BE23: 0 | BK23: 0 | BP23: Cumple | BQ23: 3 | BV23: Cumple | BW23: 2 | CC23: 0 | CH23: Cumple | CI23: 2 | CN23: Cumple | CO23: 2 | CU23: 0 | CZ23: Cumple | DA23: 2 | DF23: Cumple | DG23: 2 | DL23: Cumple | DM23: 3 | DR23: Cumple | DS23: 3 | DX23: Cumple | DY23: 3 | EE23: 0 | EJ23: No cumple | EK23: 0 | EP23: Cumple | EQ23: 2 | EW23: 0 | FB23: No cumple | FC23: 0 | FE23: camaras no cumplen , por lo tanto los alimentos estan en zona de peligro | FH23: Cumple | FI23: 2 | FN23: Cumple | FO23: 2 | FT23: Cumple | FU23: 2 | FZ23: Cumple | GA23: 2 | GF23: Cumple | GG23: 2 | GL23: Cumple | GM23: 2 | GR23: Cumple | GS23: 2 | GY23: 0 | HE23: 0 | HK23: 0 | HQ23: 0 | HW23: 0 | IC23: 0 | II23: 0 | IO23: 0 | IU23: 0 | JA23: 0 | JG23: 0 | JM23: 0 | JS23: 0 | JY23: 0
A24: 23 | B24: 45093.632 | C24: 45093.64 | D24: anonymous | F24: 46 | H24: FC Pueblo Antiguo | K24: 45093 | N24: Henry y Diana | Q24: Angie Valverde | T24: Cumple | U24: 2 | Z24: Cumple | AA24: 2 | AF24: Cumple | AG24: 2 | AM24: 0 | AS24: 0 | AY24: 0 | BE24: 0 | BK24: 0 | BP24: Cumple | BQ24: 3 | BV24: Cumple | BW24: 2 | CC24: 0 | CH24: Cumple | CI24: 2 | CN24: Cumple | CO24: 2 | CU24: 0 | CZ24: Cumple | DA24: 2 | DF24: Cumple | DG24: 2 | DL24: Cumple | DM24: 3 | DR24: Cumple | DS24: 3 | DX24: Cumple | DY24: 3 | EE24: 0 | EJ24: Cumple | EK24: 2 | EP24: Cumple | EQ24: 2 | EW24: 0 | FB24: No cumple | FC24: 0 | FE24: camara de congelado , no cumple temperatura por lo tanto productos tampoco | FH24: Cumple | FI24: 2 | FN24: Cumple | FO24: 2 | FT24: Cumple | FU24: 2 | FZ24: Cumple | GA24: 2 | GF24: Cumple | GG24: 2 | GL24: Cumple | GM24: 2 | GR24: Cumple | GS24: 2 | GY24: 0 | HE24: 0 | HK24: 0 | HQ24: 0 | HW24: 0 | IC24: 0 | II24: 0 | IO24: 0 | IU24: 0 | JA24: 0 | JG24: 0 | JM24: 0 | JS24: 0 | JY24: 0
A25: 24 | B25: 45096.748 | C25: 45096.753 | D25: anonymous | F25: 42 | H25: Guadalupe | K25: 45096 | N25: Sharon | Q25: Angie Valverde | T25: Cumple | U25: 2 | Z25: Cumple | AA25: 2 | AF25: Cumple | AG25: 2 | AM25: 0 | AS25: 0 | AY25: 0 | BE25: 0 | BK25: 0 | BP25: Cumple | BQ25: 3 | BV25: Cumple | BW25: 2 | CC25: 0 | CH25: No cumple | CI25: 0 | CK25: dispensador de alcohol en mal estado , por lo tanto no hay sanitizacion de manos | CN25: Cumple | CO25: 2 | CU25: 0 | CZ25: No cumple | DA25: 0 | DC25: pañitos no estaban en sanitizante | DF25: Cumple | DG25: 2 | DL25: Cumple | DM25: 3 | DR25: Cumple | DS25: 3 | DX25: Cumple | DY25: 3 | EE25: 0 | EJ25: Cumple | EK25: 2 | EP25: Cumple | EQ25: 2 | EW25: 0 | FB25: No cumple | FC25: 0 | FE25: camara de congelado , refrigeracion y postres no cumple con la temperatura por lo tantos los alimentos almacenados ahi estan en zona de peligro | FH25: Cumple | FI25: 2 | FN25: Cumple | FO25: 2 | FT25: Cumple | FU25: 2 | FZ25: Cumple | GA25: 2 | GF25: Cumple | GG25: 2 | GL25: Cumple | GM25: 2 | GR25: Cumple | GS25: 2 | GY25: 0 | HE25: 0 | HK25: 0 | HQ25: 0 | HW25: 0 | IC25: 0 | II25: 0 | IO25: 0 | IU25: 0 | JA25: 0 | JG25: 0 | JM25: 0 | JS25: 0 | JY25: 0
A26: 25 | B26: 45097.784 | C26: 45097.79 | D26: anonymous | F26: 26 | H26: Multiplaza Curridabat | K26: 45097 | N26: Edwin | Q26: Angie Valverde | T26: No cumple | U26: 0 | W26: sin sanitizante | Z26: No Cumple | AA26: 0 | AC26: camara de frio tiene pollo crudo revuelto con frescos, postres y otros. paños de limpieza revueltos | AF26: Cumple | AG26: 2 | AM26: 0 | AS26: 0 | AY26: 0 | BE26: 0 | BK26: 0 | BP26: No cumple | BQ26: 0 | BS26: productos sobre piso , papas fritas. huevos encima de empaques | BV26: Cumple | BW26: 2 | CC26: 0 | CH26: No cumple | CI26: 0 | CK26: sin alcohol en los dispensadores | CN26: No cumple | CO26: 0 | CQ26: 2 bactogel vencidos. | CU26: 0 | CZ26: No cumple | DA26: 0 | DC26: sin sanitizante | DF26: Cumple | DG26: 2 | DL26: No cumple | DM26: 0 | DO26: basureros sin tapa | DR26: Cumple | DS26: 3 | DX26: Cumple | DY26: 3 | EE26: 0 | EJ26: No cumple | EK26: 0 | EM26: postres flan, empanizafor sin fechas | EP26: Cumple | EQ26: 2 | EW26: 0 | FB26: No cumple | FC26: 0 | FE26: camara de postres y mesas frias no tienen temperatura por lo tanto los productos estan en zona de peligro | FH26: No cumple | FI26: 0 | FK26: salsas estan sin hielo, a temperatura ambiente. | FN26: Cumple | FO26: 2 | FT26: Cumple | FU26: 2 | FZ26: Cumple | GA26: 2 | GF26: Cumple | GG26: 2 | GL26: Cumple | GM26: 2 | GR26: Cumple | GS26: 2 | GY26: 0 | HE26: 0 | HK26: 0 | HQ26: 0 | HW26: 0 | IC26: 0 | II26: 0 | IO26: 0 | IU26: 0 | JA26: 0 | JG26: 0 | JM26: 0 | JS26: 0 | JY26: 0
A27: 26 | B27: 45098.692 | C27: 45098.703 | D27: anonymous | F27: 35 | H27: Tibás | K27: 45098 | N27: Roberto | Q27: Angie Valverde | T27: Cumple | U27: 2 | Z27: Cumple | AA27: 2 | AF27: No cumple | AG27: 0 | AI27: se revisa las horas de la ultima monta de pollo y ya esta apuntada que salio a las 5 pm y son las 4 y 49 y hace rato se desmonto el pollo en conclusión datos falsos, | AM27: 0 | AS27: 0 | AY27: 0 | BE27: 0 | BK27: 0 | BP27: No cumple | BQ27: 0 | BS27: empanizador abierto, ademas de que hay producto derramado en el piso y salsas . | BV27: Cumple | BW27: 2 | CC27: 0 | CH27: No cumple | CI27: 0 | CK27: en lavamanos del lado de pollo crudo no hay jabon de manos | CN27: No cumple | CO27: 0 | CQ27: se encuentra cloro en pila | CU27: 0 | CZ27: Cumple | DA27: 2 | DF27: Cumple | DG27: 2 | DL27: Cumple | DM27: 3 | DR27: Cumple | DS27: 3 | DX27: Cumple | DY27: 3 | EE27: 0 | EJ27: No cumple | EK27: 0 | EM27: cebollitas dulces y picantes sin tapar, ademas se encuentra rostineta sin fechar | EP27: Cumple | EQ27: 2 | EW27: 0 | FB27: No cumple | FC27: 0 | FE27: hay camaras que no cumplen con temperatura por lo tanto los alimentos estan en una zona de peligro. ademas se encuentran salsas sin hielo a temperatura ambien y estas deben mantenerse en refrigeracion | FH27: Cumple | FI27: 2 | FN27: Cumple | FO27: 2 | FT27: Cumple | FU27: 2 | FZ27: Cumple | GA27: 2 | GF27: Cumple | GG27: 2 | GL27: Cumple | GM27: 2 | GR27: Cumple | GS27: 2 | GY27: 0 | HE27: 0 | HK27: 0 | HQ27: 0 | HW27: 0 | IC27: 0 | II27: 0 | IO27: 0 | IU27: 0 | JA27: 0 | JG27: 0 | JM27: 0 | JS27: 0 | JY27: 0
A28: 27 | B28: 45099.495 | C28: 45099.583 | D28: anonymous | F28: 46 | H28: Pinares | K28: 45099 | N28: Mario Meza | Q28: Nazira Herrera | T28: Cumple | U28: 2 | Z28: Cumple | AA28: 2 | AF28: No cumple | AG28: 0 | AI28: Hay montas con tiempos superiores a las 3 hrs y faltantes de montas o venta de pollo vencido. En el mes hay varias revisiones y comentarios de las correcciones sin embargo el problema persiste en días recientes a la visita (18-21/06) | AM28: 0 | AS28: 0 | AY28: 0 | BE28: 0 | BK28: 0 | BP28: Cumple | BQ28: 3 | BV28: Cumple | BW28: 2 | CC28: 0 | CH28: Cumple | CI28: 2 | CN28: Cumple | CO28: 2 | CU28: 0 | CZ28: Cumple | DA28: 2 | DF28: Cumple | DG28: 2 | DL28: Cumple | DM28: 3 | DR28: Cumple | DS28: 3 | DX28: Cumple | DY28: 3 | EE28: 0 | EJ28: Cumple | EK28: 2 | EP28: Cumple | EQ28: 2 | EW28: 0 | FB28: Cumple | FC28: 2 | FH28: Cumple | FI28: 2 | FN28: Cumple | FO28: 2 | FT28: Cumple | FU28: 2 | FZ28: Cumple | GA28: 2 | GF28: Cumple | GG28: 2 | GL28: Cumple | GM28: 2 | GR28: Cumple | GS28: 2 | GY28: 0 | HE28: 0 | HK28: 0 | HQ28: 0 | HW28: 0 | IC28: 0 | II28: 0 | IO28: 0 | IU28: 0 | JA28: 0 | JG28: 0 | JM28: 0 | JS28: 0 | JY28: 0 | KD28: Hay importantes mejoras en temas de limpieza, sin embargo falta detallar algunas áreas (tapas de congeladores, olla arrocera y horno, el cual requiere cualquier limpieza diaria). Se recomienda reubicar cámara de postres que se encuentra en la entrada principal, asi como el correcto llenado de registro de cocción del pollo que pese a las observaciones continúa con oportunidades de mejora.
A29: 28 | B29: 45103.683 | C29: 45103.692 | D29: anonymous | F29: 42 | H29: Escazú | K29: 45103 | N29: karla | Q29: Angie Valverde | T29: Cumple | U29: 2 | Z29: Cumple | AA29: 2 | AF29: Cumple | AG29: 2 | AM29: 0 | AS29: 0 | AY29: 0 | BE29: 0 | BK29: 0 | BP29: Cumple | BQ29: 3 | BV29: Cumple | BW29: 2 | CC29: 0 | CH29: Cumple | CI29: 2 | CN29: Cumple | CO29: 2 | CU29: 0 | CZ29: No cumple | DA29: 0 | DC29: no se encuentran con sanitizante | DF29: Cumple | DG29: 2 | DL29: Cumple | DM29: 3 | DR29: Cumple | DS29: 3 | DX29: Cumple | DY29: 3 | EE29: 0 | EJ29: Cumple | EK29: 2 | EP29: Cumple | EQ29: 2 | EW29: 0 | FB29: No cumple | FC29: 0 | FE29: se encuentran salsas sin hielo , a temperatura ambiente y camaras no cumplen con temperatura por lo tanto los productos estan en zona de peligro | FH29: Cumple | FI29: 2 | FN29: Cumple | FO29: 2 | FT29: Cumple | FU29: 2 | FZ29: No cumple | GA29: 0 | GC29: rebanada de cristal con presentacion del queque muy seco y deteriorado | GF29: Cumple | GG29: 2 | GL29: Cumple | GM29: 2 | GR29: Cumple | GS29: 2 | GY29: 0 | HE29: 0 | HK29: 0 | HQ29: 0 | HW29: 0 | IC29: 0 | II29: 0 | IO29: 0 | IU29: 0 | JA29: 0 | JG29: 0 | JM29: 0 | JS29: 0 | JY29: 0
A30: 29 | B30: 45103.656 | C30: 45103.731 | D30: anonymous | F30: 32 | H30: Heredia | K30: 45103 | N30: Angie Chacón | Q30: Nazira Herrera | T30: Cumple | U30: 2 | W30: No utilizar termómetro del freidor en sanitizante por temas de seguridad | Z30: No Cumple | AA30: 0 | AC30: Se utiliza trapo verde para limpieza de piso. Utensilios de limpieza de plancha con exceso de suciedad acumulada. | AF30: No cumple | AG30: 0 | AI30: Datos exactos en montas, desmontas y temperaturas de manera reincidentes. Faltan datos de montas del día 22/06. | AM30: 0 | AS30: 0 | AY30: 0 | BE30: 0 | BK30: 0 | BP30: No cumple | BQ30: 0 | BS30: La bodega está ordenada, sin embargo falta limpieza en recipiente de empanizador (interne y externa) | BV30: Cumple | BW30: 2 | CC30: 0 | CE30: Reforzar tema de barba con el personal. | CH30: Cumple | CI30: 2 | CN30: Cumple | CO30: 2 | CU30: 0 | CZ30: Cumple | DA30: 2 | DF30: No cumple | DG30: 0 | DI30: Falta ordenar área de lockers. Hay artículos fuera de los casilleros | DL30: No cumple | DM30: 0 | DO30: Exterior de los basureros requieren limpieza | DR30: Cumple | DS30: 3 | DX30: Cumple | DY30: 3 | EA30: Solicitar retiro de saco de cemento que quedó en el àrea por parte de mantenimiento. | EE30: 0 | EJ30: Cumple | EK30: 2 | EP30: Cumple | EQ30: 2 | EW30: 0 | FB30: Cumple | FC30: 2 | FH30: Cumple | FI30: 2 | FK30: No se utiliza bandeja de acero inoxidable para el proceso | FN30: Cumple | FO30: 2 | FT30: Cumple | FU30: 2 | FZ30: Cumple | GA30: 2 | GF30: No cumple | GG30: 0 | GI30: Cajas plásticas de almacenamiento de productos en cámaras de refrigeración requieren limpieza. Además realizar limpieza de suciedad acumulada debajo de la cámara de refrigeración (cervecería), correrla. | GL30: No cumple | GM30: 0 | GO30: Baño limpio, sin embargo se mantiene un rollo de papel higiénico sobre el sanitario y otro en el dispensador en uso. | GR30: Cumple | GS30: 2 | GY30: 0 | HE30: 0 | HK30: 0 | HQ30: 0 | HW30: 0 | IC30: 0 | II30: 0 | IO30: 0 | IU30: 0 | JA30: 0 | JG30: 0 | JM30: 0 | JS30: 0 | JY30: 0 | KD30: Hay mejoras evidentes en el orden y limpieza, sin embargo hace falta detallar las oportunidades identificadas. Revisar tema del registro de cocción de pollo.
A31: 30 | B31: 45104.567 | C31: 45104.573 | D31: anonymous | F31: 40 | H31: Real Alajuela | K31: 45104 | N31: Danny | Q31: Angie Valverde | T31: Cumple | U31: 2 | Z31: No Cumple | AA31: 0 | AC31: tienen empaques cerca de palopisos con aguas | AF31: Cumple | AG31: 2 | AM31: 0 | AS31: 0 | AY31: 0 | BE31: 0 | BK31: 0 | BP31: Cumple | BQ31: 3 | BV31: Cumple | BW31: 2 | CC31: 0 | CH31: Cumple | CI31: 2 | CN31: Cumple | CO31: 2 | CU31: 0 | CZ31: No cumple | DA31: 0 | DC31: pañitos no reacciona con solución sanitizante | DF31: Cumple | DG31: 2 | DL31: Cumple | DM31: 3 | DR31: Cumple | DS31: 3 | DX31: Cumple | DY31: 3 | EE31: 0 | EJ31: No cumple | EK31: 0 | EM31: se encuentra en mesa frias guacamole sin tapar | EP31: Cumple | EQ31: 2 | EW31: 0 | FB31: No cumple | FC31: 0 | FE31: se encuentra una bolsa de queso descongelando a temperatura ambiente sin seguir procedimiento adecuado. | FH31: Cumple | FI31: 2 | FN31: Cumple | FO31: 2 | FT31: Cumple | FU31: 2 | FZ31: Cumple | GA31: 2 | GF31: Cumple | GG31: 2 | GL31: Cumple | GM31: 2 | GR31: Cumple | GS31: 2 | GY31: 0 | HE31: 0 | HK31: 0 | HQ31: 0 | HW31: 0 | IC31: 0 | II31: 0 | IO31: 0 | IU31: 0 | JA31: 0 | JG31: 0 | JM31: 0 | JS31: 0 | JY31: 0
A32: 31 | B32: 45104.765 | C32: 45104.773 | D32: anonymous | F32: 41 | H32: City Mall | K32: 45104 | N32: Josue | Q32: Angie Valverde | T32: Cumple | U32: 2 | Z32: Cumple | AA32: 2 | AF32: Cumple | AG32: 2 | AM32: 0 | AS32: 0 | AY32: 0 | BE32: 0 | BK32: 0 | BP32: No cumple | BQ32: 0 | BS32: piso sucio con derrame de aceite | BV32: Cumple | BW32: 2 | CC32: 0 | CH32: Cumple | CI32: 2 | CN32: Cumple | CO32: 2 | CU32: 0 | CZ32: No cumple | DA32: 0 | DC32: los paños se encuentran si sanitizante | DF32: Cumple | DG32: 2 | DL32: Cumple | DM32: 3 | DR32: Cumple | DS32: 3 | DX32: Cumple | DY32: 3 | EE32: 0 | EJ32: Cumple | EK32: 2 | EP32: Cumple | EQ32: 2 | EW32: 0 | FB32: Cumple | FC32: 2 | FH32: Cumple | FI32: 2 | FN32: Cumple | FO32: 2 | FT32: No cumple | FU32: 0 | FW32: tabla guadada sucia en la camara, , pinsas de pollo en otro sitio, ademas el area , las paredes tienen pollo viejo pegado | FZ32: Cumple | GA32: 2 | GF32: Cumple | GG32: 2 | GL32: Cumple | GM32: 2 | GR32: Cumple | GS32: 2 | GY32: 0 | HE32: 0 | HK32: 0 | HQ32: 0 | HW32: 0 | IC32: 0 | II32: 0 | IO32: 0 | IU32: 0 | JA32: 0 | JG32: 0 | JM32: 0 | JS32: 0 | JY32: 0
A33: 32 | B33: 45105.568 | C33: 45105.573 | D33: anonymous | F33: 44 | H33: Sabana | K33: 45105 | N33: Ingrid | Q33: Angie Valverde | T33: No cumple | U33: 0 | W33: Sin sanitizante o sanitizante muy bajo | Z33: Cumple | AA33: 2 | AF33: Cumple | AG33: 2 | AM33: 0 | AS33: 0 | AY33: 0 | BE33: 0 | BK33: 0 | BP33: Cumple | BQ33: 3 | BV33: Cumple | BW33: 2 | CC33: 0 | CH33: Cumple | CI33: 2 | CN33: Cumple | CO33: 2 | CU33: 0 | CZ33: No cumple | DA33: 0 | DF33: Cumple | DG33: 2 | DL33: Cumple | DM33: 3 | DR33: Cumple | DS33: 3 | DX33: Cumple | DY33: 3 | EE33: 0 | EJ33: Cumple | EK33: 2 | EP33: Cumple | EQ33: 2 | EW33: 0 | FB33: Cumple | FC33: 2 | FH33: Cumple | FI33: 2 | FN33: Cumple | FO33: 2 | FT33: Cumple | FU33: 2 | FZ33: Cumple | GA33: 2 | GF33: Cumple | GG33: 2 | GL33: Cumple | GM33: 2 | GR33: Cumple | GS33: 2 | GY33: 0 | HE33: 0 | HK33: 0 | HQ33: 0 | HW33: 0 | IC33: 0 | II33: 0 | IO33: 0 | IU33: 0 | JA33: 0 | JG33: 0 | JM33: 0 | JS33: 0 | JY33: 0
A34: 33 | B34: 45105.744 | C34: 45105.747 | D34: anonymous | F34: 46 | H34: Real Cariari | K34: 45105 | N34: Victor | Q34: Angie Valverde | T34: Cumple | U34: 2 | Z34: Cumple | AA34: 2 | AF34: Cumple | AG34: 2 | AM34: 0 | AS34: 0 | AY34: 0 | BE34: 0 | BK34: 0 | BP34: Cumple | BQ34: 3 | BV34: Cumple | BW34: 2 | CC34: 0 | CH34: Cumple | CI34: 2 | CN34: Cumple | CO34: 2 | CU34: 0 | CZ34: Cumple | DA34: 2 | DF34: Cumple | DG34: 2 | DL34: Cumple | DM34: 3 | DR34: Cumple | DS34: 3 | DX34: Cumple | DY34: 3 | EE34: 0 | EJ34: No cumple | EK34: 0 | EM34: se encuentra guacamole sin fechar y descubierto, se encuentra repollo sin fechar | EP34: Cumple | EQ34: 2 | EW34: 0 | FB34: Cumple | FC34: 2 | FH34: Cumple | FI34: 2 | FN34: Cumple | FO34: 2 | FT34: Cumple | FU34: 2 | FZ34: Cumple | GA34: 2 | GF34: Cumple | GG34: 2 | GL34: Cumple | GM34: 2 | GR34: Cumple | GS34: 2 | GY34: 0 | HE34: 0 | HK34: 0 | HQ34: 0 | HW34: 0 | IC34: 0 | II34: 0 | IO34: 0 | IU34: 0 | JA34: 0 | JG34: 0 | JM34: 0 | JS34: 0 | JY34: 0
A35: 34 | B35: 45106.583 | C35: 45106.619 | D35: anonymous | F35: 44 | H35: Santa Ana | K35: 45106 | N35: Irving Salas | Q35: Nazira Herrera | T35: Cumple | U35: 2 | Z35: Cumple | AA35: 2 | AF35: Cumple | AG35: 2 | AM35: 0 | AS35: 0 | AY35: 0 | BE35: 0 | BK35: 0 | BP35: Cumple | BQ35: 3 | BV35: Cumple | BW35: 2 | CC35: 0 | CH35: No cumple | CI35: 0 | CK35: Los lavamanos tanto de salón como de cocina se utilizan como apoyo a procesos de elaboración de productos. Hay residuos en los mismos. Destacar que el intermedio solo tiene esa pila y si es requerida para labores del salón. | CN35: Cumple | CO35: 2 | CU35: 0 | CZ35: Cumple | DA35: 2 | DF35: Cumple | DG35: 2 | DL35: Cumple | DM35: 3 | DR35: Cumple | DS35: 3 | DU35: Gestionar retiro de cajas plásticas de área externa (parte trasera) | DX35: Cumple | DY35: 3 | EE35: 0 | EJ35: Cumple | EK35: 2 | EP35: Cumple | EQ35: 2 | EW35: 0 | FB35: Cumple | FC35: 2 | FH35: Cumple | FI35: 2 | FN35: Cumple | FO35: 2 | FT35: Cumple | FU35: 2 | FZ35: No cumple | GA35: 0 | GC35: Queque Cristal no cuenta con estandar de decoración establecido (cristales de caramelo muy pequeños) | GF35: Cumple | GG35: 2 | GL35: Cumple | GM35: 2 | GR35: Cumple | GS35: 2 | GY35: 0 | HE35: 0 | HK35: 0 | HQ35: 0 | HW35: 0 | IC35: 0 | II35: 0 | IO35: 0 | IU35: 0 | JA35: 0 | JG35: 0 | JM35: 0 | JS35: 0 | JY35: 0 | KD35: Durante la visita se identifica el faltante de queso mozarella, por lo que todos los platillos se elaboran con queso parmesano (aliñadas, rosters, todo menú birrira). Se solicita cambio de aceite de freidor oscuro ya que se encuentra muy por fuera del límite superior (35.5 %). Realizar limpieza de la parte exterior de olla arrocera, tablas de mesa fría y horno. Además detallar en proceso de preparación de empanadas para que no se salga el relleno. Trabajar en las oportunidades identificadas en el libro del mes en registro de cocción de pollo.
A36: 35 | B36: 45106.62 | C36: 45106.651 | D36: anonymous | F36: 42 | H36: Alajuela | K36: 45106 | N36: Eduard | Q36: Angie Valverde | T36: Cumple | U36: 2 | Z36: Cumple | AA36: 2 | AF36: Cumple | AG36: 2 | AI36: por favor mantener mas el orden en el libro | AM36: 0 | AS36: 0 | AY36: 0 | BE36: 0 | BK36: 0 | BP36: Cumple | BQ36: 3 | BV36: Cumple | BW36: 2 | CC36: 0 | CH36: Cumple | CI36: 2 | CN36: Cumple | CO36: 2 | CU36: 0 | CZ36: No cumple | DA36: 0 | DC36: se encuentran algunos con la solucion sanitizante muy baja y otros no reaccionaron | DF36: Cumple | DG36: 2 | DL36: Cumple | DM36: 3 | DR36: Cumple | DS36: 3 | DX36: Cumple | DY36: 3 | EE36: 0 | EJ36: Cumple | EK36: 2 | EP36: Cumple | EQ36: 2 | EW36: 0 | FB36: No cumple | FC36: 0 | FE36: las mesas frias no cumplen con la temperatura por lo tantos los alimentos almacenados ahi estan en zona de peligro | FH36: Cumple | FI36: 2 | FN36: Cumple | FO36: 2 | FT36: No cumple | FU36: 0 | FW36: camara de pollo crudo se encuentra sucia por fuera especialmente en sus puertas además el quipo para cortar pollo, cuchillos y tablas estan sucios. | FZ36: Cumple | GA36: 2 | GF36: Cumple | GG36: 2 | GL36: Cumple | GM36: 2 | GR36: Cumple | GS36: 2 | GY36: 0 | HE36: 0 | HK36: 0 | HQ36: 0 | HW36: 0 | IC36: 0 | II36: 0 | IO36: 0 | IU36: 0 | JA36: 0 | JG36: 0 | JM36: 0 | JS36: 0 | JY36: 0
A37: 36 | B37: 45107.543 | C37: 45107.544 | D37: anonymous | F37: 44 | H37: FC Pueblo Antiguo | K37: 45107 | N37: Daniel | Q37: Angie Valverde | T37: Cumple | U37: 2 | Z37: No Cumple | AA37: 0 | AC37: Pollo crudo donde almacenan otros productos | AF37: Cumple | AG37: 2 | AM37: 0 | AS37: 0 | AY37: 0 | BE37: 0 | BK37: 0 | BP37: Cumple | BQ37: 3 | BV37: Cumple | BW37: 2 | CC37: 0 | CH37: Cumple | CI37: 2 | CN37: Cumple | CO37: 2 | CU37: 0 | CZ37: Cumple | DA37: 2 | DF37: Cumple | DG37: 2 | DL37: Cumple | DM37: 3 | DR37: Cumple | DS37: 3 | DX37: Cumple | DY37: 3 | EE37: 0 | EJ37: No cumple | EK37: 0 | EM37: Se encuentra un pico de gallo sin tapar | EP37: Cumple | EQ37: 2 | EW37: 0 | FB37: Cumple | FC37: 2 | FH37: Cumple | FI37: 2 | FN37: Cumple | FO37: 2 | FT37: Cumple | FU37: 2 | FZ37: Cumple | GA37: 2 | GF37: Cumple | GG37: 2 | GL37: Cumple | GM37: 2 | GR37: Cumple | GS37: 2 | GY37: 0 | HE37: 0 | HK37: 0 | HQ37: 0 | HW37: 0 | IC37: 0 | II37: 0 | IO37: 0 | IU37: 0 | JA37: 0 | JG37: 0 | JM37: 0 | JS37: 0 | JY37: 0
A38: 37 | B38: 45110.55 | C38: 45110.563 | D38: anonymous | F38: 40 | H38: Multiplaza Escazú | K38: 45110 | N38: maricela | Q38: Angie Valverde | T38: No cumple | U38: 0 | W38: termómetro sin sanitizante | Z38: Cumple | AA38: 2 | AF38: No cumple | AG38: 0 | AI38: no tienen libro, y tienen lleno hasta el 1 de julio, no estan los registros de 2 dias | AM38: 0 | AS38: 0 | AY38: 0 | BE38: 0 | BK38: 0 | BP38: Cumple | BQ38: 3 | BV38: Cumple | BW38: 2 | CC38: 0 | CH38: Cumple | CI38: 2 | CN38: Cumple | CO38: 2 | CU38: 0 | CZ38: No cumple | DA38: 0 | DC38: pañitos y utensilios sin sanitizante | DF38: Cumple | DG38: 2 | DL38: Cumple | DM38: 3 | DR38: Cumple | DS38: 3 | DX38: Cumple | DY38: 3 | EE38: 0 | EJ38: No cumple | EK38: 0 | EM38: se encuentra repollo, ensalada de repollo , sin fechar, y pico de gallo , frescos sin tapar | EP38: Cumple | EQ38: 2 | EW38: 0 | FB38: Cumple | FC38: 2 | FH38: Cumple | FI38: 2 | FN38: Cumple | FO38: 2 | FT38: Cumple | FU38: 2 | FZ38: Cumple | GA38: 2 | GF38: Cumple | GG38: 2 | GL38: Cumple | GM38: 2 | GR38: Cumple | GS38: 2 | GY38: 0 | HE38: 0 | HK38: 0 | HQ38: 0 | HW38: 0 | IC38: 0 | II38: 0 | IO38: 0 | IU38: 0 | JA38: 0 | JG38: 0 | JM38: 0 | JS38: 0 | JY38: 0
A39: 38 | B39: 45111.592 | C39: 45111.604 | D39: anonymous | F39: 44 | H39: Curridabat | K39: 45111 | N39: Dayanna | Q39: Angie Valverde | T39: Cumple | U39: 2 | Z39: No Cumple | AA39: 0 | AC39: se encuentra cloro , y este esta encima de empanizador. | AF39: Cumple | AG39: 2 | AI39: no se acepta corrector ni tachones , por favor mejorar eso | AM39: 0 | AS39: 0 | AY39: 0 | BE39: 0 | BK39: 0 | BP39: Cumple | BQ39: 3 | BV39: Cumple | BW39: 2 | CC39: 0 | CH39: Cumple | CI39: 2 | CN39: No cumple | CO39: 0 | CQ39: cloro se encuentra en área de preparación y no bajo llave | CU39: 0 | CZ39: Cumple | DA39: 2 | DF39: Cumple | DG39: 2 | DL39: Cumple | DM39: 3 | DR39: Cumple | DS39: 3 | DX39: Cumple | DY39: 3 | EE39: 0 | EJ39: Cumple | EK39: 2 | EP39: Cumple | EQ39: 2 | EW39: 0 | FB39: Cumple | FC39: 2 | FH39: Cumple | FI39: 2 | FN39: Cumple | FO39: 2 | FT39: Cumple | FU39: 2 | FZ39: Cumple | GA39: 2 | GF39: Cumple | GG39: 2 | GL39: Cumple | GM39: 2 | GR39: Cumple | GS39: 2 | GY39: 0 | HE39: 0 | HK39: 0 | HQ39: 0 | HW39: 0 | IC39: 0 | II39: 0 | IO39: 0 | IU39: 0 | JA39: 0 | JG39: 0 | JM39: 0 | JS39: 0 | JY39: 0
A40: 39 | B40: 45113.824 | C40: 45113.832 | D40: anonymous | F40: 41 | H40: Pinares | K40: 45113 | N40: Marco | Q40: Angie Valverde | T40: Cumple | U40: 2 | Z40: Cumple | AA40: 2 | AF40: No cumple | AG40: 0 | AI40: registro del pollo esta incompleto , ultima monta fue a las 4 pm | AM40: 0 | AS40: 0 | AY40: 0 | BE40: 0 | BK40: 0 | BP40: Cumple | BQ40: 3 | BV40: Cumple | BW40: 2 | CC40: 0 | CH40: Cumple | CI40: 2 | CN40: Cumple | CO40: 2 | CU40: 0 | CZ40: Cumple | DA40: 2 | DF40: Cumple | DG40: 2 | DL40: Cumple | DM40: 3 | DR40: No cumple | DS40: 0 | DU40: area de atras del restaurante tiene muchos galones de aceite y otras cosas | DX40: Cumple | DY40: 3 | EE40: 0 | EJ40: No cumple | EK40: 0 | EM40: se encuentra caldo de pollo y pollo desmenuzado sin fechar | EP40: Cumple | EQ40: 2 | EW40: 0 | FB40: Cumple | FC40: 2 | FH40: Cumple | FI40: 2 | FN40: Cumple | FO40: 2 | FT40: Cumple | FU40: 2 | FZ40: Cumple | GA40: 2 | GF40: Cumple | GG40: 2 | GL40: Cumple | GM40: 2 | GR40: Cumple | GS40: 2 | GY40: 0 | HE40: 0 | HK40: 0 | HQ40: 0 | HW40: 0 | IC40: 0 | II40: 0 | IO40: 0 | IU40: 0 | JA40: 0 | JG40: 0 | JM40: 0 | JS40: 0 | JY40: 0
A41: 40 | B41: 45114.721 | C41: 45114.731 | D41: anonymous | F41: 42 | H41: Guadalupe | K41: 45114 | N41: Axel | Q41: Angie Valverde | T41: Cumple | U41: 2 | Z41: Cumple | AA41: 2 | AF41: Cumple | AG41: 2 | AM41: 0 | AS41: 0 | AY41: 0 | BE41: 0 | BK41: 0 | BP41: Cumple | BQ41: 3 | BV41: Cumple | BW41: 2 | CC41: 0 | CH41: Cumple | CI41: 2 | CN41: Cumple | CO41: 2 | CU41: 0 | CZ41: Cumple | DA41: 2 | DF41: Cumple | DG41: 2 | DL41: Cumple | DM41: 3 | DR41: Cumple | DS41: 3 | DX41: Cumple | DY41: 3 | EE41: 0 | EJ41: No cumple | EK41: 0 | EM41: se encuentra fresco de cas sin fechar | EP41: Cumple | EQ41: 2 | EW41: 0 | FB41: No cumple | FC41: 0 | FE41: camaras de postres y congelado no cumple con temperatura por lo tanto producto se encuentra en zona de peligro | FH41: Cumple | FI41: 2 | FN41: Cumple | FO41: 2 | FT41: No cumple | FU41: 0 | FW41: se encuentra pollo para rostifrijo sin fechar | FZ41: Cumple | GA41: 2 | GF41: Cumple | GG41: 2 | GL41: Cumple | GM41: 2 | GR41: Cumple | GS41: 2 | GY41: 0 | HE41: 0 | HK41: 0 | HQ41: 0 | HW41: 0 | IC41: 0 | II41: 0 | IO41: 0 | IU41: 0 | JA41: 0 | JG41: 0 | JM41: 0 | JS41: 0 | JY41: 0
A42: 41 | B42: 45117.587 | C42: 45117.595 | D42: anonymous | F42: 46 | H42: Desamparados | K42: 45117 | N42: Sonia | Q42: Angie Valverde | T42: Cumple | U42: 2 | Z42: Cumple | AA42: 2 | AF42: Cumple | AG42: 2 | AM42: 0 | AS42: 0 | AY42: 0 | BE42: 0 | BK42: 0 | BP42: Cumple | BQ42: 3 | BV42: Cumple | BW42: 2 | CC42: 0 | CH42: Cumple | CI42: 2 | CN42: Cumple | CO42: 2 | CU42: 0 | CZ42: Cumple | DA42: 2 | DF42: Cumple | DG42: 2 | DL42: Cumple | DM42: 3 | DR42: Cumple | DS42: 3 | DX42: Cumple | DY42: 3 | EE42: 0 | EJ42: Cumple | EK42: 2 | EP42: Cumple | EQ42: 2 | EW42: 0 | FB42: Cumple | FC42: 2 | FH42: Cumple | FI42: 2 | FN42: Cumple | FO42: 2 | FT42: No cumple | FU42: 0 | FW42: se encuentra unas bolsas de pollo para piqueo sin fechar | FZ42: Cumple | GA42: 2 | GF42: Cumple | GG42: 2 | GL42: Cumple | GM42: 2 | GR42: Cumple | GS42: 2 | GY42: 0 | HE42: 0 | HK42: 0 | HQ42: 0 | HW42: 0 | IC42: 0 | II42: 0 | IO42: 0 | IU42: 0 | JA42: 0 | JG42: 0 | JM42: 0 | JS42: 0 | JY42: 0
A43: 42 | B43: 45117.83 | C43: 45117.84 | D43: anonymous | F43: 43 | H43: Escazú | K43: 45117 | N43: Karla | Q43: Angie Valverde | T43: Cumple | U43: 2 | Z43: Cumple | AA43: 2 | AF43: Cumple | AG43: 2 | AM43: 0 | AS43: 0 | AY43: 0 | BE43: 0 | BK43: 0 | BP43: No cumple | BQ43: 0 | BS43: se encuentra mala rotacion en PEPS, con la salsa de frijol | BV43: Cumple | BW43: 2 | CC43: 0 | CH43: Cumple | CI43: 2 | CN43: Cumple | CO43: 2 | CU43: 0 | CZ43: Cumple | DA43: 2 | DF43: Cumple | DG43: 2 | DL43: Cumple | DM43: 3 | DR43: Cumple | DS43: 3 | DX43: Cumple | DY43: 3 | EE43: 0 | EJ43: Cumple | EK43: 2 | EP43: Cumple | EQ43: 2 | EW43: 0 | FB43: No cumple | FC43: 0 | FE43: camara de congelado, camara de postres , camara de refrigeracion y mesas frias no cumplen con temperatura por lo tanto los productos que se almacenan ahi estan en zona de peligro | FH43: Cumple | FI43: 2 | FN43: Cumple | FO43: 2 | FT43: Cumple | FU43: 2 | FZ43: Cumple | GA43: 2 | GF43: Cumple | GG43: 2 | GL43: Cumple | GM43: 2 | GR43: Cumple | GS43: 2 | GY43: 0 | HE43: 0 | HK43: 0 | HQ43: 0 | HW43: 0 | IC43: 0 | II43: 0 | IO43: 0 | IU43: 0 | JA43: 0 | JG43: 0 | JM43: 0 | JS43: 0 | JY43: 0
A44: 43 | B44: 45118.503 | C44: 45118.504 | D44: anonymous | F44: 46 | H44: FC Pueblo Antiguo | K44: 45118 | N44: Luis | Q44: Angie Valverde | T44: Cumple | U44: 2 | Z44: Cumple | AA44: 2 | AF44: Cumple | AG44: 2 | AM44: 0 | AS44: 0 | AY44: 0 | BE44: 0 | BK44: 0 | BP44: Cumple | BQ44: 3 | BV44: Cumple | BW44: 2 | CC44: 0 | CH44: Cumple | CI44: 2 | CN44: Cumple | CO44: 2 | CU44: 0 | CZ44: Cumple | DA44: 2 | DF44: Cumple | DG44: 2 | DL44: Cumple | DM44: 3 | DR44: Cumple | DS44: 3 | DX44: Cumple | DY44: 3 | EE44: 0 | EJ44: No cumple | EK44: 0 | EM44: Se encuentra pollo de desmenuzado sin fechar | EP44: Cumple | EQ44: 2 | EW44: 0 | FB44: Cumple | FC44: 2 | FH44: Cumple | FI44: 2 | FN44: Cumple | FO44: 2 | FT44: Cumple | FU44: 2 | FZ44: Cumple | GA44: 2 | GF44: Cumple | GG44: 2 | GL44: Cumple | GM44: 2 | GR44: Cumple | GS44: 2 | GY44: 0 | HE44: 0 | HK44: 0 | HQ44: 0 | HW44: 0 | IC44: 0 | II44: 0 | IO44: 0 | IU44: 0 | JA44: 0 | JG44: 0 | JM44: 0 | JS44: 0 | JY44: 0
A45: 44 | B45: 45118.574 | C45: 45118.579 | D45: anonymous | F45: 46 | H45: San José | K45: 45118 | N45: Diana | Q45: Angie Valverde | T45: Cumple | U45: 2 | Z45: Cumple | AA45: 2 | AF45: Cumple | AG45: 2 | AM45: 0 | AS45: 0 | AY45: 0 | BE45: 0 | BK45: 0 | BP45: Cumple | BQ45: 3 | BV45: Cumple | BW45: 2 | CC45: 0 | CH45: Cumple | CI45: 2 | CN45: Cumple | CO45: 2 | CU45: 0 | CZ45: Cumple | DA45: 2 | DF45: Cumple | DG45: 2 | DL45: Cumple | DM45: 3 | DR45: Cumple | DS45: 3 | DX45: Cumple | DY45: 3 | EE45: 0 | EJ45: Cumple | EK45: 2 | EP45: Cumple | EQ45: 2 | EW45: 0 | FB45: No cumple | FC45: 0 | FE45: hay equiposque nocumplen con temperatura por lo tanto hay productos en zona de peligro | FH45: Cumple | FI45: 2 | FN45: Cumple | FO45: 2 | FT45: Cumple | FU45: 2 | FZ45: Cumple | GA45: 2 | GF45: Cumple | GG45: 2 | GL45: Cumple | GM45: 2 | GR45: Cumple | GS45: 2 | GY45: 0 | HE45: 0 | HK45: 0 | HQ45: 0 | HW45: 0 | IC45: 0 | II45: 0 | IO45: 0 | IU45: 0 | JA45: 0 | JG45: 0 | JM45: 0 | JS45: 0 | JY45: 0
A46: 45 | B46: 45118.537 | C46: 45118.579 | D46: anonymous | F46: 41 | H46: Terramall | K46: 45118 | N46: Andrea Angulo | Q46: Nazira Herrera | T46: Cumple | U46: 2 | Z46: Cumple | AA46: 2 | AF46: No cumple | AG46: 0 | AI46: Faltan datos del día 06/07 (última desmonta 3:20 pm). El día de la visita 11/07 al ser la 1:00 pm no hay datos registrados de las montas realizadas. | AM46: 0 | AS46: 0 | AY46: 0 | BE46: 0 | BK46: 0 | BP46: No cumple | BQ46: 0 | BS46: Realizar limpieza de cajas y recipientes de almacenamiento. | BV46: Cumple | BW46: 2 | CC46: 0 | CH46: Cumple | CI46: 2 | CN46: Cumple | CO46: 2 | CU46: 0 | CZ46: Cumple | DA46: 2 | DF46: Cumple | DG46: 2 | DL46: Cumple | DM46: 3 | DR46: Cumple | DS46: 3 | DX46: Cumple | DY46: 3 | EE46: 0 | EJ46: No cumple | EK46: 0 | EP46: Cumple | EQ46: 2 | EW46: 0 | FB46: Cumple | FC46: 2 | FH46: Cumple | FI46: 2 | FN46: Cumple | FO46: 2 | FT46: Cumple | FU46: 2 | FZ46: Cumple | GA46: 2 | GF46: Cumple | GG46: 2 | GL46: Cumple | GM46: 2 | GR46: Cumple | GS46: 2 | GY46: 0 | HE46: 0 | HK46: 0 | HQ46: 0 | HW46: 0 | IC46: 0 | II46: 0 | IO46: 0 | IU46: 0 | JA46: 0 | JG46: 0 | JM46: 0 | JS46: 0 | JY46: 0 | KD46: Muy buenas condiciones de orden y limpieza. Dar seguimiento al tema del registro de monta de pollo.
A47: 46 | B47: 45119.644 | C47: 45119.646 | D47: anonymous | F47: 45 | H47: Real Alajuela | K47: 45119 | N47: Danny | Q47: Angie Valverde | T47: Cumple | U47: 2 | Z47: Cumple | AA47: 2 | AF47: Cumple | AG47: 2 | AM47: 0 | AS47: 0 | AY47: 0 | BE47: 0 | BK47: 0 | BP47: No cumple | BQ47: 0 | BS47: bodega esta desordenada y ademas tienen cajas en el piso | BV47: Cumple | BW47: 2 | CC47: 0 | CH47: Cumple | CI47: 2 | CN47: Cumple | CO47: 2 | CU47: 0 | CZ47: Cumple | DA47: 2 | DF47: Cumple | DG47: 2 | DL47: Cumple | DM47: 3 | DR47: Cumple | DS47: 3 | DX47: Cumple | DY47: 3 | EE47: 0 | EJ47: Cumple | EK47: 2 | EP47: Cumple | EQ47: 2 | EW47: 0 | FB47: Cumple | FC47: 2 | FH47: Cumple | FI47: 2 | FN47: Cumple | FO47: 2 | FT47: Cumple | FU47: 2 | FZ47: Cumple | GA47: 2 | GF47: Cumple | GG47: 2 | GL47: Cumple | GM47: 2 | GR47: Cumple | GS47: 2 | GY47: 0 | HE47: 0 | HK47: 0 | HQ47: 0 | HW47: 0 | IC47: 0 | II47: 0 | IO47: 0 | IU47: 0 | JA47: 0 | JG47: 0 | JM47: 0 | JS47: 0 | JY47: 0
A48: 47 | B48: 45120.542 | C48: 45120.625 | D48: anonymous | F48: 42 | H48: Heredia | K48: 45120 | N48: Yoryanela Vargas | Q48: Nazira Herrera | T48: Cumple | U48: 2 | W48: Se recomienda no mantener termómetro de freidor en solución sanitizante por temas de seguridad. | Z48: No Cumple | AA48: 0 | AC48: Cuchillos amarillos mal almacenados (prensados entre mesa de trabajo y pared) | AF48: No cumple | AG48: 0 | AI48: Datos poco confiables, no hay variación de datos. Horas de montas, desmontas y temperaras siempre iguales. | AM48: 0 | AS48: 0 | AY48: 0 | BE48: 0 | BK48: 0 | BP48: Cumple | BQ48: 3 | BV48: Cumple | BW48: 2 | CC48: 0 | CH48: Cumple | CI48: 2 | CN48: Cumple | CO48: 2 | CU48: 0 | CZ48: Cumple | DA48: 2 | DF48: Cumple | DG48: 2 | DL48: Cumple | DM48: 3 | DR48: Cumple | DS48: 3 | DX48: Cumple | DY48: 3 | EE48: 0 | EJ48: Cumple | EK48: 2 | EP48: Cumple | EQ48: 2 | EW48: 0 | FB48: Cumple | FC48: 2 | FH48: No cumple | FI48: 0 | FK48: No se realiza enfriamiento adecuado de los productos. hielo no cubre las paredes del recipiente. | FN48: Cumple | FO48: 2 | FT48: Cumple | FU48: 2 | FZ48: Cumple | GA48: 2 | GF48: Cumple | GG48: 2 | GL48: Cumple | GM48: 2 | GR48: Cumple | GS48: 2 | GY48: 0 | HE48: 0 | HK48: 0 | HQ48: 0 | HW48: 0 | IC48: 0 | II48: 0 | IO48: 0 | IU48: 0 | JA48: 0 | JG48: 0 | JM48: 0 | JS48: 0 | JY48: 0 | KD48: Dar seguimiento al llenado correcto de registro de montas de pollo.
A49: 48 | B49: 45125.62 | C49: 45125.627 | D49: anonymous | F49: 40 | H49: Coronado | K49: 45125 | N49: Graciela | Q49: Angie Valverde | T49: Cumple | U49: 2 | Z49: Cumple | AA49: 2 | AF49: No cumple | AG49: 0 | AI49: faltan datos de montas del dia de hoy | AM49: 0 | AS49: 0 | AY49: 0 | BE49: 0 | BK49: 0 | BP49: Cumple | BQ49: 3 | BV49: No cumple | BW49: 0 | CC49: 0 | CE49: ayudantes de servicio y salonera portn aretes | CH49: Cumple | CI49: 2 | CN49: Cumple | CO49: 2 | CU49: 0 | CZ49: No cumple | DA49: 0 | DC49: al momento de hacer la medicion no cumplen con sanitizante | DF49: Cumple | DG49: 2 | DL49: Cumple | DM49: 3 | DR49: Cumple | DS49: 3 | DX49: Cumple | DY49: 3 | EE49: 0 | EJ49: Cumple | EK49: 2 | EP49: Cumple | EQ49: 2 | EW49: 0 | FB49: Cumple | FC49: 2 | FH49: Cumple | FI49: 2 | FN49: Cumple | FO49: 2 | FT49: Cumple | FU49: 2 | FZ49: Cumple | GA49: 2 | GF49: Cumple | GG49: 2 | GL49: Cumple | GM49: 2 | GR49: No cumple | GS49: 0 | GY49: 0 | HE49: 0 | HK49: 0 | HQ49: 0 | HW49: 0 | IC49: 0 | II49: 0 | IO49: 0 | IU49: 0 | JA49: 0 | JG49: 0 | JM49: 0 | JS49: 0 | JY49: 0
A50: 49 | B50: 45127.64 | C50: 45127.663 | D50: anonymous | F50: 42 | H50: Cartago | K50: 45127 | N50: Grettel | Q50: Angie Valverde | T50: Cumple | U50: 2 | Z50: Cumple | AA50: 2 | AF50: Cumple | AG50: 2 | AM50: 0 | AS50: 0 | AY50: 0 | BE50: 0 | BK50: 0 | BP50: Cumple | BQ50: 3 | BV50: No cumple | BW50: 0 | CC50: 0 | CE50: alfredo porta anillo | CH50: Cumple | CI50: 2 | CN50: Cumple | CO50: 2 | CU50: 0 | CZ50: Cumple | DA50: 2 | DF50: Cumple | DG50: 2 | DL50: Cumple | DM50: 3 | DR50: Cumple | DS50: 3 | DX50: Cumple | DY50: 3 | EE50: 0 | EJ50: No cumple | EK50: 0 | EM50: se encuentra fresco sin tapar en refrigerador | EP50: Cumple | EQ50: 2 | EW50: 0 | FB50: No cumple | FC50: 0 | FE50: hay camaras que no cumplen temperatura por lo tanto hay productos en zona de peligro | FH50: Cumple | FI50: 2 | FN50: Cumple | FO50: 2 | FT50: Cumple | FU50: 2 | FZ50: Cumple | GA50: 2 | GF50: Cumple | GG50: 2 | GL50: Cumple | GM50: 2 | GR50: Cumple | GS50: 2 | GY50: 0 | HE50: 0 | HK50: 0 | HQ50: 0 | HW50: 0 | IC50: 0 | II50: 0 | IO50: 0 | IU50: 0 | JA50: 0 | JG50: 0 | JM50: 0 | JS50: 0 | JY50: 0
A51: 50 | B51: 45127.654 | C51: 45127.716 | D51: anonymous | F51: 44 | H51: City Mall | K51: 45127 | N51: Patricia | Q51: Nazira Herrera | T51: Cumple | U51: 2 | Z51: No Cumple | AA51: 0 | AC51: Mal almacenamiento y ubicación de productos: alas de pollo cocinadas junto a cebolla y chile dulce crudo. Arroz con pollo porcionado sobre recipiente de pasta de pollo caliente (aumenta de temperatura), chalupas destapadas almacenadas junto a abanico muy muy sucio (partículas de polvo). Uso de recipiente plástico para almacenamiento de pechugas en holding. | AF51: Cumple | AG51: 2 | AM51: 0 | AS51: 0 | AY51: 0 | BE51: 0 | BK51: 0 | BP51: Cumple | BQ51: 3 | BV51: Cumple | BW51: 2 | CC51: 0 | CH51: Cumple | CI51: 2 | CN51: Cumple | CO51: 2 | CU51: 0 | CZ51: Cumple | DA51: 2 | DF51: Cumple | DG51: 2 | DL51: Cumple | DM51: 3 | DR51: Cumple | DS51: 3 | DX51: Cumple | DY51: 3 | EE51: 0 | EJ51: No cumple | EK51: 0 | EM51: Chalupas destapadas. | EP51: Cumple | EQ51: 2 | EW51: 0 | FB51: Cumple | FC51: 2 | FH51: Cumple | FI51: 2 | FN51: Cumple | FO51: 2 | FT51: Cumple | FU51: 2 | FZ51: Cumple | GA51: 2 | GF51: Cumple | GG51: 2 | GL51: Cumple | GM51: 2 | GO51: Se recomienda hacer una revisión y limpieza posterior a las 2:00 pm para hacer ajustes en orden y limpieza de los baños | GR51: Cumple | GS51: 2 | GY51: 0 | HE51: 0 | HK51: 0 | HQ51: 0 | HW51: 0 | IC51: 0 | II51: 0 | IO51: 0 | IU51: 0 | JA51: 0 | JG51: 0 | JM51: 0 | JS51: 0 | JY51: 0 | KD51: Importante realizar tareas de limpieza profunda posterior a periodo de vacaciones (temporada alta). Verificar manejo de productos, rotación y vida útil.
A52: 51 | B52: 45128.636 | C52: 45128.643 | D52: anonymous | F52: 43 | H52: Tibás | K52: 45128 | N52: Eliecer | Q52: Angie Valverde | T52: Cumple | U52: 2 | Z52: Cumple | AA52: 2 | AF52: Cumple | AG52: 2 | AM52: 0 | AS52: 0 | AY52: 0 | BE52: 0 | BK52: 0 | BP52: No cumple | BQ52: 0 | BS52: bodega sucia el piso | BV52: Cumple | BW52: 2 | CC52: 0 | CH52: Cumple | CI52: 2 | CN52: Cumple | CO52: 2 | CU52: 0 | CZ52: Cumple | DA52: 2 | DF52: Cumple | DG52: 2 | DL52: Cumple | DM52: 3 | DR52: Cumple | DS52: 3 | DX52: Cumple | DY52: 3 | EE52: 0 | EJ52: Cumple | EK52: 2 | EP52: Cumple | EQ52: 2 | EW52: 0 | FB52: No cumple | FC52: 0 | FE52: camaras de frio, mesas frias, camara de postres y camara de congelado no cumplen con temperatura por lo tanto hay productos en zona de riesgo | FH52: Cumple | FI52: 2 | FN52: Cumple | FO52: 2 | FT52: Cumple | FU52: 2 | FZ52: Cumple | GA52: 2 | GF52: Cumple | GG52: 2 | GL52: Cumple | GM52: 2 | GR52: Cumple | GS52: 2 | GY52: 0 | HE52: 0 | HK52: 0 | HQ52: 0 | HW52: 0 | IC52: 0 | II52: 0 | IO52: 0 | IU52: 0 | JA52: 0 | JG52: 0 | JM52: 0 | JS52: 0 | JY52: 0
A53: 52 | B53: 45132.631 | C53: 45132.634 | D53: anonymous | F53: 46 | H53: Alajuela | K53: 45132 | N53: Oscar | Q53: Angie Valverde | T53: Cumple | U53: 2 | Z53: Cumple | AA53: 2 | AF53: Cumple | AG53: 2 | AM53: 0 | AS53: 0 | AY53: 0 | BE53: 0 | BK53: 0 | BP53: Cumple | BQ53: 3 | BV53: Cumple | BW53: 2 | CC53: 0 | CH53: Cumple | CI53: 2 | CN53: Cumple | CO53: 2 | CU53: 0 | CZ53: Cumple | DA53: 2 | DF53: Cumple | DG53: 2 | DL53: Cumple | DM53: 3 | DR53: Cumple | DS53: 3 | DX53: Cumple | DY53: 3 | EE53: 0 | EJ53: No cumple | EK53: 0 | EM53: se encuentran postres cheecake dulce de leche sin fechar y baby cristal con etiqueta de otro producto | EP53: Cumple | EQ53: 2 | EW53: 0 | FB53: Cumple | FC53: 2 | FH53: Cumple | FI53: 2 | FN53: Cumple | FO53: 2 | FT53: Cumple | FU53: 2 | FZ53: Cumple | GA53: 2 | GF53: Cumple | GG53: 2 | GL53: Cumple | GM53: 2 | GR53: Cumple | GS53: 2 | GY53: 0 | HE53: 0 | HK53: 0 | HQ53: 0 | HW53: 0 | IC53: 0 | II53: 0 | IO53: 0 | IU53: 0 | JA53: 0 | JG53: 0 | JM53: 0 | JS53: 0 | JY53: 0
A54: 53 | B54: 45133.631 | C54: 45133.646 | D54: anonymous | F54: 36 | H54: Multiplaza Curridabat | K54: 45133 | N54: Alejandra | Q54: Angie Valverde | T54: Cumple | U54: 2 | Z54: No Cumple | AA54: 0 | AC54: camara de refrigeracion tienen pollo crudo frescos naturales debajo de abanicos basureros se abre con las manos | AF54: Cumple | AG54: 2 | AM54: 0 | AS54: 0 | AY54: 0 | BE54: 0 | BK54: 0 | BP54: Cumple | BQ54: 3 | BV54: Cumple | BW54: 2 | CC54: 0 | CH54: Cumple | CI54: 2 | CN54: No cumple | CO54: 0 | CQ54: se encuentra bactogel vencido | CU54: 0 | CZ54: No cumple | DA54: 0 | DC54: los pañitos de pollo crudo estan sin santizante | DF54: No cumple | DG54: 0 | DI54: galleta en gaveta de cubiertos | DL54: Cumple | DM54: 3 | DR54: Cumple | DS54: 3 | DX54: Cumple | DY54: 3 | EE54: 0 | EJ54: No cumple | EK54: 0 | EM54: frescos sin tapar en camara de refrigeracion | EP54: Cumple | EQ54: 2 | EW54: 0 | FB54: No cumple | FC54: 0 | FE54: camaras de mesas frias y postres no cumplen con temperatura por lo tanto los alimentos almacenados ahi estan en zona de peligro | FH54: Cumple | FI54: 2 | FN54: Cumple | FO54: 2 | FT54: Cumple | FU54: 2 | FZ54: Cumple | GA54: 2 | GF54: Cumple | GG54: 2 | GL54: Cumple | GM54: 2 | GR54: Cumple | GS54: 2 | GY54: 0 | HE54: 0 | HK54: 0 | HQ54: 0 | HW54: 0 | IC54: 0 | II54: 0 | IO54: 0 | IU54: 0 | JA54: 0 | JG54: 0 | JM54: 0 | JS54: 0 | JY54: 0
A55: 54 | B55: 45134.52 | C55: 45134.527 | D55: anonymous | F55: 46 | H55: Oxígeno | K55: 45134 | N55: German | Q55: Angie Valverde | T55: Cumple | U55: 2 | Z55: Cumple | AA55: 2 | AF55: Cumple | AG55: 2 | AM55: 0 | AS55: 0 | AY55: 0 | BE55: 0 | BK55: 0 | BP55: Cumple | BQ55: 3 | BV55: Cumple | BW55: 2 | CC55: 0 | CE55: pol | CH55: Cumple | CI55: 2 | CN55: Cumple | CO55: 2 | CU55: 0 | CZ55: Cumple | DA55: 2 | DF55: Cumple | DG55: 2 | DL55: Cumple | DM55: 3 | DR55: Cumple | DS55: 3 | DX55: Cumple | DY55: 3 | EE55: 0 | EJ55: Cumple | EK55: 2 | EP55: Cumple | EQ55: 2 | EW55: 0 | FB55: No cumple | FC55: 0 | FE55: mesas frias no cumplen con temperaturas por lo tanto los productos que estan ahi estan en zona de peligro | FH55: Cumple | FI55: 2 | FN55: Cumple | FO55: 2 | FT55: Cumple | FU55: 2 | FZ55: Cumple | GA55: 2 | GF55: Cumple | GG55: 2 | GL55: Cumple | GM55: 2 | GR55: Cumple | GS55: 2 | GY55: 0 | HE55: 0 | HK55: 0 | HQ55: 0 | HW55: 0 | IC55: 0 | II55: 0 | IO55: 0 | IU55: 0 | JA55: 0 | JG55: 0 | JM55: 0 | JS55: 0 | JY55: 0
A56: 55 | B56: 45134.783 | C56: 45134.83 | D56: anonymous | F56: 36 | H56: Lincoln | K56: 45132 | N56: Henyel Contreras | Q56: Nazira Herrera | T56: Cumple | U56: 2 | Z56: No Cumple | AA56: 0 | AC56: Hay utensilios, materias primas y procesos junto a trampa de grasa con aperturas. Todo el área cercana está sucia, requiere limpieza profunda. | AF56: No cumple | AG56: 0 | AI56: Faltan dos de montas de pollo del día | AM56: 0 | AS56: 0 | AY56: 0 | BE56: 0 | BK56: 0 | BP56: Cumple | BQ56: 3 | BV56: No cumple | BW56: 0 | CC56: 0 | CE56: Auxiliar no usa malla en la operación | CH56: No cumple | CI56: 0 | CK56: Pila de lavado de manos con residuos de productos (trozos de pollo) | CN56: Cumple | CO56: 2 | CU56: 0 | CZ56: Cumple | DA56: 2 | DF56: No cumple | DG56: 0 | DI56: Ordenar área de lockers. Muchos artículos afuera (bolsos, zapatos), lockers abiertos, etc. | DL56: Cumple | DM56: 3 | DR56: Cumple | DS56: 3 | DX56: Cumple | DY56: 3 | EE56: 0 | EJ56: Cumple | EK56: 2 | EP56: Cumple | EQ56: 2 | EW56: 0 | FB56: Cumple | FC56: 2 | FE56: Se mantienen productos a temperatura ambiente. Planta entrega en hora de movimiento con problema en el sistema de pedidos por lo que los productos no se guardan de manera oportuna y permanecen un tiempo indebido a temperatura ambiente. | FH56: Cumple | FI56: 2 | FN56: Cumple | FO56: 2 | FT56: Cumple | FU56: 2 | FZ56: No cumple | GA56: 0 | GC56: Cámara de postres fuera de funcionamiento. Ya reportada | GF56: Cumple | GG56: 2 | GL56: Cumple | GM56: 2 | GR56: Cumple | GS56: 2 | GY56: 0 | HE56: 0 | HK56: 0 | HQ56: 0 | HW56: 0 | IC56: 0 | II56: 0 | IO56: 0 | IU56: 0 | JA56: 0 | JG56: 0 | JM56: 0 | JS56: 0 | JY56: 0 | KD56: Gestionar limpieza en área de la trampa de grasa de la cocina. Solicitar la colocación de algùn cierre o mecanismo de barrera. Realizar limpieza profunda general de la cocina.
A57: 56 | B57: 45135.621 | C57: 45135.625 | D57: anonymous | F57: 42 | H57: FC Pueblo Antiguo | K57: 45135 | N57: Daniel | Q57: Angie Valverde | T57: Cumple | U57: 2 | Z57: Cumple | AA57: 2 | AF57: No cumple | AG57: 0 | AI57: Esta las montas hasta las 10 y media am y son las 3 pm | AM57: 0 | AS57: 0 | AY57: 0 | BE57: 0 | BK57: 0 | BP57: Cumple | BQ57: 3 | BV57: No cumple | BW57: 0 | CC57: 0 | CE57: Salonero porta aretes expansiones | CH57: Cumple | CI57: 2 | CN57: No cumple | CO57: 0 | CQ57: Bactogel vencido | CU57: 0 | CZ57: Cumple | DA57: 2 | DF57: Cumple | DG57: 2 | DL57: Cumple | DM57: 3 | DR57: Cumple | DS57: 3 | DX57: Cumple | DY57: 3 | EE57: 0 | EJ57: Cumple | EK57: 2 | EP57: Cumple | EQ57: 2 | EW57: 0 | FB57: Cumple | FC57: 2 | FH57: Cumple | FI57: 2 | FN57: Cumple | FO57: 2 | FT57: Cumple | FU57: 2 | FZ57: Cumple | GA57: 2 | GF57: Cumple | GG57: 2 | GL57: Cumple | GM57: 2 | GR57: Cumple | GS57: 2 | GY57: 0 | HE57: 0 | HK57: 0 | HQ57: 0 | HW57: 0 | IC57: 0 | II57: 0 | IO57: 0 | IU57: 0 | JA57: 0 | JG57: 0 | JM57: 0 | JS57: 0 | JY57: 0
A58: 57 | B58: 45136.98 | C58: 45136.982 | D58: anonymous | F58: 44 | H58: Real Cariari | K58: 45135 | N58: Victor | Q58: Angie Valverde | T58: Cumple | U58: 2 | Z58: Cumple | AA58: 2 | AF58: Cumple | AG58: 2 | AM58: 0 | AS58: 0 | AY58: 0 | BE58: 0 | BK58: 0 | BP58: Cumple | BQ58: 3 | BV58: Cumple | BW58: 2 | CC58: 0 | CH58: Cumple | CI58: 2 | CN58: Cumple | CO58: 2 | CU58: 0 | CZ58: Cumple | DA58: 2 | DF58: Cumple | DG58: 2 | DL58: Cumple | DM58: 3 | DR58: Cumple | DS58: 3 | DX58: Cumple | DY58: 3 | EE58: 0 | EJ58: No cumple | EK58: 0 | EM58: Se encuentra guacamole sin tapar ni fechado | EP58: Cumple | EQ58: 2 | EW58: 0 | FB58: No cumple | FC58: 0 | FE58: Todas las cámaras no cumplen con las temperaturas por. Lo. Tanto los productos están en zona de peligro | FH58: Cumple | FI58: 2 | FN58: Cumple | FO58: 2 | FT58: Cumple | FU58: 2 | FZ58: Cumple | GA58: 2 | GF58: Cumple | GG58: 2 | GL58: Cumple | GM58: 2 | GR58: Cumple | GS58: 2 | GY58: 0 | HE58: 0 | HK58: 0 | HQ58: 0 | HW58: 0 | IC58: 0 | II58: 0 | IO58: 0 | IU58: 0 | JA58: 0 | JG58: 0 | JM58: 0 | JS58: 0 | JY58: 0
A59: 58 | B59: 45138.544 | C59: 45138.552 | D59: anonymous | F59: 42 | H59: Sabana | K59: 45138 | N59: Ingrid | Q59: Angie Valverde | T59: No cumple | U59: 0 | W59: termometro sin sanitizante | Z59: Cumple | AA59: 2 | AF59: Cumple | AG59: 2 | AI59: deben evitar los tachones | AM59: 0 | AS59: 0 | AY59: 0 | BE59: 0 | BK59: 0 | BP59: Cumple | BQ59: 3 | BV59: Cumple | BW59: 2 | CC59: 0 | CH59: Cumple | CI59: 2 | CN59: Cumple | CO59: 2 | CU59: 0 | CZ59: Cumple | DA59: 2 | DF59: Cumple | DG59: 2 | DL59: Cumple | DM59: 3 | DR59: Cumple | DS59: 3 | DX59: Cumple | DY59: 3 | EE59: 0 | EJ59: No cumple | EK59: 0 | EM59: estaban porcionando picos pero los dejan estapados afuera | EP59: Cumple | EQ59: 2 | EW59: 0 | FB59: No cumple | FC59: 0 | FE59: camara de refrigeracion y mesa fria no cumplen con temperatura por lo tanto los alimentos que estan dentro de esas camaras estan en zona de peligro | FH59: Cumple | FI59: 2 | FN59: Cumple | FO59: 2 | FT59: Cumple | FU59: 2 | FZ59: Cumple | GA59: 2 | GF59: Cumple | GG59: 2 | GL59: Cumple | GM59: 2 | GR59: Cumple | GS59: 2 | GY59: 0 | HE59: 0 | HK59: 0 | HQ59: 0 | HW59: 0 | IC59: 0 | II59: 0 | IO59: 0 | IU59: 0 | JA59: 0 | JG59: 0 | JM59: 0 | JS59: 0 | JY59: 0
A60: 59 | B60: 45138.606 | C60: 45138.639 | D60: anonymous | F60: 27 | H60: Guachipelín | K60: 45138 | N60: Doris Fajardo | Q60: Nazira Herrera | T60: Cumple | U60: 2 | Z60: No Cumple | AA60: 0 | AC60: Cuhillos almacenados entre la mesa y la pared. Se almacenan alimentos en bandejas plásticas dentro dl holding (las mismas no son para función caliente por lo que pueden desprender olor o sabor). El área de pollo tiene un fuerte mal olor. | AF60: No cumple | AG60: 0 | AI60: No realizar tachones en datos del libro. | AM60: 0 | AS60: 0 | AY60: 0 | BE60: 0 | BK60: 0 | BP60: No cumple | BQ60: 0 | BS60: Falta mejorar orden en estantes de almacenamiento de bolsas plásticas, además hay cajas sucias sin producto pero con residuos de hojas. | BV60: Cumple | BW60: 2 | CC60: 0 | CH60: No cumple | CI60: 0 | CK60: No cuenta con papel toalla | CN60: No cumple | CO60: 0 | CQ60: Galones de productos químicos debajo de la mesa de pollo. Además se identifica un producto no aprobado y se desconoce su uso (ácido muriático). | CU60: 0 | CZ60: Cumple | DA60: 2 | DF60: No cumple | DG60: 0 | DI60: Lockers abiertos, ropa de colaboradores guindada en el baño. Baño desordenado y con mal olor. Dos rollos de higiénicos en uso. | DL60: Cumple | DM60: 3 | DR60: Cumple | DS60: 3 | DX60: Cumple | DY60: 3 | EE60: 0 | EJ60: No cumple | EK60: 0 | EM60: No hay plástico adhesivo por lo que se identifican productos almacenados sin tapas (refrescos, productos de holding) | EP60: No cumple | EQ60: 0 | ES60: Se mantiene pollo a temperatura ambiente junto al freidor, destacar que mesa fría tampoco cumple con la temperatura. | EW60: 0 | FB60: Cumple | FC60: 2 | FH60: Cumple | FI60: 2 | FN60: Cumple | FO60: 2 | FT60: Cumple | FU60: 2 | FZ60: No cumple | GA60: 0 | GF60: Cumple | GG60: 2 | GI60: Recomendaciòn: aunque el área de arriba no esté en uso, mantenerla limpia y ordenada. | GL60: Cumple | GM60: 2 | GO60: N/A | GR60: No cumple | GS60: 0 | GY60: 0 | HE60: 0 | HK60: 0 | HQ60: 0 | HW60: 0 | IC60: 0 | II60: 0 | IO60: 0 | IU60: 0 | JA60: 0 | JG60: 0 | JM60: 0 | JS60: 0 | JY60: 0 | KD60: El calor tanto en el área de salón como de cocina es excesivo. Es importante tomar medidas sobre este tema. Verificar tema Pet Friendly para efectos de los artículos que necesitan y rotulación del área. El área de cocina es muy pequeña para todos los procesos, sin embargo procurar realizar limpiezas profundas de manera frecuente. Además importante el seguimiento de quipos en mal estado y utensilios faltantes. Se requiere reparar la luz de la cocina que está en mal estado.
A61: 60 | B61: 45138.637 | C61: 45138.66 | D61: anonymous | F61: 42 | H61: Santa Ana | K61: 45138 | N61: Fabiola | Q61: Angie Valverde | T61: Cumple | U61: 2 | Z61: Cumple | AA61: 2 | AF61: Cumple | AG61: 2 | AI61: no deben usar color rojo en el registro y deben de disminuir errores y tachones | AM61: 0 | AS61: 0 | AY61: 0 | BE61: 0 | BK61: 0 | BP61: Cumple | BQ61: 3 | BV61: Cumple | BW61: 2 | CC61: 0 | CH61: Cumple | CI61: 2 | CN61: Cumple | CO61: 2 | CU61: 0 | CZ61: No cumple | DA61: 0 | DC61: el agua de los paños de pollo estaba muy sucia | DF61: Cumple | DG61: 2 | DL61: Cumple | DM61: 3 | DR61: Cumple | DS61: 3 | DX61: Cumple | DY61: 3 | EE61: 0 | EJ61: Cumple | EK61: 2 | EP61: Cumple | EQ61: 2 | EW61: 0 | FB61: No cumple | FC61: 0 | FH61: Cumple | FI61: 2 | FN61: Cumple | FO61: 2 | FT61: No cumple | FU61: 0 | FW61: pollo con fecha incorrecta | FZ61: Cumple | GA61: 2 | GF61: Cumple | GG61: 2 | GL61: Cumple | GM61: 2 | GR61: Cumple | GS61: 2 | GY61: 0 | HE61: 0 | HK61: 0 | HQ61: 0 | HW61: 0 | IC61: 0 | II61: 0 | IO61: 0 | IU61: 0 | JA61: 0 | JG61: 0 | JM61: 0 | JS61: 0 | JY61: 0
A62: 61 | B62: 45141.675 | C62: 45141.677 | D62: anonymous | F62: 40 | H62: San José | K62: 45141 | N62: Diana | Q62: Angie Valverde | T62: Cumple | U62: 2 | Z62: Cumple | AA62: 2 | AF62: Cumple | AG62: 2 | AM62: 0 | AS62: 0 | AY62: 0 | BE62: 0 | BK62: 0 | BP62: Cumple | BQ62: 3 | BV62: Cumple | BW62: 2 | CC62: 0 | CH62: Cumple | CI62: 2 | CN62: No cumple | CO62: 0 | CQ62: Cloro fuera de lugar | CU62: 0 | CZ62: Cumple | DA62: 2 | DF62: Cumple | DG62: 2 | DL62: Cumple | DM62: 3 | DR62: Cumple | DS62: 3 | DX62: Cumple | DY62: 3 | EE62: 0 | EJ62: No cumple | EK62: 0 | EM62: Salsas sin fechas | EP62: Cumple | EQ62: 2 | EW62: 0 | FB62: No cumple | FC62: 0 | FE62: Cámaras no cumplen con temperaturas por lo tanto productos están en zona de peligro | FH62: Cumple | FI62: 2 | FN62: Cumple | FO62: 2 | FT62: No cumple | FU62: 0 | FW62: Pollo mechado sin fechar | FZ62: Cumple | GA62: 2 | GF62: Cumple | GG62: 2 | GL62: Cumple | GM62: 2 | GR62: Cumple | GS62: 2 | GY62: 0 | HE62: 0 | HK62: 0 | HQ62: 0 | HW62: 0 | IC62: 0 | II62: 0 | IO62: 0 | IU62: 0 | JA62: 0 | JG62: 0 | JM62: 0 | JS62: 0 | JY62: 0
A63: 62 | B63: 45142.834 | C63: 45142.837 | D63: anonymous | F63: 37 | H63: Sabana | K63: 45142 | N63: Ingrid | Q63: Angie Valverde | T63: Cumple | U63: 2 | Z63: No Cumple | AA63: 0 | AC63: Me. Encontré una bolsa qué contiene masa con. Moho | AF63: Cumple | AG63: 2 | AM63: 0 | AS63: 0 | AY63: 0 | BE63: 0 | BK63: 0 | BP63: No cumple | BQ63: 0 | BS63: Aceite en. Piso y empaque de empanizador abierto | BV63: Cumple | BW63: 2 | CC63: 0 | CH63: Cumple | CI63: 2 | CN63: Cumple | CO63: 2 | CU63: 0 | CZ63: No cumple | DA63: 0 | DC63: Pañitos del área de pollo sin sanitizante | DF63: Cumple | DG63: 2 | DL63: Cumple | DM63: 3 | DR63: Cumple | DS63: 3 | DX63: Cumple | DY63: 3 | EE63: 0 | EJ63: No cumple | EK63: 0 | EM63: Huevos sin. Tapar, y pollo sin fechar | EP63: Cumple | EQ63: 2 | EW63: 0 | FB63: No cumple | FC63: 0 | FE63: Algunas cámaras no. Cumplen por lo tanto. Los productos que están. Ahí están. En zona de peligro | FH63: Cumple | FI63: 2 | FN63: Cumple | FO63: 2 | FT63: Cumple | FU63: 2 | FZ63: Cumple | GA63: 2 | GF63: Cumple | GG63: 2 | GL63: Cumple | GM63: 2 | GR63: Cumple | GS63: 2 | GY63: 0 | HE63: 0 | HK63: 0 | HQ63: 0 | HW63: 0 | IC63: 0 | II63: 0 | IO63: 0 | IU63: 0 | JA63: 0 | JG63: 0 | JM63: 0 | JS63: 0 | JY63: 0
A64: 63 | B64: 45145.647 | C64: 45145.654 | D64: anonymous | F64: 42 | H64: Curridabat | K64: 45145 | N64: Dayanna | Q64: Angie Valverde | T64: Cumple | U64: 2 | Z64: Cumple | AA64: 2 | AF64: Cumple | AG64: 2 | AM64: 0 | AS64: 0 | AY64: 0 | BE64: 0 | BK64: 0 | BP64: Cumple | BQ64: 3 | BV64: Cumple | BW64: 2 | CC64: 0 | CH64: Cumple | CI64: 2 | CN64: Cumple | CO64: 2 | CU64: 0 | CZ64: Cumple | DA64: 2 | DF64: Cumple | DG64: 2 | DL64: Cumple | DM64: 3 | DR64: Cumple | DS64: 3 | DX64: Cumple | DY64: 3 | EE64: 0 | EJ64: No cumple | EK64: 0 | EM64: ch dulce de leche, flan de coco y cristal sin fechar | EP64: Cumple | EQ64: 2 | EW64: 0 | FB64: No cumple | FC64: 0 | FE64: camara de postres y mesa fría de pollo, no cumplen por lo tanto los alimentos que están ahí están en zona de peligro | FH64: Cumple | FI64: 2 | FN64: Cumple | FO64: 2 | FT64: Cumple | FU64: 2 | FZ64: No cumple | GA64: 0 | GC64: camara de postres esta ehando mucha agua | GF64: Cumple | GG64: 2 | GL64: Cumple | GM64: 2 | GR64: Cumple | GS64: 2 | GY64: 0 | HE64: 0 | HK64: 0 | HQ64: 0 | HW64: 0 | IC64: 0 | II64: 0 | IO64: 0 | IU64: 0 | JA64: 0 | JG64: 0 | JM64: 0 | JS64: 0 | JY64: 0
A65: 64 | B65: 45146.587 | C65: 45146.594 | D65: anonymous | F65: 42 | H65: Terramall | K65: 45146 | N65: Andrea | Q65: Angie Valverde | T65: Cumple | U65: 2 | Z65: Cumple | AA65: 2 | AF65: Cumple | AG65: 2 | AM65: 0 | AS65: 0 | AY65: 0 | BE65: 0 | BK65: 0 | BP65: Cumple | BQ65: 3 | BV65: Cumple | BW65: 2 | CC65: 0 | CH65: Cumple | CI65: 2 | CN65: Cumple | CO65: 2 | CU65: 0 | CZ65: Cumple | DA65: 2 | DF65: Cumple | DG65: 2 | DL65: Cumple | DM65: 3 | DR65: Cumple | DS65: 3 | DX65: Cumple | DY65: 3 | EE65: 0 | EJ65: No cumple | EK65: 0 | EM65: pollo crudo sin tapar, y guacamole, chile , huevos duros, pinto, sin fechas | EP65: Cumple | EQ65: 2 | EW65: 0 | FB65: No cumple | FC65: 0 | FE65: mesas fria de pollo y camara de postres no cumplen , por lo tanto los alimentos que estan ahi estan en zona de peligro | FH65: Cumple | FI65: 2 | FN65: Cumple | FO65: 2 | FT65: No cumple | FU65: 0 | FW65: pollo crudo sin fechar ni ningun dato | FZ65: Cumple | GA65: 2 | GF65: Cumple | GG65: 2 | GL65: Cumple | GM65: 2 | GR65: Cumple | GS65: 2 | GY65: 0 | HE65: 0 | HK65: 0 | HQ65: 0 | HW65: 0 | IC65: 0 | II65: 0 | IO65: 0 | IU65: 0 | JA65: 0 | JG65: 0 | JM65: 0 | JS65: 0 | JY65: 0
A66: 65 | B66: 45147.746 | C66: 45147.754 | D66: anonymous | F66: 46 | H66: Escazú | K66: 45147 | N66: Karla | Q66: Angie Valverde | T66: Cumple | U66: 2 | Z66: Cumple | AA66: 2 | AF66: Cumple | AG66: 2 | AI66: deben evitar los tachones , se les explica como deben hacer para las correciones | AM66: 0 | AS66: 0 | AY66: 0 | BE66: 0 | BK66: 0 | BP66: Cumple | BQ66: 3 | BV66: Cumple | BW66: 2 | CC66: 0 | CH66: Cumple | CI66: 2 | CN66: Cumple | CO66: 2 | CU66: 0 | CZ66: Cumple | DA66: 2 | DF66: Cumple | DG66: 2 | DL66: Cumple | DM66: 3 | DR66: Cumple | DS66: 3 | DX66: Cumple | DY66: 3 | EE66: 0 | EJ66: Cumple | EK66: 2 | EP66: Cumple | EQ66: 2 | EW66: 0 | FB66: No cumple | FC66: 0 | FE66: productos en cámaras que no cumplen están en zona de peligro | FH66: Cumple | FI66: 2 | FN66: Cumple | FO66: 2 | FT66: Cumple | FU66: 2 | FZ66: Cumple | GA66: 2 | GF66: Cumple | GG66: 2 | GL66: Cumple | GM66: 2 | GR66: Cumple | GS66: 2 | GY66: 0 | HE66: 0 | HK66: 0 | HQ66: 0 | HW66: 0 | IC66: 0 | II66: 0 | IO66: 0 | IU66: 0 | JA66: 0 | JG66: 0 | JM66: 0 | JS66: 0 | JY66: 0
A67: 66 | B67: 45148.851 | C67: 45148.858 | D67: anonymous | F67: 39 | H67: Pinares | K67: 45148 | N67: Marco | Q67: Angie Valverde | T67: Cumple | U67: 2 | Z67: Cumple | AA67: 2 | AF67: No cumple | AG67: 0 | AI67: falta verificacion y ademas muchos tachones | AM67: 0 | AS67: 0 | AY67: 0 | BE67: 0 | BK67: 0 | BP67: No cumple | BQ67: 0 | BS67: materias primas en piso | BV67: Cumple | BW67: 2 | CC67: 0 | CH67: Cumple | CI67: 2 | CN67: Cumple | CO67: 2 | CU67: 0 | CZ67: Cumple | DA67: 2 | DF67: Cumple | DG67: 2 | DL67: Cumple | DM67: 3 | DR67: Cumple | DS67: 3 | DX67: Cumple | DY67: 3 | EE67: 0 | EJ67: No cumple | EK67: 0 | EM67: se encuentra arroz con pollo sin tapar, ademas varios productos estan sin fechas en camaras frias como salsas, tomates . | EP67: Cumple | EQ67: 2 | EW67: 0 | FB67: No cumple | FC67: 0 | FE67: cámaras de postres , camara de congelado y mesas frías no cumplen con temperaturas , por lo tanto los alimentos que están ahí están en zona de peligro | FH67: Cumple | FI67: 2 | FN67: Cumple | FO67: 2 | FT67: Cumple | FU67: 2 | FZ67: Cumple | GA67: 2 | GF67: Cumple | GG67: 2 | GL67: Cumple | GM67: 2 | GR67: Cumple | GS67: 2 | GY67: 0 | HE67: 0 | HK67: 0 | HQ67: 0 | HW67: 0 | IC67: 0 | II67: 0 | IO67: 0 | IU67: 0 | JA67: 0 | JG67: 0 | JM67: 0 | JS67: 0 | JY67: 0
A68: 67 | B68: 45149.66 | C68: 45149.693 | D68: anonymous | F68: 42 | H68: Multiplaza Curridabat | K68: 45149 | N68: Alejandra | Q68: Angie Valverde | T68: Cumple | U68: 2 | Z68: No Cumple | AA68: 0 | AC68: almacenamiento del pollo en camara con otros productos y exceso de agua en la mesas frias puede entrar al producto | AF68: Cumple | AG68: 2 | AM68: 0 | AS68: 0 | AY68: 0 | BE68: 0 | BK68: 0 | BP68: Cumple | BQ68: 3 | BV68: Cumple | BW68: 2 | CC68: 0 | CH68: Cumple | CI68: 2 | CN68: Cumple | CO68: 2 | CU68: 0 | CZ68: Cumple | DA68: 2 | DF68: No cumple | DG68: 0 | DI68: baños sucios con papel en el piso y servilletas | DL68: Cumple | DM68: 3 | DR68: Cumple | DS68: 3 | DX68: Cumple | DY68: 3 | EE68: 0 | EJ68: Cumple | EK68: 2 | EP68: Cumple | EQ68: 2 | EW68: 0 | FB68: No cumple | FC68: 0 | FE68: mesas frias no funcionan , por lo tanto los productos estan en zona de peligro | FH68: Cumple | FI68: 2 | FN68: Cumple | FO68: 2 | FT68: Cumple | FU68: 2 | FZ68: Cumple | GA68: 2 | GF68: Cumple | GG68: 2 | GL68: Cumple | GM68: 2 | GR68: Cumple | GS68: 2 | GY68: 0 | HE68: 0 | HK68: 0 | HQ68: 0 | HW68: 0 | IC68: 0 | II68: 0 | IO68: 0 | IU68: 0 | JA68: 0 | JG68: 0 | JM68: 0 | JS68: 0 | JY68: 0
A69: 68 | B69: 45154.6 | C69: 45154.606 | D69: anonymous | F69: 40 | H69: Coronado | K69: 45154 | N69: Zayda | Q69: Angie Valverde | T69: Cumple | U69: 2 | Z69: Cumple | AA69: 2 | AF69: Cumple | AG69: 2 | AM69: 0 | AS69: 0 | AY69: 0 | BE69: 0 | BK69: 0 | BP69: Cumple | BQ69: 3 | BV69: Cumple | BW69: 2 | CC69: 0 | CH69: Cumple | CI69: 2 | CN69: No cumple | CO69: 0 | CQ69: bactogel vencido | CU69: 0 | CZ69: Cumple | DA69: 2 | DF69: Cumple | DG69: 2 | DL69: Cumple | DM69: 3 | DR69: Cumple | DS69: 3 | DX69: Cumple | DY69: 3 | EE69: 0 | EJ69: No cumple | EK69: 0 | EM69: pollo inyectado sin fechar ,zanahoria sin fechar | EP69: Cumple | EQ69: 2 | EW69: 0 | FB69: No cumple | FC69: 0 | FE69: camara de postres y no cumple con temperatura por lo tanto los postres guardados en ella no cumplen | FH69: Cumple | FI69: 2 | FN69: Cumple | FO69: 2 | FT69: No cumple | FU69: 0 | FW69: pollo crudo sin fechas de inyeccion | FZ69: Cumple | GA69: 2 | GF69: Cumple | GG69: 2 | GL69: Cumple | GM69: 2 | GR69: Cumple | GS69: 2 | GY69: 0 | HE69: 0 | HK69: 0 | HQ69: 0 | HW69: 0 | IC69: 0 | II69: 0 | IO69: 0 | IU69: 0 | JA69: 0 | JG69: 0 | JM69: 0 | JS69: 0 | JY69: 0
A70: 69 | B70: 45154.682 | C70: 45154.689 | D70: anonymous | F70: 42 | H70: Guadalupe | K70: 45154 | N70: Martha | Q70: Angie Valverde | T70: Cumple | U70: 2 | Z70: No Cumple | AA70: 0 | AC70: En mesas frías de ensalada se encuentra pollo crudo, y no podemos. Tener estos 2 productos ya qué los vegetales no llevan ningun proceso de cocción si no que se sirve de una vez. Además la cámara de pollo no. Tiene manguera y recogen el. Agua con sangre que bota la cámara en una tina., tina qué deben. Manipular con las manos y uniforme. Puesto | AF70: Cumple | AG70: 2 | AM70: 0 | AS70: 0 | AY70: 0 | BE70: 0 | BK70: 0 | BP70: Cumple | BQ70: 3 | BV70: Cumple | BW70: 2 | CC70: 0 | CH70: Cumple | CI70: 2 | CN70: Cumple | CO70: 2 | CU70: 0 | CZ70: Cumple | DA70: 2 | DF70: Cumple | DG70: 2 | DL70: Cumple | DM70: 3 | DR70: Cumple | DS70: 3 | DX70: Cumple | DY70: 3 | EE70: 0 | EJ70: No cumple | EK70: 0 | EM70: Pollo desmenuzado sin fechar, tortillas sin tapar | EP70: Cumple | EQ70: 2 | EW70: 0 | FB70: No cumple | FC70: 0 | FE70: Cámaras frías, cámara de postre y camara de congelado no cumplen, por lo tanto los productos que están ahí tampoco están en. Zona de peligro | FH70: Cumple | FI70: 2 | FN70: Cumple | FO70: 2 | FT70: Cumple | FU70: 2 | FZ70: Cumple | GA70: 2 | GF70: Cumple | GG70: 2 | GL70: Cumple | GM70: 2 | GR70: Cumple | GS70: 2 | GY70: 0 | HE70: 0 | HK70: 0 | HQ70: 0 | HW70: 0 | IC70: 0 | II70: 0 | IO70: 0 | IU70: 0 | JA70: 0 | JG70: 0 | JM70: 0 | JS70: 0 | JY70: 0
A71: 70 | B71: 45155.617 | C71: 45155.621 | D71: anonymous | F71: 44 | H71: Oxígeno | K71: 45155 | N71: Zayda | Q71: Angie Valverde | T71: Cumple | U71: 2 | Z71: Cumple | AA71: 2 | AF71: Cumple | AG71: 2 | AI71: por favor no hacer tachones en el libro | AM71: 0 | AS71: 0 | AY71: 0 | BE71: 0 | BK71: 0 | BP71: Cumple | BQ71: 3 | BV71: Cumple | BW71: 2 | CC71: 0 | CH71: Cumple | CI71: 2 | CN71: No cumple | CO71: 0 | CQ71: se encuentra un bactogel vencido | CU71: 0 | CZ71: Cumple | DA71: 2 | DF71: Cumple | DG71: 2 | DL71: Cumple | DM71: 3 | DR71: Cumple | DS71: 3 | DX71: Cumple | DY71: 3 | EE71: 0 | EJ71: Cumple | EK71: 2 | EP71: Cumple | EQ71: 2 | EW71: 0 | FB71: No cumple | FC71: 0 | FE71: mesas frias no cumplen con temperatura y se encontro pollo en ellas por lo tanto estan en zona de peligro | FH71: Cumple | FI71: 2 | FN71: Cumple | FO71: 2 | FT71: Cumple | FU71: 2 | FZ71: Cumple | GA71: 2 | GF71: Cumple | GG71: 2 | GL71: Cumple | GM71: 2 | GR71: Cumple | GS71: 2 | GY71: 0 | HE71: 0 | HK71: 0 | HQ71: 0 | HW71: 0 | IC71: 0 | II71: 0 | IO71: 0 | IU71: 0 | JA71: 0 | JG71: 0 | JM71: 0 | JS71: 0 | JY71: 0
A72: 71 | B72: 45156.779 | C72: 45156.782 | D72: anonymous | F72: 42 | H72: Desamparados | K72: 45156 | N72: Sonia | Q72: Angie Valverde | T72: Cumple | U72: 2 | Z72: No Cumple | AA72: 0 | AC72: Pollo crudo en camara de vegetales | AF72: Cumple | AG72: 2 | AM72: 0 | AS72: 0 | AY72: 0 | BE72: 0 | BK72: 0 | BP72: Cumple | BQ72: 3 | BV72: Cumple | BW72: 2 | CC72: 0 | CH72: Cumple | CI72: 2 | CN72: Cumple | CO72: 2 | CU72: 0 | CZ72: Cumple | DA72: 2 | DF72: Cumple | DG72: 2 | DL72: Cumple | DM72: 3 | DR72: Cumple | DS72: 3 | DX72: Cumple | DY72: 3 | EE72: 0 | EJ72: Cumple | EK72: 2 | EP72: Cumple | EQ72: 2 | EW72: 0 | FB72: No cumple | FC72: 0 | FE72: Cámaras no cumplen con temperaturas productos en zona de peligro | FH72: No cumple | FI72: 0 | FK72: Salsas y aderezos a temperatura ambiente | FN72: Cumple | FO72: 2 | FT72: Cumple | FU72: 2 | FZ72: Cumple | GA72: 2 | GF72: Cumple | GG72: 2 | GL72: Cumple | GM72: 2 | GR72: Cumple | GS72: 2 | GY72: 0 | HE72: 0 | HK72: 0 | HQ72: 0 | HW72: 0 | IC72: 0 | II72: 0 | IO72: 0 | IU72: 0 | JA72: 0 | JG72: 0 | JM72: 0 | JS72: 0 | JY72: 0
A73: 72 | B73: 45159.605 | C73: 45159.611 | D73: anonymous | F73: 34 | H73: Real Alajuela | K73: 45159 | N73: Esteban | Q73: Angie Valverde | T73: Cumple | U73: 2 | Z73: No Cumple | AA73: 0 | AC73: se encuentra en camara de pollo crudo, pollo en mal estado cerca del pollo en buen estado | AF73: No cumple | AG73: 0 | AI73: muchos tachones, uso de corrector . ademas solo tienen una monta apuntada | AM73: 0 | AS73: 0 | AY73: 0 | BE73: 0 | BK73: 0 | BP73: Cumple | BQ73: 3 | BV73: Cumple | BW73: 2 | CC73: 0 | CH73: Cumple | CI73: 2 | CN73: No cumple | CO73: 0 | CQ73: se encuentra bactogel vencido | CU73: 0 | CZ73: Cumple | DA73: 2 | DF73: Cumple | DG73: 2 | DL73: Cumple | DM73: 3 | DR73: Cumple | DS73: 3 | DX73: Cumple | DY73: 3 | EE73: 0 | EJ73: No cumple | EK73: 0 | EM73: se encuentra guacamole sin fechar | EP73: Cumple | EQ73: 2 | EW73: 0 | FB73: No cumple | FC73: 0 | FE73: camaras no cumplen , ni mesas frias, por lo tanto los productos que estan almacenados ahi estan en zona de peligro | FH73: No cumple | FI73: 0 | FK73: aderezos estan a temperatura ambiente , no estan en hielo | FN73: Cumple | FO73: 2 | FT73: No cumple | FU73: 0 | FW73: se encuentra pollo sin datos de marinado | FZ73: Cumple | GA73: 2 | GF73: Cumple | GG73: 2 | GL73: Cumple | GM73: 2 | GR73: Cumple | GS73: 2 | GY73: 0 | HE73: 0 | HK73: 0 | HQ73: 0 | HW73: 0 | IC73: 0 | II73: 0 | IO73: 0 | IU73: 0 | JA73: 0 | JG73: 0 | JM73: 0 | JS73: 0 | JY73: 0
A74: 73 | B74: 45159.697 | C74: 45159.702 | D74: anonymous | F74: 35 | H74: Real Cariari | K74: 45159 | N74: Karen | Q74: Angie Valverde | T74: No cumple | U74: 0 | W74: sanitizante no reacciona, ya que le estaban echando menos | Z74: No Cumple | AA74: 0 | AF74: Cumple | AG74: 2 | AM74: 0 | AS74: 0 | AY74: 0 | BE74: 0 | BK74: 0 | BP74: No cumple | BQ74: 0 | BS74: tenían un contenedor lleno de grasa, eso es atrayende de plagas | BV74: Cumple | BW74: 2 | CC74: 0 | CH74: Cumple | CI74: 2 | CN74: No cumple | CO74: 0 | CQ74: se encuentra bactogel vencido | CU74: 0 | CZ74: No cumple | DA74: 0 | DC74: sanitizante bajo casi que sin reaccion | DF74: Cumple | DG74: 2 | DL74: Cumple | DM74: 3 | DR74: Cumple | DS74: 3 | DX74: Cumple | DY74: 3 | EE74: 0 | EJ74: Cumple | EK74: 2 | EP74: Cumple | EQ74: 2 | EW74: 0 | FB74: No cumple | FC74: 0 | FE74: solo 3 camaras cumplen con la temperatura por lo tanto la mayoria de productos estan en zona de pleligro | FH74: Cumple | FI74: 2 | FN74: Cumple | FO74: 2 | FT74: Cumple | FU74: 2 | FZ74: Cumple | GA74: 2 | GF74: Cumple | GG74: 2 | GL74: Cumple | GM74: 2 | GR74: Cumple | GS74: 2 | GY74: 0 | HE74: 0 | HK74: 0 | HQ74: 0 | HW74: 0 | IC74: 0 | II74: 0 | IO74: 0 | IU74: 0 | JA74: 0 | JG74: 0 | JM74: 0 | JS74: 0 | JY74: 0
A75: 74 | B75: 45160.632 | C75: 45160.636 | D75: anonymous | F75: 40 | H75: Lincoln | K75: 45160 | N75: Henyel | Q75: Angie Valverde | T75: No cumple | U75: 0 | W75: termometro sin reaccion a sanitizante | Z75: No Cumple | AA75: 0 | AC75: en camara depollo crudo hay guardado frijoles | AF75: Cumple | AG75: 2 | AM75: 0 | AS75: 0 | AY75: 0 | BE75: 0 | BK75: 0 | BP75: Cumple | BQ75: 3 | BV75: Cumple | BW75: 2 | CC75: 0 | CH75: Cumple | CI75: 2 | CN75: Cumple | CO75: 2 | CU75: 0 | CZ75: No cumple | DA75: 0 | DC75: sin reacción a la hora de medir sanitizante | DF75: Cumple | DG75: 2 | DL75: Cumple | DM75: 3 | DR75: Cumple | DS75: 3 | DX75: Cumple | DY75: 3 | EE75: 0 | EJ75: Cumple | EK75: 2 | EP75: Cumple | EQ75: 2 | EW75: 0 | FB75: No cumple | FC75: 0 | FE75: camara de postres, y mesa fria no cumplen por lo tanto los productos que estan ahi estan en zona de pleligro | FH75: Cumple | FI75: 2 | FN75: Cumple | FO75: 2 | FT75: Cumple | FU75: 2 | FZ75: Cumple | GA75: 2 | GF75: Cumple | GG75: 2 | GL75: Cumple | GM75: 2 | GR75: Cumple | GS75: 2 | GY75: 0 | HE75: 0 | HK75: 0 | HQ75: 0 | HW75: 0 | IC75: 0 | II75: 0 | IO75: 0 | IU75: 0 | JA75: 0 | JG75: 0 | JM75: 0 | JS75: 0 | JY75: 0
A76: 75 | B76: 45160.668 | C76: 45160.727 | D76: anonymous | F76: 36 | H76: Heredia | K76: 45160 | N76: Yoryanela Vargas | Q76: Nazira Herrera | T76: Cumple | U76: 2 | Z76: No Cumple | AA76: 0 | AC76: Tablas de picar muy deterioradas, manchadas y sucias, requieren cambio. | AF76: Cumple | AG76: 2 | AM76: 0 | AS76: 0 | AY76: 0 | BE76: 0 | BK76: 0 | BP76: Cumple | BQ76: 3 | BS76: Alto inventario de huevos. Alerta ya que esto afecta la calidad y frescura del producto. | BV76: Cumple | BW76: 2 | CC76: 0 | CH76: Cumple | CI76: 2 | CN76: Cumple | CO76: 2 | CU76: 0 | CZ76: Cumple | DA76: 2 | DF76: No cumple | DG76: 0 | DI76: Area desordenada. Lockers abiertos. Artículos almacenados fuera. El baño es bodega de artículos en desuso. Hay muchos pares de zapatos y vajilla blanca. | DL76: Cumple | DM76: 3 | DR76: Cumple | DS76: 3 | DX76: Cumple | DY76: 3 | EE76: 0 | EJ76: No cumple | EK76: 0 | EM76: Arepas se mantienen sin tapa, aceite de lubricar jeringa de inyección sin tapa, Chalupas sin tapa. | EP76: Cumple | EQ76: 2 | EW76: 0 | FB76: Cumple | FC76: 2 | FH76: Cumple | FI76: 2 | FN76: Cumple | FO76: 2 | FT76: Cumple | FU76: 2 | FZ76: No cumple | GA76: 0 | GC76: Incorrecta presentación del cc del dulce de leche. No es adecuada decoración, exceso de dulce de leche y galleta. | GF76: No cumple | GG76: 0 | GI76: Falta limpieza en cajas de almacenamiento de cubiertos. | GL76: No cumple | GM76: 0 | GO76: Dispensador de papel higiénico flojo, torcido en baño de mujeres | GR76: Cumple | GS76: 2 | GY76: 0 | HE76: 0 | HK76: 0 | HQ76: 0 | HW76: 0 | IC76: 0 | II76: 0 | IO76: 0 | IU76: 0 | JA76: 0 | JG76: 0 | JM76: 0 | JS76: 0 | JY76: 0
A77: 76 | B77: 45161.628 | C77: 45161.643 | D77: anonymous | F77: 40 | H77: Alajuela | K77: 45161 | N77: Oscar Lara | Q77: Nazira Herrera | T77: Cumple | U77: 2 | Z77: No Cumple | AA77: 0 | AC77: Ensalada coleslaw almacenada junto al pollo crudo en mesa fría. | AF77: No cumple | AG77: 0 | AI77: A pesar de las correcciones de inicio de mes se continúa el tema de tachones y uso de corrector en el registro. | AM77: 0 | AS77: 0 | AY77: 0 | BE77: 0 | BK77: 0 | BP77: Cumple | BQ77: 3 | BV77: Cumple | BW77: 2 | CC77: 0 | CH77: Cumple | CI77: 2 | CN77: Cumple | CO77: 2 | CU77: 0 | CZ77: Cumple | DA77: 2 | DF77: Cumple | DG77: 2 | DL77: Cumple | DM77: 3 | DR77: Cumple | DS77: 3 | DU77: Se encuentra en proceso de poda de los arboles exteriores. Hay ramas y hojas como parte del proceso. | DX77: Cumple | DY77: 3 | EE77: 0 | EJ77: No cumple | EK77: 0 | EM77: Se identifica caldo de pollo congelado, sin porcionar y tapado con los recipientes de las empanadas. | EP77: Cumple | EQ77: 2 | EW77: 0 | FB77: Cumple | FC77: 2 | FH77: Cumple | FI77: 2 | FN77: Cumple | FO77: 2 | FT77: Cumple | FU77: 2 | FZ77: No cumple | GA77: 0 | GC77: Cristal decorado con trozos muy pequeños (picadura de final de la bolsa). | GF77: Cumple | GG77: 2 | GL77: Cumple | GM77: 2 | GR77: Cumple | GS77: 2 | GY77: 0 | HE77: 0 | HK77: 0 | HQ77: 0 | HW77: 0 | IC77: 0 | II77: 0 | IO77: 0 | IU77: 0 | JA77: 0 | JG77: 0 | JM77: 0 | JS77: 0 | JY77: 0 | KD77: Muy bien en temas de limpieza. Reforzar temas de registro de monta de pollo y de contaminación cruzada. Pollo crudo vrs producto listo para consumir.
A78: 77 | B78: 45161.704 | C78: 45161.712 | D78: anonymous | F78: 39 | H78: Guachipelín | K78: 45161 | N78: Dorys | Q78: Angie Valverde | T78: Cumple | U78: 2 | Z78: No Cumple | AA78: 0 | AC78: limpiones amarillos de pollo revueltos con verdes en sanitizante | AF78: Cumple | AG78: 2 | AM78: 0 | AS78: 0 | AY78: 0 | BE78: 0 | BK78: 0 | BP78: No cumple | BQ78: 0 | BS78: se encuentra saco de masa en el piso | BV78: Cumple | BW78: 2 | CC78: 0 | CH78: Cumple | CI78: 2 | CN78: Cumple | CO78: 2 | CU78: 0 | CZ78: No cumple | DA78: 0 | DC78: sin sanitizante | DF78: Cumple | DG78: 2 | DL78: Cumple | DM78: 3 | DR78: Cumple | DS78: 3 | DX78: Cumple | DY78: 3 | EE78: 0 | EJ78: Cumple | EK78: 2 | EP78: Cumple | EQ78: 2 | EW78: 0 | FB78: No cumple | FC78: 0 | FE78: mesas frias no cumplen por lo tanto los productos que estan ahi tampoco | FH78: Cumple | FI78: 2 | FN78: Cumple | FO78: 2 | FT78: Cumple | FU78: 2 | FZ78: Cumple | GA78: 2 | GF78: Cumple | GG78: 2 | GL78: Cumple | GM78: 2 | GR78: Cumple | GS78: 2 | GY78: 0 | HE78: 0 | HK78: 0 | HQ78: 0 | HW78: 0 | IC78: 0 | II78: 0 | IO78: 0 | IU78: 0 | JA78: 0 | JG78: 0 | JM78: 0 | JS78: 0 | JY78: 0
A79: 78 | B79: 45162.65 | C79: 45162.663 | D79: anonymous | F79: 42 | H79: Multiplaza Escazú | K79: 45162 | N79: Maricela | Q79: Angie Valverde | T79: Cumple | U79: 2 | Z79: Cumple | AA79: 2 | AF79: Cumple | AG79: 2 | AM79: 0 | AS79: 0 | AY79: 0 | BE79: 0 | BK79: 0 | BP79: Cumple | BQ79: 3 | BV79: Cumple | BW79: 2 | CC79: 0 | CH79: No cumple | CI79: 0 | CK79: sin toalla para secarse en el lavamanos | CN79: Cumple | CO79: 2 | CU79: 0 | CZ79: No cumple | DA79: 0 | DC79: paños del área de pollo sin sanitizante | DF79: Cumple | DG79: 2 | DL79: Cumple | DM79: 3 | DR79: Cumple | DS79: 3 | DX79: Cumple | DY79: 3 | EE79: 0 | EJ79: No cumple | EK79: 0 | EM79: tomate sin fechar | EP79: Cumple | EQ79: 2 | EW79: 0 | FB79: Cumple | FC79: 2 | FH79: Cumple | FI79: 2 | FN79: Cumple | FO79: 2 | FT79: Cumple | FU79: 2 | FZ79: Cumple | GA79: 2 | GF79: Cumple | GG79: 2 | GL79: Cumple | GM79: 2 | GR79: Cumple | GS79: 2 | GY79: 0 | HE79: 0 | HK79: 0 | HQ79: 0 | HW79: 0 | IC79: 0 | II79: 0 | IO79: 0 | IU79: 0 | JA79: 0 | JG79: 0 | JM79: 0 | JS79: 0 | JY79: 0
A80: 79 | B80: 45162.575 | C80: 45162.67 | D80: anonymous | F80: 38 | H80: Tibás | K80: 45162 | N80: Jessie Chavarría | Q80: Nazira Herrera | T80: Cumple | U80: 2 | Z80: No Cumple | AA80: 0 | AC80: Productos químicos se mantienen en la mesa junto a la preparación de vegetales. | AF80: Cumple | AG80: 2 | AM80: 0 | AS80: 0 | AY80: 0 | BE80: 0 | BK80: 0 | BP80: Cumple | BQ80: 3 | BV80: Cumple | BW80: 2 | CC80: 0 | CH80: Cumple | CI80: 2 | CN80: Cumple | CO80: 2 | CU80: 0 | CZ80: Cumple | DA80: 2 | DF80: Cumple | DG80: 2 | DL80: Cumple | DM80: 3 | DR80: Cumple | DS80: 3 | DX80: Cumple | DY80: 3 | EE80: 0 | EJ80: No cumple | EK80: 0 | EM80: Se identifican muchos alimentos sin tapar: guacamole, pico de gallo de quesadillas, tortillas de harina (deshidratadas) | EP80: No cumple | EQ80: 0 | ES80: Bolsas abiertas | EW80: 0 | FB80: Cumple | FC80: 2 | FH80: Cumple | FI80: 2 | FN80: Cumple | FO80: 2 | FT80: Cumple | FU80: 2 | FZ80: No cumple | GA80: 0 | GC80: Todo el Queque Cristal está decorado, los caramelos se están derritiendo y manchando el queque. Etiqueta de fechado del flan de coco se coloca sobre el plato en contacto con el postre. | GF80: Cumple | GG80: 2 | GL80: Cumple | GM80: 2 | GO80: Por sugerencia de cliente se solicita reubicación de jabonera en baño de hombres ya que está muy cerca de la puerta y hay riesgo de accidente. | GR80: No cumple | GS80: 0 | GY80: 0 | HE80: 0 | HK80: 0 | HQ80: 0 | HW80: 0 | IC80: 0 | II80: 0 | IO80: 0 | IU80: 0 | JA80: 0 | JG80: 0 | JM80: 0 | JS80: 0 | JY80: 0 | KD80: No utilizar las jaulas para la colocación de las cebollitas. Dar seguimiento al uso de las redecillas por parte de los morizados.
A81: 80 | B81: 45163.559 | C81: 45163.56 | D81: anonymous | F81: 46 | H81: Parque Diversiones Pueblo Antiguo | K81: 45163 | N81: Daniel | Q81: Angie Valverde | T81: Cumple | U81: 2 | Z81: No Cumple | AA81: 0 | AC81: Agua de cámara de postres cae directamente en los postres, ya que están sin tapar | AF81: Cumple | AG81: 2 | AM81: 0 | AS81: 0 | AY81: 0 | BE81: 0 | BK81: 0 | BP81: Cumple | BQ81: 3 | BV81: Cumple | BW81: 2 | CC81: 0 | CH81: Cumple | CI81: 2 | CN81: Cumple | CO81: 2 | CU81: 0 | CZ81: Cumple | DA81: 2 | DF81: Cumple | DG81: 2 | DL81: Cumple | DM81: 3 | DR81: Cumple | DS81: 3 | DX81: Cumple | DY81: 3 | EE81: 0 | EJ81: Cumple | EK81: 2 | EP81: Cumple | EQ81: 2 | EW81: 0 | FB81: Cumple | FC81: 2 | FH81: Cumple | FI81: 2 | FN81: Cumple | FO81: 2 | FT81: Cumple | FU81: 2 | FZ81: Cumple | GA81: 2 | GF81: Cumple | GG81: 2 | GL81: Cumple | GM81: 2 | GR81: Cumple | GS81: 2 | GY81: 0 | HE81: 0 | HK81: 0 | HQ81: 0 | HW81: 0 | IC81: 0 | II81: 0 | IO81: 0 | IU81: 0 | JA81: 0 | JG81: 0 | JM81: 0 | JS81: 0 | JY81: 0
A82: 81 | B82: 45164.624 | C82: 45164.626 | D82: anonymous | F82: 44 | H82: Food Court Parque Diversiones | K82: 45164 | N82: Luis | Q82: Angie Valverde | T82: Cumple | U82: 2 | Z82: Cumple | AA82: 2 | AF82: Cumple | AG82: 2 | AM82: 0 | AS82: 0 | AY82: 0 | BE82: 0 | BK82: 0 | BP82: Cumple | BQ82: 3 | BV82: Cumple | BW82: 2 | CC82: 0 | CH82: No cumple | CI82: 0 | CK82: No hay servilletas para secarse las manos | CN82: Cumple | CO82: 2 | CU82: 0 | CZ82: Cumple | DA82: 2 | DF82: Cumple | DG82: 2 | DL82: Cumple | DM82: 3 | DR82: Cumple | DS82: 3 | DX82: Cumple | DY82: 3 | EE82: 0 | EJ82: No cumple | EK82: 0 | EM82: Se encuentra lechuga y pollo sin fecha | EP82: Cumple | EQ82: 2 | EW82: 0 | FB82: Cumple | FC82: 2 | FH82: Cumple | FI82: 2 | FN82: Cumple | FO82: 2 | FT82: Cumple | FU82: 2 | FZ82: Cumple | GA82: 2 | GF82: Cumple | GG82: 2 | GL82: Cumple | GM82: 2 | GR82: Cumple | GS82: 2 | GY82: 0 | HE82: 0 | HK82: 0 | HQ82: 0 | HW82: 0 | IC82: 0 | II82: 0 | IO82: 0 | IU82: 0 | JA82: 0 | JG82: 0 | JM82: 0 | JS82: 0 | JY82: 0
A83: 82 | B83: 45166.594 | C83: 45166.597 | D83: anonymous | F83: 44 | H83: Cartago | K83: 45166 | N83: Katiola | Q83: Angie Valverde | T83: No cumple | U83: 0 | W83: Sin sanitizante | Z83: Cumple | AA83: 2 | AF83: Cumple | AG83: 2 | AM83: 0 | AS83: 0 | AY83: 0 | BE83: 0 | BK83: 0 | BP83: Cumple | BQ83: 3 | BV83: Cumple | BW83: 2 | CC83: 0 | CH83: Cumple | CI83: 2 | CN83: Cumple | CO83: 2 | CU83: 0 | CZ83: No cumple | DA83: 0 | DC83: Sin sanitizante | DF83: Cumple | DG83: 2 | DL83: Cumple | DM83: 3 | DR83: Cumple | DS83: 3 | DX83: Cumple | DY83: 3 | EE83: 0 | EJ83: Cumple | EK83: 2 | EP83: Cumple | EQ83: 2 | EW83: 0 | FB83: Cumple | FC83: 2 | FH83: Cumple | FI83: 2 | FN83: Cumple | FO83: 2 | FT83: Cumple | FU83: 2 | FZ83: Cumple | GA83: 2 | GF83: Cumple | GG83: 2 | GL83: Cumple | GM83: 2 | GR83: Cumple | GS83: 2 | GY83: 0 | HE83: 0 | HK83: 0 | HQ83: 0 | HW83: 0 | IC83: 0 | II83: 0 | IO83: 0 | IU83: 0 | JA83: 0 | JG83: 0 | JM83: 0 | JS83: 0 | JY83: 0
A84: 83 | B84: 45168.573 | C84: 45168.581 | D84: anonymous | F84: 44 | H84: City Mall | K84: 45168 | N84: Yahaira | Q84: Angie Valverde | T84: Cumple | U84: 2 | Z84: No Cumple | AA84: 0 | AC84: se encuentra jabón en polvo y cloro en bodega de materias primas | AF84: Cumple | AG84: 2 | AI84: por favor evitar tachones | AM84: 0 | AS84: 0 | AY84: 0 | BE84: 0 | BK84: 0 | BP84: Cumple | BQ84: 3 | BV84: Cumple | BW84: 2 | CC84: 0 | CH84: Cumple | CI84: 2 | CK84: solicitar que le pongan químicos de sanitización de manos en área de pollo | CN84: Cumple | CO84: 2 | CU84: 0 | CZ84: Cumple | DA84: 2 | DF84: No cumple | DG84: 0 | DI84: comedor sucio, con servilletas en piso y gorros. por favor mantener el orden y limpieza | DL84: Cumple | DM84: 3 | DR84: Cumple | DS84: 3 | DX84: Cumple | DY84: 3 | EE84: 0 | EJ84: Cumple | EK84: 2 | EP84: Cumple | EQ84: 2 | EW84: 0 | FB84: Cumple | FC84: 2 | FH84: Cumple | FI84: 2 | FN84: Cumple | FO84: 2 | FT84: Cumple | FU84: 2 | FZ84: Cumple | GA84: 2 | GF84: Cumple | GG84: 2 | GL84: Cumple | GM84: 2 | GR84: Cumple | GS84: 2 | GY84: 0 | HE84: 0 | HK84: 0 | HQ84: 0 | HW84: 0 | IC84: 0 | II84: 0 | IO84: 0 | IU84: 0 | JA84: 0 | JG84: 0 | JM84: 0 | JS84: 0 | JY84: 0 | KD84: tienen problematica con la plaga de cucarachas, en si el restaurante esta limpio , pero ustedes deben de mantener los procesos de limpieza muy definidos por la problematica que tienen, evitar dejar basura en pisos y platos sucios. saludos
A85: 84 | B85: 45168.522 | C85: 45168.584 | D85: anonymous | F85: 30 | H85: Santa Ana | K85: 45168 | N85: Carlos Sandino | Q85: Nazira Herrera | T85: Cumple | U85: 2 | Z85: No Cumple | AA85: 0 | AC85: Cuchillos se almacenan en rejillas entre los equipos y las paredes. Delantal amarillo sucio. Cortadora de tomate sucia, sello con residuos acumulados y hongos. Huevos quebrados. Colador de intermedio con mucha acumulación de suciedad. Recipientes de almacenamiento/ empaque llevar almacenado "para arriba" (expuesto). | AF85: No cumple | AG85: 0 | AI85: Se hacen observaciones de errores del registro de cocción de pollo pero es reincidente en todo el mes. Hay tachones y faltante de datos. | AM85: 0 | AS85: 0 | AY85: 0 | BE85: 0 | BK85: 0 | BP85: No cumple | BQ85: 0 | BS85: Productos abiertos, residuos de productos. Cajas de almacenamiento sucio, atrayente de plagas- Bodega de material de empaque desordenada. | BV85: Cumple | BW85: 2 | CC85: 0 | CH85: Cumple | CI85: 2 | CN85: Cumple | CO85: 2 | CU85: 0 | CZ85: Cumple | DA85: 2 | DF85: No cumple | DG85: 0 | DI85: Area de lockers requiere orden y limpieza. Artículos mal almacenados, lockers abiertos, toallas en el lavamanos. | DL85: No cumple | DM85: 0 | DO85: Tapa de basurero de cocina con exceso de residuos y suciedad acumulada. | DR85: Cumple | DS85: 3 | DU85: Parte trasera requiere limpieza. Eliminar caja de papas deterioradas. | DX85: Cumple | DY85: 3 | EE85: 0 | EJ85: No cumple | EK85: 0 | EM85: Mal fechado de productos. Pollo a 3 días, pasta de pollo a más de 1 mes. Todos los recipientes y baño María se fechan con fecha de hoy sin razón alguna. | EP85: Cumple | EQ85: 2 | EW85: 0 | FB85: No cumple | FC85: 0 | FE85: Queso molido se mantiene a temperatura ambiente, no en cama de hielo. | FH85: Cumple | FI85: 2 | FN85: Cumple | FO85: 2 | FT85: Cumple | FU85: 2 | FZ85: Cumple | GA85: 2 | GF85: No cumple | GG85: 0 | GI85: En el área de la terraza las plantas requieren mantenimiento. La taza de agua para perros esta sucia, manchada, agua sucia. | GL85: Cumple | GM85: 2 | GR85: Cumple | GS85: 2 | GY85: 0 | HE85: 0 | HK85: 0 | HQ85: 0 | HW85: 0 | IC85: 0 | II85: 0 | IO85: 0 | IU85: 0 | JA85: 0 | JG85: 0 | JM85: 0 | JS85: 0 | JY85: 0 | KD85: Atender con prioridad el tema de manejo de producto, vida útil, rotación y volumen de pedidos. Registro de cocción de pollo atender oportunidades y temas de limpieza.
A86: 85 | B86: 45173.847 | C86: 45173.851 | D86: anonymous | F86: 37 | H86: Desamparados | K86: 45173 | N86: Mario | Q86: Angie Valverde | T86: No cumple | U86: 0 | W86: No está en sanitizante | Z86: Cumple | AA86: 2 | AF86: Cumple | AG86: 2 | AM86: 0 | AS86: 0 | AY86: 0 | BE86: 0 | BK86: 0 | BP86: No cumple | BQ86: 0 | BS86: Se encuentra condimentos abiertos y bolsas en el piso | BV86: Cumple | BW86: 2 | CC86: 0 | CH86: No cumple | CI86: 0 | CK86: El contenedor de alcohol esta dañado y no dispensa alcohol | CN86: Cumple | CO86: 2 | CU86: 0 | CZ86: No cumple | DA86: 0 | DC86: Sanitizante muy bajo | DF86: Cumple | DG86: 2 | DL86: Cumple | DM86: 3 | DR86: Cumple | DS86: 3 | DX86: Cumple | DY86: 3 | EE86: 0 | EJ86: Cumple | EK86: 2 | EP86: Cumple | EQ86: 2 | EW86: 0 | FB86: No cumple | FC86: 0 | FE86: Cámaras dañadas por lo tanto hay productos en zona de peligro | FH86: Cumple | FI86: 2 | FN86: Cumple | FO86: 2 | FT86: Cumple | FU86: 2 | FZ86: Cumple | GA86: 2 | GF86: Cumple | GG86: 2 | GL86: Cumple | GM86: 2 | GR86: Cumple | GS86: 2 | GY86: 0 | HE86: 0 | HK86: 0 | HQ86: 0 | HW86: 0 | IC86: 0 | II86: 0 | IO86: 0 | IU86: 0 | JA86: 0 | JG86: 0 | JM86: 0 | JS86: 0 | JY86: 0
A87: 86 | B87: 45174.659 | C87: 45174.669 | D87: anonymous | F87: 32 | H87: Heredia | K87: 45174 | N87: Adan | Q87: Angie Valverde | T87: Cumple | U87: 2 | Z87: Cumple | AA87: 2 | AF87: Cumple | AG87: 2 | AM87: 0 | AS87: 0 | AY87: 0 | BE87: 0 | BK87: 0 | BP87: No cumple | BQ87: 0 | BS87: se encuentra provedor de cocacola sin cubre cabezas | BV87: Cumple | BW87: 2 | CC87: 0 | CH87: Cumple | CI87: 2 | CN87: Cumple | CO87: 2 | CU87: 0 | CZ87: No cumple | DA87: 0 | DC87: los utensilios de postres tienen agua desinfectante con eexcesos de postres | DF87: Cumple | DG87: 2 | DL87: Cumple | DM87: 3 | DR87: No cumple | DS87: 0 | DU87: se encuentra n suciedad y basura alrededores | DX87: Cumple | DY87: 3 | EE87: 0 | EJ87: Cumple | EK87: 2 | EP87: Cumple | EQ87: 2 | EW87: 0 | FB87: No cumple | FC87: 0 | FE87: postres, camaras de mesas frias , congelador y camaras de refrigeracion no cumplen con temperaturas por lo tanto hay productos en zona de peligro. | FH87: Cumple | FI87: 2 | FN87: Cumple | FO87: 2 | FT87: No cumple | FU87: 0 | FW87: se encuentra pollo sin fechar ni ninguna informacion | FZ87: Cumple | GA87: 2 | GF87: No cumple | GG87: 0 | GI87: exceso de agua en el piso , y puede provocar algun accidente | GL87: No cumple | GM87: 0 | GO87: se encuentran ambos baños sucios | GR87: Cumple | GS87: 2 | GY87: 0 | HE87: 0 | HK87: 0 | HQ87: 0 | HW87: 0 | IC87: 0 | II87: 0 | IO87: 0 | IU87: 0 | JA87: 0 | JG87: 0 | JM87: 0 | JS87: 0 | JY87: 0
A88: 87 | B88: 45175.546 | C88: 45175.554 | D88: anonymous | F88: 38 | H88: Guadalupe | K88: 45175 | N88: Martha | Q88: Angie Valverde | T88: Cumple | U88: 2 | Z88: Cumple | AA88: 2 | AF88: Cumple | AG88: 2 | AM88: 0 | AS88: 0 | AY88: 0 | BE88: 0 | BK88: 0 | BP88: Cumple | BQ88: 3 | BV88: Cumple | BW88: 2 | CC88: 0 | CH88: Cumple | CI88: 2 | CN88: No cumple | CO88: 0 | CQ88: se encuentra cloro fuera de bodega de quimicos | CU88: 0 | CZ88: No cumple | DA88: 0 | DC88: no dio sanitizante | DF88: No cumple | DG88: 0 | DI88: baño de colaboradores sucio | DL88: Cumple | DM88: 3 | DR88: Cumple | DS88: 3 | DX88: Cumple | DY88: 3 | EE88: 0 | EJ88: No cumple | EK88: 0 | EM88: se encuentran flan de coco sin fechas | EP88: Cumple | EQ88: 2 | EW88: 0 | FB88: No cumple | FC88: 0 | FE88: camara de postres, mesas frias y congelador no cumple con temperatura por lo tanto los productos estan en zona de peligro | FH88: Cumple | FI88: 2 | FN88: Cumple | FO88: 2 | FT88: Cumple | FU88: 2 | FZ88: Cumple | GA88: 2 | GF88: Cumple | GG88: 2 | GL88: Cumple | GM88: 2 | GR88: Cumple | GS88: 2 | GY88: 0 | HE88: 0 | HK88: 0 | HQ88: 0 | HW88: 0 | IC88: 0 | II88: 0 | IO88: 0 | IU88: 0 | JA88: 0 | JG88: 0 | JM88: 0 | JS88: 0 | JY88: 0
A89: 88 | B89: 45176.493 | C89: 45176.513 | D89: anonymous | F89: 39 | H89: Tibás | K89: 45176 | N89: Jesica | Q89: Angie Valverde | T89: Cumple | U89: 2 | Z89: Cumple | AA89: 2 | AF89: Cumple | AG89: 2 | AI89: Evitar tachones | AM89: 0 | AS89: 0 | AY89: 0 | BE89: 0 | BK89: 0 | BP89: Cumple | BQ89: 3 | BV89: Cumple | BW89: 2 | CC89: 0 | CH89: Cumple | CI89: 2 | CN89: Cumple | CO89: 2 | CU89: 0 | CZ89: Cumple | DA89: 2 | DF89: Cumple | DG89: 2 | DL89: Cumple | DM89: 3 | DR89: No cumple | DS89: 0 | DU89: S e encuentra pepel de galletas y vasos en alrededores, deben hablar con el señor que cuida los carros de recoger esa basura , y no dejarla ahi. | DX89: Cumple | DY89: 3 | EE89: 0 | EJ89: No cumple | EK89: 0 | EM89: postre de queque de chocolate sin fechas | EP89: Cumple | EQ89: 2 | EW89: 0 | FB89: No cumple | FC89: 0 | FE89: varios equipos no cumplen con temperatura por lo tanto los alimentos guardados ahí están en zona de peligro. | FH89: Cumple | FI89: 2 | FN89: Cumple | FO89: 2 | FT89: No cumple | FU89: 0 | FW89: equipo se encuentra afuera encima del lavamanos, además que delantal marillo estaba sucio | FZ89: Cumple | GA89: 2 | GF89: Cumple | GG89: 2 | GL89: Cumple | GM89: 2 | GR89: Cumple | GS89: 2 | GY89: 0 | HE89: 0 | HK89: 0 | HQ89: 0 | HW89: 0 | IC89: 0 | II89: 0 | IO89: 0 | IU89: 0 | JA89: 0 | JG89: 0 | JM89: 0 | JS89: 0 | JY89: 0
A90: 89 | B90: 45176.616 | C90: 45176.629 | D90: anonymous | F90: 40 | H90: San José | K90: 45176 | N90: Diana | Q90: Angie Valverde | T90: Cumple | U90: 2 | Z90: No Cumple | AA90: 0 | AC90: tienen productofrijoles abierto en la parte de abajo de mesa fría, el equipo tiene fuga de agua y los frijoles están tocado el agua. | AF90: Cumple | AG90: 2 | AM90: 0 | AS90: 0 | AY90: 0 | BE90: 0 | BK90: 0 | BP90: Cumple | BQ90: 3 | BV90: No cumple | BW90: 0 | CC90: 0 | CE90: diana porta joyas | CH90: Cumple | CI90: 2 | CN90: Cumple | CO90: 2 | CU90: 0 | CZ90: Cumple | DA90: 2 | DF90: Cumple | DG90: 2 | DL90: Cumple | DM90: 3 | DR90: Cumple | DS90: 3 | DX90: Cumple | DY90: 3 | EE90: 0 | EJ90: No cumple | EK90: 0 | EM90: se encuentra tomate picado sin fechar | EP90: Cumple | EQ90: 2 | EW90: 0 | FB90: No cumple | FC90: 0 | FE90: tienen alimentos en zona de peligro ya que algunos equipos no cumplen | FH90: Cumple | FI90: 2 | FN90: Cumple | FO90: 2 | FT90: Cumple | FU90: 2 | FZ90: Cumple | GA90: 2 | GF90: Cumple | GG90: 2 | GL90: Cumple | GM90: 2 | GR90: Cumple | GS90: 2 | GY90: 0 | HE90: 0 | HK90: 0 | HQ90: 0 | HW90: 0 | IC90: 0 | II90: 0 | IO90: 0 | IU90: 0 | JA90: 0 | JG90: 0 | JM90: 0 | JS90: 0 | JY90: 0
A91: 90 | B91: 45177.791 | C91: 45177.794 | D91: anonymous | F91: 46 | H91: Curridabat | K91: 45177 | N91: dayana | Q91: Angie Valverde | T91: Cumple | U91: 2 | Z91: Cumple | AA91: 2 | AF91: No cumple | AG91: 0 | AI91: libro con tachones | AM91: 0 | AS91: 0 | AY91: 0 | BE91: 0 | BK91: 0 | BP91: Cumple | BQ91: 3 | BV91: Cumple | BW91: 2 | CC91: 0 | CH91: Cumple | CI91: 2 | CN91: Cumple | CO91: 2 | CU91: 0 | CZ91: Cumple | DA91: 2 | DF91: Cumple | DG91: 2 | DL91: Cumple | DM91: 3 | DR91: Cumple | DS91: 3 | DX91: Cumple | DY91: 3 | EE91: 0 | EJ91: Cumple | EK91: 2 | EP91: Cumple | EQ91: 2 | EW91: 0 | FB91: Cumple | FC91: 2 | FH91: Cumple | FI91: 2 | FN91: Cumple | FO91: 2 | FT91: Cumple | FU91: 2 | FZ91: Cumple | GA91: 2 | GF91: Cumple | GG91: 2 | GL91: Cumple | GM91: 2 | GR91: Cumple | GS91: 2 | GY91: 0 | HE91: 0 | HK91: 0 | HQ91: 0 | HW91: 0 | IC91: 0 | II91: 0 | IO91: 0 | IU91: 0 | JA91: 0 | JG91: 0 | JM91: 0 | JS91: 0 | JY91: 0
A92: 91 | B92: 45180.558 | C92: 45180.561 | D92: anonymous | F92: 42 | H92: Terramall | K92: 45180 | N92: Andrea | Q92: Angie Valverde | T92: Cumple | U92: 2 | Z92: Cumple | AA92: 2 | AF92: Cumple | AG92: 2 | AI92: no se debe tener tachones | AM92: 0 | AS92: 0 | AY92: 0 | BE92: 0 | BK92: 0 | BP92: Cumple | BQ92: 3 | BV92: Cumple | BW92: 2 | CC92: 0 | CH92: Cumple | CI92: 2 | CN92: Cumple | CO92: 2 | CU92: 0 | CZ92: Cumple | DA92: 2 | DF92: No cumple | DG92: 0 | DI92: se encuentra pinto de colaboradores en áreas de producción del restaurante | DL92: Cumple | DM92: 3 | DR92: Cumple | DS92: 3 | DX92: Cumple | DY92: 3 | EE92: 0 | EJ92: No cumple | EK92: 0 | EM92: pollo, chile dulce, cebollas moradas, salsas, sin fechar | EP92: Cumple | EQ92: 2 | EW92: 0 | FB92: No cumple | FC92: 0 | FE92: mesa fria y camara de postres no cumplen por lo tanto los alimentos que estan ahi estan en zona de peligro | FH92: Cumple | FI92: 2 | FN92: Cumple | FO92: 2 | FT92: Cumple | FU92: 2 | FZ92: Cumple | GA92: 2 | GF92: Cumple | GG92: 2 | GL92: Cumple | GM92: 2 | GR92: Cumple | GS92: 2 | GY92: 0 | HE92: 0 | HK92: 0 | HQ92: 0 | HW92: 0 | IC92: 0 | II92: 0 | IO92: 0 | IU92: 0 | JA92: 0 | JG92: 0 | JM92: 0 | JS92: 0 | JY92: 0
A93: 92 | B93: 45180.681 | C93: 45180.691 | D93: anonymous | F93: 40 | H93: Multiplaza Curridabat | K93: 45180 | N93: alejandra | Q93: Angie Valverde | T93: Cumple | U93: 2 | Z93: Cumple | AA93: 2 | AF93: Cumple | AG93: 2 | AM93: 0 | AS93: 0 | AY93: 0 | BE93: 0 | BK93: 0 | BP93: Cumple | BQ93: 3 | BV93: No cumple | BW93: 0 | CC93: 0 | CE93: se encuentra a compañera sin uniforme en camara de refrigeracion | CH93: Cumple | CI93: 2 | CN93: Cumple | CO93: 2 | CU93: 0 | CZ93: Cumple | DA93: 2 | DF93: Cumple | DG93: 2 | DL93: Cumple | DM93: 3 | DR93: Cumple | DS93: 3 | DX93: Cumple | DY93: 3 | EE93: 0 | EJ93: No cumple | EK93: 0 | EM93: arroz blanco y pinto sin fechas | EP93: Cumple | EQ93: 2 | EW93: 0 | FB93: No cumple | FC93: 0 | FE93: camara de mesas frias no cumplen por lo tanto los alimentos que estan ahi estan en zona de peligro | FH93: No cumple | FI93: 0 | FK93: ensaladas de mesa fria, al no funcionar la mesa deben de estar en cama de hielo, y se encuentra solo en agua. | FN93: Cumple | FO93: 2 | FT93: Cumple | FU93: 2 | FZ93: Cumple | GA93: 2 | GF93: Cumple | GG93: 2 | GL93: Cumple | GM93: 2 | GR93: Cumple | GS93: 2 | GY93: 0 | HE93: 0 | HK93: 0 | HQ93: 0 | HW93: 0 | IC93: 0 | II93: 0 | IO93: 0 | IU93: 0 | JA93: 0 | JG93: 0 | JM93: 0 | JS93: 0 | JY93: 0
A94: 93 | B94: 45181.575 | C94: 45181.6 | D94: anonymous | F94: 26 | H94: Real Alajuela | K94: 45181 | N94: Patricia Vega | Q94: Nazira Herrera | T94: No cumple | U94: 0 | W94: Termómetros no se encuentran en solución sanitizante | Z94: No Cumple | AA94: 0 | AC94: En el área de cocina se están usando paños naranja (de limpieza profunda). Los aros de elaborar huevo están extremadamente sucios con acumulación de grasa, requieren limpieza profunda. Los dispensadores de salsa con muchos residuos. Debajo de la cocina hay una bandeja con agua y residuos deteriorados. Vajilla almacenada boca arriba. Bolsas de zanahoria rallada abiertas. | AF94: Cumple | AG94: 2 | AM94: 0 | AS94: 0 | AY94: 0 | BE94: 0 | BK94: 0 | BP94: No cumple | BQ94: 0 | BS94: Salsa Rosti colocada en el piso | BV94: No cumple | BW94: 0 | CC94: 0 | CE94: Colaborador de servicio requiere hacerse la barba | CH94: Cumple | CI94: 2 | CN94: Cumple | CO94: 2 | CU94: 0 | CZ94: Cumple | DA94: 2 | DF94: No cumple | DG94: 0 | DI94: Area de lockers desordenada, guantes, cascos, bolsas en el área. Puertas de lockers con mucha oxidación. | DL94: No cumple | DM94: 0 | DO94: Los basureros se encuentran muy sucios, realizar limpieza de tapas y tapas reducidas. | DR94: Cumple | DS94: 3 | DX94: Cumple | DY94: 3 | EE94: 0 | EJ94: Cumple | EK94: 2 | EP94: Cumple | EQ94: 2 | EW94: 0 | FB94: No cumple | FC94: 0 | FE94: Se almacena alimentos en mesa fría del freidor la cual no está funcionando. | FH94: Cumple | FI94: 2 | FN94: Cumple | FO94: 2 | FT94: No cumple | FU94: 0 | FW94: Strips con color no característico. Se solicita descarte. | FZ94: No cumple | GA94: 0 | GC94: Tres leches vencido (7 porciones) con fecha del 10/09. | GF94: Cumple | GG94: 2 | GL94: No cumple | GM94: 0 | GO94: Piso del baño sucio | GR94: Cumple | GS94: 2 | GY94: 0 | HE94: 0 | HK94: 0 | HQ94: 0 | HW94: 0 | IC94: 0 | II94: 0 | IO94: 0 | IU94: 0 | JA94: 0 | JG94: 0 | JM94: 0 | JS94: 0 | JY94: 0 | KD94: Se identifica una diferencia bastante importante de la visita de los meses anteriores a este en temas de limpieza, manejo de producto y procedimientos. No deben mantener productos vencidos, realizar limpieza profunda en equipo y utensilios.
A95: 94 | B95: 45181.599 | C95: 45181.605 | D95: anonymous | F95: 40 | H95: Lincoln | K95: 45181 | N95: stephanie | Q95: Angie Valverde | T95: Cumple | U95: 2 | Z95: No Cumple | AA95: 0 | AC95: se tiene guardado en el mueble de quimicos , los empaques de caja de papas fritas junto a jabones lava platos | AF95: Cumple | AG95: 2 | AM95: 0 | AS95: 0 | AY95: 0 | BE95: 0 | BK95: 0 | BP95: Cumple | BQ95: 3 | BV95: Cumple | BW95: 2 | CC95: 0 | CH95: Cumple | CI95: 2 | CN95: Cumple | CO95: 2 | CU95: 0 | CZ95: No cumple | DA95: 0 | DC95: algunos daban otros no | DF95: Cumple | DG95: 2 | DL95: Cumple | DM95: 3 | DR95: Cumple | DS95: 3 | DX95: Cumple | DY95: 3 | EE95: 0 | EJ95: No cumple | EK95: 0 | EM95: se encuentra aguacate sin tapar , y pollos sin fechas | EP95: Cumple | EQ95: 2 | EW95: 0 | FB95: No cumple | FC95: 0 | FE95: camaras no cumplen con temperatura , por lo tanto los alimentos estan en zona de peligro | FH95: Cumple | FI95: 2 | FN95: Cumple | FO95: 2 | FT95: Cumple | FU95: 2 | FZ95: Cumple | GA95: 2 | GF95: Cumple | GG95: 2 | GL95: Cumple | GM95: 2 | GR95: Cumple | GS95: 2 | GY95: 0 | HE95: 0 | HK95: 0 | HQ95: 0 | HW95: 0 | IC95: 0 | II95: 0 | IO95: 0 | IU95: 0 | JA95: 0 | JG95: 0 | JM95: 0 | JS95: 0 | JY95: 0
A96: 95 | B96: 45182.66 | C96: 45182.679 | D96: anonymous | F96: 44 | H96: Real Cariari | K96: 45182 | N96: Victor | Q96: Angie Valverde | T96: Cumple | U96: 2 | Z96: Cumple | AA96: 2 | AF96: Cumple | AG96: 2 | AM96: 0 | AS96: 0 | AY96: 0 | BE96: 0 | BK96: 0 | BP96: Cumple | BQ96: 3 | BV96: Cumple | BW96: 2 | CC96: 0 | CH96: Cumple | CI96: 2 | CN96: Cumple | CO96: 2 | CU96: 0 | CZ96: Cumple | DA96: 2 | DF96: Cumple | DG96: 2 | DL96: Cumple | DM96: 3 | DR96: Cumple | DS96: 3 | DX96: Cumple | DY96: 3 | EE96: 0 | EJ96: Cumple | EK96: 2 | EP96: No cumple | EQ96: 0 | ES96: cuchillo y delantal de pollo sucio | EW96: 0 | FB96: No cumple | FC96: 0 | FE96: cámaras de refrigeración no cumplen , por lo tanto los alimentos que estan ahi estan en zona de peligro | FH96: Cumple | FI96: 2 | FN96: Cumple | FO96: 2 | FT96: Cumple | FU96: 2 | FZ96: Cumple | GA96: 2 | GF96: Cumple | GG96: 2 | GL96: Cumple | GM96: 2 | GR96: Cumple | GS96: 2 | GY96: 0 | HE96: 0 | HK96: 0 | HQ96: 0 | HW96: 0 | IC96: 0 | II96: 0 | IO96: 0 | IU96: 0 | JA96: 0 | JG96: 0 | JM96: 0 | JS96: 0 | JY96: 0
A97: 96 | B97: 45182.774 | C97: 45182.78 | D97: anonymous | F97: 43 | H97: Real Alajuela | K97: 45182 | N97: Esteban | Q97: Angie Valverde | T97: Cumple | U97: 2 | Z97: Cumple | AA97: 2 | AF97: Cumple | AG97: 2 | AM97: 0 | AS97: 0 | AY97: 0 | BE97: 0 | BK97: 0 | BP97: Cumple | BQ97: 3 | BV97: Cumple | BW97: 2 | CC97: 0 | CH97: Cumple | CI97: 2 | CN97: Cumple | CO97: 2 | CU97: 0 | CZ97: Cumple | DA97: 2 | DF97: Cumple | DG97: 2 | DL97: No cumple | DM97: 0 | DO97: se encuentran basureros sucios | DR97: Cumple | DS97: 3 | DX97: Cumple | DY97: 3 | EE97: 0 | EJ97: Cumple | EK97: 2 | EP97: Cumple | EQ97: 2 | EW97: 0 | FB97: No cumple | FC97: 0 | FE97: camaras no cumplen con temperatura por lo tanto hay productos en zona de peligro | FH97: Cumple | FI97: 2 | FN97: Cumple | FO97: 2 | FT97: Cumple | FU97: 2 | FZ97: Cumple | GA97: 2 | GF97: Cumple | GG97: 2 | GL97: Cumple | GM97: 2 | GR97: Cumple | GS97: 2 | GY97: 0 | HE97: 0 | HK97: 0 | HQ97: 0 | HW97: 0 | IC97: 0 | II97: 0 | IO97: 0 | IU97: 0 | JA97: 0 | JG97: 0 | JM97: 0 | JS97: 0 | JY97: 0
A98: 97 | B98: 45183.634 | C98: 45183.638 | D98: anonymous | F98: 36 | H98: Guachipelín | K98: 45183 | N98: Stephanie | Q98: Angie Valverde | T98: Cumple | U98: 2 | Z98: No Cumple | AA98: 0 | AC98: Cámara de pollo crudo tenían rostinetas | AF98: Cumple | AG98: 2 | AM98: 0 | AS98: 0 | AY98: 0 | BE98: 0 | BK98: 0 | BP98: No cumple | BQ98: 0 | BS98: Cocacolas y refrescos en el piso | BV98: Cumple | BW98: 2 | CC98: 0 | CH98: Cumple | CI98: 2 | CN98: Cumple | CO98: 2 | CU98: 0 | CZ98: Cumple | DA98: 2 | DF98: Cumple | DG98: 2 | DL98: No cumple | DM98: 0 | DO98: Basureros sucios | DR98: Cumple | DS98: 3 | DX98: Cumple | DY98: 3 | EE98: 0 | EJ98: No cumple | EK98: 0 | EM98: Puré sin fechar | EP98: Cumple | EQ98: 2 | EW98: 0 | FB98: No cumple | FC98: 0 | FE98: Mesas frías no cumplen por lo tanto hay alimentos en zona de peligro | FH98: Cumple | FI98: 2 | FN98: Cumple | FO98: 2 | FT98: Cumple | FU98: 2 | FZ98: Cumple | GA98: 2 | GF98: Cumple | GG98: 2 | GL98: Cumple | GM98: 2 | GR98: Cumple | GS98: 2 | GY98: 0 | HE98: 0 | HK98: 0 | HQ98: 0 | HW98: 0 | IC98: 0 | II98: 0 | IO98: 0 | IU98: 0 | JA98: 0 | JG98: 0 | JM98: 0 | JS98: 0 | JY98: 0
A99: 98 | B99: 45185.809 | C99: 45185.817 | D99: anonymous | F99: 36 | H99: Pinares | K99: 45185 | N99: Marco | Q99: Angie Valverde | T99: Cumple | U99: 2 | Z99: Cumple | AA99: 2 | AF99: No cumple | AG99: 0 | AI99: registro lleno de tachones | AM99: 0 | AS99: 0 | AY99: 0 | BE99: 0 | BK99: 0 | BP99: No cumple | BQ99: 0 | BS99: bodega de almacenamiento de alimentos esta sucia y con sobrante de caramelo en el piso, deben tenerla limpia para evitar que las plagas tengan alimento | BV99: Cumple | BW99: 2 | CC99: 0 | CH99: Cumple | CI99: 2 | CN99: No cumple | CO99: 0 | CU99: 0 | CZ99: Cumple | DA99: 2 | DF99: Cumple | DG99: 2 | DL99: Cumple | DM99: 3 | DR99: No cumple | DS99: 0 | DU99: parte de atrás del restaurante tiene excesos de comida. | DX99: Cumple | DY99: 3 | EE99: 0 | EJ99: Cumple | EK99: 2 | EP99: Cumple | EQ99: 2 | EW99: 0 | FB99: No cumple | FC99: 0 | FE99: mesas frias y congelador no cumplen por lo tanto tienen alimentos en zona de peligro | FH99: Cumple | FI99: 2 | FN99: Cumple | FO99: 2 | FT99: Cumple | FU99: 2 | FZ99: Cumple | GA99: 2 | GF99: Cumple | GG99: 2 | GL99: Cumple | GM99: 2 | GR99: Cumple | GS99: 2 | GY99: 0 | HE99: 0 | HK99: 0 | HQ99: 0 | HW99: 0 | IC99: 0 | II99: 0 | IO99: 0 | IU99: 0 | JA99: 0 | JG99: 0 | JM99: 0 | JS99: 0 | JY99: 0
A100: 99 | B100: 45187.608 | C100: 45187.628 | D100: anonymous | F100: 40 | H100: Santa Ana | K100: 45187 | N100: Maria | Q100: Angie Valverde | T100: Cumple | U100: 2 | Z100: Cumple | AA100: 2 | AF100: Cumple | AG100: 2 | AI100: DEBE DE ESTAR LIBRE DE TACHONES | AM100: 0 | AS100: 0 | AY100: 0 | BE100: 0 | BK100: 0 | BP100: Cumple | BQ100: 3 | BV100: Cumple | BW100: 2 | CC100: 0 | CH100: No cumple | CI100: 0 | CK100: TIENEN EL DISPENSADOR DEL JABON SUELTO | CN100: Cumple | CO100: 2 | CU100: 0 | CZ100: Cumple | DA100: 2 | DF100: Cumple | DG100: 2 | DL100: Cumple | DM100: 3 | DR100: Cumple | DS100: 3 | DX100: Cumple | DY100: 3 | EE100: 0 | EJ100: No cumple | EK100: 0 | EM100: SE ENCUENTRA REPOLLO, SIN FECHAR, TE SIN FECHAR, GUACAMOLE SIN TAPAR | EP100: Cumple | EQ100: 2 | EW100: 0 | FB100: No cumple | FC100: 0 | FE100: HAY ALIMENTOS EN ZONA DE PELIGRO PORQUE ALGUNAS CAMARAS NO CUMPLEN CON TEMPERATURA | FH100: Cumple | FI100: 2 | FN100: Cumple | FO100: 2 | FT100: Cumple | FU100: 2 | FZ100: Cumple | GA100: 2 | GF100: Cumple | GG100: 2 | GL100: Cumple | GM100: 2 | GR100: No cumple | GS100: 0 | GY100: 0 | HE100: 0 | HK100: 0 | HQ100: 0 | HW100: 0 | IC100: 0 | II100: 0 | IO100: 0 | IU100: 0 | JA100: 0 | JG100: 0 | JM100: 0 | JS100: 0 | JY100: 0
...
